Workbook
Name MF_LatestAUMCol: MATCH("Net Assets Under Management as on March 31, 2026 (INR in crore)",'AMFI-Mar''25 to Mar''26'!$3:$3,0)
Name MF_NetFlowCol: MATCH("Net Inflow (+ve)/Outflow (-ve) for the month of March 2026 (INR in crore)",'AMFI-Mar''25 to Mar''26'!$3:$3,0)
Name MF_RedemptionCol: MATCH("Repurchase/Redemption for the month of March 2026 (INR in crore)",'AMFI-Mar''25 to Mar''26'!$3:$3,0)
Name MF_SalesCol: MATCH("Funds Mobilized for the month of March 2026 (INR in crore)",'AMFI-Mar''25 to Mar''26'!$3:$3,0)

Sheet AMFI-SIP
A1: SIP Contribution
A2: Month-wise SIP contribution collected from FY 2016-17 onwards are mentioned below:
A3: Month | C3: SIP Contribution ₹ Crore
A4: Fig in cr | B4: FY 2026-27 | C4: FY 2025-26 | D4: FY 2024-25 | E4: FY 2023-24 | F4: FY 2022-23 | G4: FY 2021-22 | H4: FY 2020-21 | I4: FY 2019-20 | J4: FY 2018-19 | K4: FY 2017-18 | L4: FY 2016-17
A5: Total During FY | B5: =SUBTOTAL(9,B6:B17) | C5: =SUBTOTAL(9,C6:C17) | D5: =SUBTOTAL(9,D6:D17) | E5: =SUBTOTAL(9,E6:E17) | F5: =SUBTOTAL(9,F6:F17) | G5: =SUBTOTAL(9,G6:G17) | H5: =SUBTOTAL(9,H6:H17) | I5: =SUBTOTAL(9,I6:I17) | ... L5: =SUBTOTAL(9,L6:L17)
A6: March | C6: 32087 | D6: 25926 | E6: 19271 | F6: 14276 | G6: 12328 | H6: 9182 | I6: 8641 | J6: 8055 | K6: 7119 | L6: 4335
A7: February | C7: 29845 | D7: 25999 | E7: 19187 | F7: 13686 | G7: 11438 | H7: 7528 | I7: 8513 | J7: 8095 | K7: 6425 | L7: 4050
A8: January | C8: 31002 | D8: 26400 | E8: 18838 | F8: 13856 | G8: 11517 | H8: 8023 | I8: 8532 | J8: 8064 | K8: 6644 | L8: 4095
A9: December | C9: 31002 | D9: 26459 | E9: 17610 | F9: 13573 | G9: 11305 | H9: 8418 | I9: 8518 | J9: 8022 | K9: 6222 | L9: 3973
A10: November | C10: 29445 | D10: 25320 | E10: 17073 | F10: 13306 | G10: 11005 | H10: 7302 | I10: 8273 | J10: 7985 | K10: 5893 | L10: 3884
A11: October | C11: 29529 | D11: 25323 | E11: 16928 | F11: 13041 | G11: 10519 | H11: 7800 | I11: 8246 | J11: 7985 | K11: 5621 | L11: 3434
A12: September | C12: 29361 | D12: 24509 | E12: 16042 | F12: 12976 | G12: 10351 | H12: 7788 | I12: 8263 | J12: 7727 | K12: 5516 | L12: 3698
A13: August | C13: 28265 | D13: 23547 | E13: 15814 | F13: 12693 | G13: 9923 | H13: 7792 | I13: 8231 | J13: 7658 | K13: 5206 | L13: 3497
A14: July | C14: 28464 | D14: 23332 | E14: 15245 | F14: 12140 | G14: 9609 | H14: 7831 | I14: 8324 | J14: 7554 | K14: 4947 | L14: 3334
A15: Jun | C15: 27269 | D15: 21262 | E15: 14734 | F15: 12276 | G15: 9156 | H15: 7917 | I15: 8122 | J15: 7554 | K15: 4744 | L15: 3310
A16: May | C16: 26688 | D16: 20904 | E16: 14749 | F16: 12286 | G16: 8819 | H16: 8123 | I16: 8183 | J16: 7304 | K16: 4584 | L16: 3189
A17: April | B17: 31115 | C17: 26632 | D17: 20371 | E17: 13728 | F17: 11863 | G17: 8596 | H17: 8376 | I17: 8238 | J17: 6690 | K17: 4269 | L17: 3122
A19: SIP Count -
A20: - | B20: (Lakh) | C20: (Lakh) | D20: (Lakh) | E20: (Lakh) | F20: (Cr) | G20: (Cr)
A21: Month | B21: Total No. of outstanding SIP Accounts | C21: No. of New SIPs registered | D21: No. of SIPs discontinued*/tenure completed | E21: No. of Contributing SIP accounts | F21: SIP Contribution ₹ crore | G21: SIP AUM ₹ crore
A22: 46113 | B22: 1044.26 | C22: 50.71 | D22: 51.29 | E22: 964.91 | F22: 31115 | G22: 1685126
A24: Apr 25 – Mar 26 | B24: =B25 | C24: =SUM(C25:C36) | D24: =SUM(D25:D36) | E24: =E25 | F24: =SUM(F25:F36) | G24: =G25
A25: 46082 | B25: 1044.84 | C25: 52.82 | D25: 53.38 | E25: 971.86 | F25: 32087 | G25: 1510943
A26: 46054 | B26: 1045.4 | C26: 65.72 | D26: 49.7 | E26: 944.48 | F26: 29845 | G26: 1664085
A27: 46023 | B27: 1029.38 | C27: 74.11 | D27: 55.46 | E27: 992.19 | F27: 31002 | G27: 1636082
A28: 45992 | B28: 1010.73 | C28: 60.46 | D28: 51.57 | E28: 979 | F28: 31002 | G28: 1663369
A29: 45962 | B29: 1001.84 | C29: 57.14 | D29: 43.18 | E29: 942.52 | F29: 29445 | G29: 1652665
A30: 45931 | B30: 987.88 | C30: 60.25 | D30: 45.1 | E30: 945.2 | F30: 29529 | G30: 1625305
A31: 45901 | B31: 972.74 | C31: 57.73 | D31: 44.03 | E31: 925.21 | F31: 29361 | G31: 1552303
A32: 45870 | B32: 959.04 | C32: 55.23 | D32: 41.15 | E32: 898.7 | F32: 28265 | G32: 1518368
A33: 45839 | B33: 944.97 | C33: 68.69 | D33: 43.04 | E33: 911.18 | F33: 28464 | G33: 1519456
A34: 45809 | B34: 919.32 | C34: 61.91 | D34: 48.16 | E34: 864.7 | F34: 27269 | G34: 1530574
A35: 45778 | B35: 905.57 | C35: 59.15 | D35: 42.66 | E35: 856 | F35: 26688 | G35: 1461360
A36: 45748 | B36: 889.08 | C36: 46.01 | D36: 162.32 | E36: 838.25 | F36: 26632 | G36: 1389655
A37: Apr 24 – Mar 25 | B37: 1005.39 | C37: 679.85 | D37: 514.17 | E37: 811.16 | F37: 289352 | G37: 1335188
A39: Apr 23 – Mar 24 | B39: 839.71 | C39: 428.09 | D39: 224.37 | E39: - | F39: 199219 | G39: 1071666
A41: * As per SEBI guidelines, the SIPs where
A42: - 3 consecutive instalments with respect to daily, weekly, fortnightly, and monthly intervals and
A43: - 2 consecutive instalments with respect to others are failed, are treated as ceased/discontinued.
A44: # Includes the past/legacy data on account of above reason, revised on 14th May 2025.

Sheet AMFI-Mar'25 to Mar'26
P1: - | Z1: - | AJ1: - | AT1: - | BD1: - | BN1: - | BX1: - | CH1: - | CR1: - | DB1: - | DL1: - | DO1: - | EB1: - | EE1: - | EI1: - | ES1: - | EV1: -
A2: - | B2: - | C2: - | D2: - | E2: - | G2: Mar'25 | P2: - | Q2: Apr'25 | Z2: - | AA2: May'25 | AJ2: - | AK2: Jun'25 | AT2: - | AU2: Jul'25 | BD2: - | BE2: Aug'25 | BN2: - | BO2: Sep'25 | BX2: - | BY2: Oct'25 | CH2: - | CI2: Nov'25 | CR2: - | CS2: Dec'25 | DB2: - | DC2: Jan'25 | DL2: - | DM2: Apr'25 to Jan'26 | DO2: - | DP2: - | DQ2: - | DR2: - | DS2: Feb'26 | EB2: - | EC2: Apr'25 to Feb'26 | EE2: - | EF2: - | EG2: - | EH2: - | EI2: - | EJ2: Mar'26 | ES2: - | ET2: Apr'25 to Mar'26 | EV2: - | EW2: - | EX2: - | EY2: -
A3: Scheme Name | B3: AMFI-Asset Type | C3: AMFI-Open ended Schemes/Closed ended Schemes | D3: DEBT / EQUITY | E3: SALES_PROD_MIS | F3: Fund Type | G3: No. of Schemes as on March 31, 2025 | H3: No. of Folios as on March 31, 2025 | I3: Funds Mobilized for the month of March 2025 (INR in crore) | J3: Repurchase/ Redemption for the month of March 2025 (INR in crore) | K3: Net Inflow (+ve)/Outflow (-ve) for the month of March 2025 (INR in crore) | L3: Net Assets Under Management as on March 31, 2025 (INR in crore) | M3: Average Net Assets Under Management for the month March 2025 (INR in crore) | N3: No. of segregated portfolios created as on March 31, 2025 | O3: Net Assets Under Management in segregated portfolio as on March 31, 2025 (INR in crore) | P3: - | Q3: No. of Schemes as on April 30, 2025 | R3: No. of Folios as on April 30, 2025 | S3: Funds Mobilized for the month of April 2025 (INR in crore) | T3: Repurchase/ Redemption for the month of April 2025 (INR in crore) | U3: Net Inflow (+ve)/Outflow (-ve) for the month of April 2025 (INR in crore) | V3: Net Assets Under Management as on April 30, 2025 (INR in crore) | W3: Average Net Assets Under Management for the month April 2025 (INR in crore) | X3: No. of segregated portfolios created as on April 30, 2025 | Y3: Net Assets Under Management in segregated portfolio as on April 30, 2025 (INR in crore) | Z3: - | AA3: No. of Schemes as on May 31, 2025 | AB3: No. of Folios as on May 31, 2025 | AC3: Funds Mobilized for the month of May 2025 (INR in crore) | AD3: Repurchase/ Redemption for the month of May 2025 (INR in crore) | AE3: Net Inflow (+ve)/Outflow (-ve) for the month of May 2025 (INR in crore) | AF3: Net Assets Under Management as on May 31, 2025 (INR in crore) | AG3: Average Net Assets Under Management for the month May 2025 (INR in crore) | AH3: No. of segregated portfolios created as on May 31, 2025 | AI3: Net Assets Under Management in segregated portfolio as on May 31, 2025 (INR in crore) | AJ3: - | AK3: No. of Schemes as on June 30, 2025 | AL3: No. of Folios as on June 30, 2025 | AM3: Funds Mobilized for the month of June 2025 (INR in crore) | AN3: Repurchase/ Redemption for the month of June 2025 (INR in crore) | AO3: Net Inflow (+ve)/Outflow (-ve) for the month of June 2025 (INR in crore) | AP3: Net Assets Under Management as on June 30, 2025 (INR in crore) | AQ3: Average Net Assets Under Management for the month June 2025 (INR in crore) | AR3: No. of segregated portfolios created as on June 30, 2025 | AS3: Net Assets Under Management in segregated portfolio as on June 30, 2025 (INR in crore) | AT3: - | AU3: No. of Schemes as on July 31, 2025 | AV3: No. of Folios as on July 31, 2025 | AW3: Funds Mobilized for the month of July 2025 (INR in crore) | AX3: Repurchase/Redemption for the month of July 2025 (INR in crore) | AY3: Net Inflow (+ve)/Outflow (-ve) for the month of July 2025 (INR in crore) | AZ3: Net Assets Under Management as on July 31, 2025 (INR in crore) | BA3: Average Net Assets Under Management for the month July 2025 (INR in crore) | BB3: No. of segregated portfolios created as on July 31, 2025 | BC3: Net Assets Under Management in segregated portfolio as on July 31, 2025 (INR in crore) | BD3: - | BE3: No. of Schemes as on August 31, 2025 | BF3: No. of Folios as on August 31, 2025 | BG3: Funds Mobilized for the month of August 2025 (INR in crore) | BH3: Repurchase/Redemption for the month of August 2025 (INR in crore) | BI3: Net Inflow (+ve)/Outflow (-ve) for the month of August 2025 (INR in crore) | BJ3: Net Assets Under Management as on August 31, 2025 (INR in crore) | BK3: Average Net Assets Under Management for the month August 2025 (INR in crore) | BL3: No. of segregated portfolios created as on August 31, 2025 | BM3: Net Assets Under Management in segregated portfolio as on August 31, 2025 (INR in crore) | BN3: - | BO3: No. of Schemes as on September 30, 2025 | BP3: No. of Folios as on September 30, 2025 | BQ3: Funds Mobilized for the month of September 2025 (INR in crore) | BR3: Repurchase/Redemption for the month of September 2025 (INR in crore) | BS3: Net Inflow (+ve)/Outflow (-ve) for the month of September 2025 (INR in crore) | BT3: Net Assets Under Management as on September 30, 2025 (INR in crore) | BU3: Average Net Assets Under Management for the month September 2025 (INR in crore) | BV3: No. of segregated portfolios created as on September 30, 2025 | BW3: Net Assets Under Management in segregated portfolio as on September 30, 2025 (INR in crore) | BX3: - | BY3: No. of Schemes as on October 31, 2025 | BZ3: No. of Folios as on October 31, 2025 | CA3: Funds Mobilized for the month of October 2025 (INR in crore) | CB3: Repurchase/Redemption for the month of October 2025 (INR in crore) | CC3: Net Inflow (+ve)/Outflow (-ve) for the month of October 2025 (INR in crore) | CD3: Net Assets Under Management as on October 31, 2025 (INR in crore) | CE3: Average Net Assets Under Management for the month October 2025 (INR in crore) | CF3: No. of segregated portfolios created as on October 31, 2025 | CG3: Net Assets Under Management in segregated portfolio as on October 31, 2025 (INR in crore) | CH3: - | CI3: No. of Schemes as on November 30, 2025 | CJ3: No. of Folios as on November 30, 2025 | CK3: Funds Mobilized for the month of November 2025 (INR in crore) | CL3: Repurchase/Redemption for the month of November 2025 (INR in crore) | CM3: Net Inflow (+ve)/Outflow (-ve) for the month of November 2025 (INR in crore) | CN3: Net Assets Under Management as on November 30, 2025 (INR in crore) | CO3: Average Net Assets Under Management for the month November 2025 (INR in crore) | CP3: No. of segregated portfolios created as on November 30, 2025 | CQ3: Net Assets Under Management in segregated portfolio as on November 30, 2025 (INR in crore) | CR3: - | CS3: No. of Schemes as on December 31, 2025 | CT3: No. of Folios as on December 31, 2025 | CU3: Funds Mobilized for the month of December 2025 (INR in crore) | CV3: Repurchase/Redemption for the month of December 2025 (INR in crore) | CW3: Net Inflow (+ve)/Outflow (-ve) for the month of December 2025 (INR in crore) | CX3: Net Assets Under Management as on December 31, 2025 (INR in crore) | CY3: Average Net Assets Under Management for the month December 2025 (INR in crore) | CZ3: No. of segregated portfolios created as on December 31, 2025 | DA3: Net Assets Under Management in segregated portfolio as on December 31, 2025 (INR in crore) | DB3: - | DC3: No. of Schemes as on January 31, 2026 | DD3: No. of Folios as on January 31, 2026 | DE3: Funds Mobilized for the month of January 2026 (INR in crore) | DF3: Repurchase/Redemption for the month of January 2026 (INR in crore) | DG3: Net Inflow (+ve)/Outflow (-ve) for the month of January 2026 (INR in crore) | DH3: Net Assets Under Management as on January 31, 2026 (INR in crore) | DI3: Average Net Assets Under Management for the month January 2026 (INR in crore) | DJ3: No. of segregated portfolios created as on January 31, 2026 | DK3: Net Assets Under Management in segregated portfolio as on January 31, 2026 (INR in crore) | DL3: - | DM3: Funds Mobilized (INR in crore) | DN3: Net Inflow (+ve)/Outflow (-ve) (INR in crore) | DO3: - | DP3: GS - Growth-(Dec'25 Vs Jan'26) | DQ3: NS - Growth-(Dec'25 Vs Jan'26) | DR3: AUM - Growth-(Dec'25 Vs Jan'26) | DS3: No. of Schemes as on February 28, 2026 | DT3: No. of Folios as on February 28, 2026 | DU3: Funds Mobilized for the month of February 2026 (INR in crore) | DV3: Repurchase/Redemption for the month of February 2026 (INR in crore) | DW3: Net Inflow (+ve)/Outflow (-ve) for the month of February 2026 (INR in crore) | DX3: Net Assets Under Management as on February 28, 2026 (INR in crore) | DY3: Average Net Assets Under Management for the month February 2026 (INR in crore) | DZ3: No. of segregated portfolios created as on February 28, 2026 | EA3: Net Assets Under Management in segregated portfolio as on February 28, 2026 (INR in crore) | EB3: - | EC3: Funds Mobilized for the month of January 2026 (INR in crore) | ED3: Net Inflow (+ve)/Outflow (-ve) for the month of January 2026 (INR in crore) | EE3: - | EF3: GS - Growth-(Jan'26 Vs Feb'26) | EG3: NS - Growth-(Jan'26 Vs Feb'26) | EH3: AUM - Growth-(Jan'26 Vs Feb'26) | EI3: - | EJ3: No. of Schemes as on March 31, 2026 | EK3: No. of Folios as on March 31, 2026 | EL3: Funds Mobilized for the month of March 2026 (INR in crore) | EM3: Repurchase/Redemption for the month of March 2026 (INR in crore) | EN3: Net Inflow (+ve)/Outflow (-ve) for the month of March 2026 (INR in crore) | EO3: Net Assets Under Management as on March 31, 2026 (INR in crore) | EP3: Average Net Assets Under Management for the month March 2026 (INR in crore) | EQ3: No. of segregated portfolios created as on March 31, 2026 | ER3: Net Assets Under Management in segregated portfolio as on March 31, 2026 (INR in crore) | ES3: - | ET3: Funds Mobilized for the month of March 2026 (INR in crore) | EU3: Net Inflow (+ve)/Outflow (-ve) for the month of March 2026 (INR in crore) | EV3: - | EW3: GS - Growth-(Feb'26 Vs Mar'26) | EX3: NS - Growth-(Feb'26 Vs Mar'26) | EY3: AUM - Growth-(Feb'26 Vs Mar'26)
A4: Active Equity (incl Hybrid)
A5: Multi Asset Allocation Fund | B5: Hybrid Schemes | C5: Open ended Schemes | D5: Equity | E5: Equity-Hybrid Schemes | F5: Active Equity (incl Hybrid) | K5: =IF(OR(I5="",J5=""),"",I5-J5) | L5: 107094.5 | M5: 113587.79 | P5: - | Q5: 28 | R5: 3121223 | S5: 3583.9126 | T5: 1478.1664 | U5: 2105.7462 | V5: 113009.41 | W5: 118248.56 | X5: 0 | Y5: 0 | Z5: - | AA5: 29 | AB5: 3226116 | AC5: 4508.2554 | AD5: 1581.4557 | AE5: 2926.7997 | AF5: 118153.73 | AG5: 123714.44 | AH5: 0 | AI5: 0 | AJ5: - | AK5: 29 | AL5: 3307121 | AM5: 4514.2515 | AN5: 1304.2772 | AO5: 3209.9742 | AP5: 123584.5 | AQ5: 130104.79 | AR5: 0 | AS5: 0 | AT5: - | AU5: 29 | AV5: 3459194 | AW5: 7480.7755 | AX5: 1283.5572 | AY5: 6197.2183 | AZ5: 128426.74 | BA5: 135201 | BB5: 0 | BC5: 0 | BD5: - | BE5: 30 | BF5: 3560534 | BG5: 4633.0019 | BH5: 1105.0929 | BI5: 3527.909 | BJ5: 132103.62 | BK5: 139994.94 | BL5: 0 | BM5: 0 | BN5: - | BO5: 31 | BP5: 3704172 | BQ5: 6608.0378 | BR5: 1625.8258 | BS5: 4982.212 | BT5: 140416.72 | BU5: 147700.94 | BV5: 0 | BW5: 0 | BX5: - | BY5: 31 | BZ5: 3861455 | CA5: 6706.8455 | CB5: 1362.66 | CC5: 5344.1855 | CD5: 151071.71 | CE5: 157277.39 | CF5: 0 | CG5: 0 | CH5: - | CI5: 32 | CJ5: 4016236 | CK5: 6655.4878 | CL5: 1340.6296 | CM5: 5314.8582 | CN5: 157266.67 | CO5: 164438.98 | CP5: 0 | CQ5: 0 | CR5: - | CS5: 33 | CT5: 4249832 | CU5: 8927.2308 | CV5: 1501.2522 | CW5: 7425.9787 | CX5: 164730.83 | CY5: 173823.59 | CZ5: 0 | DA5: 0 | DB5: - | DC5: 33 | DD5: 4592478 | DE5: 12139.134 | DF5: 1653.7527 | DG5: 10485.381 | DH5: 174660.32 | DI5: 185088.95 | DJ5: 0 | DK5: 0 | DL5: - | DM5: =S5+AC5+AM5+AW5+BG5+BQ5+CA5+CK5+CU5+DE5 | DN5: =U5+AE5+AO5+AY5+BI5+BS5+CC5+CM5+CW5+DG5 | DO5: - | DP5: =IFERROR((DE5-CU5)/CU5,"-") | DQ5: =IFERROR((DG5-CW5)/CW5,"-") | DR5: =IFERROR((DH5-CX5)/CX5,"-") | DS5: 33 | DT5: 4908663 | DU5: 10151.087 | DV5: 1674.8311 | DW5: 8476.2558 | DX5: 183245.91 | DY5: 196730.61 | DZ5: 0 | EA5: 0 | EB5: - | EC5: =S5+AC5+AM5+AW5+BG5+BQ5+CA5+CK5+CU5+DE5+DU5 | ED5: =U5+AE5+AO5+AY5+BI5+BS5+CC5+CM5+CW5+DG5+DW5 | EE5: - | EF5: =IFERROR((DU5-DE5)/DE5,"-") | EG5: =IFERROR((DW5-DG5)/DG5,"-") | EH5: =IFERROR((DX5-DH5)/DH5,"-") | EI5: - | EJ5: 34 | EK5: 5160754 | EL5: 8270.4619 | EM5: 3057.7299 | EN5: 5212.732 | EO5: 173762.06 | EP5: 195113.53 | EQ5: 0 | ER5: 0 | ES5: - | ET5: =S5+AC5+AM5+AW5+BG5+BQ5+CA5+CK5+CU5+DE5+DU5+EL5 | EU5: =U5+AE5+AO5+AY5+BI5+BS5+CC5+CM5+CW5+DG5+DW5+EN5 | EV5: - | EW5: =IFERROR((EL5-DU5)/DU5,"-") | EX5: =IFERROR((EN5-DW5)/DW5,"-") | EY5: =IFERROR((EO5-DX5)/DX5,"-")
A6: Flexi Cap Fund | B6: Growth/Equity Oriented Schemes | C6: Open ended Schemes | D6: Equity | E6: Equity | F6: Active Equity (incl Hybrid) | K6: =IF(OR(I6="",J6=""),"",I6-J6) | L6: 435508.97 | M6: 422113.98 | P6: - | Q6: 39 | R6: 18209314 | S6: 10026.303 | T6: 4484.5884 | U6: 5541.7141 | V6: 454667.91 | W6: 440289.91 | X6: 0 | Y6: 0 | Z6: - | AA6: 39 | AB6: 18510887 | AC6: 9241.5932 | AD6: 5400.2711 | AE6: 3841.3221 | AF6: 471974.48 | AG6: 464765.76 | AH6: 0 | AI6: 0 | AJ6: - | AK6: 40 | AL6: 18938944 | AM6: 9525.6885 | AN6: 3792.5289 | AO6: 5733.1596 | AP6: 494278.83 | AQ6: 482665.23 | AR6: 0 | AS6: 0 | AT6: - | AU6: 40 | AV6: 19448661 | AW6: 11378.229 | AX6: 3723.9019 | AY6: 7654.3271 | AZ6: 493229.47 | BA6: 494656.52 | BB6: 0 | BC6: 0 | BD6: - | BE6: 41 | BF6: 19838017 | BG6: 11664.641 | BH6: 3985.2393 | BI6: 7679.4018 | BJ6: 495445.68 | BK6: 497155.76 | BL6: 0 | BM6: 0 | BN6: - | BO6: 41 | BP6: 20206005 | BQ6: 11354.999 | BR6: 4325.7373 | BS6: 7029.2622 | BT6: 507916.03 | BU6: 512367.92 | BV6: 0 | BW6: 0 | BX6: - | BY6: 43 | BZ6: 21182395 | CA6: 12968.501 | CB6: 4039.7958 | CC6: 8928.705 | CD6: 533756.17 | CE6: 527143.34 | CF6: 0 | CG6: 0 | CH6: - | CI6: 43 | CJ6: 21635346 | CK6: 11822.383 | CL6: 3687.3705 | CM6: 8135.0125 | CN6: 545189.58 | CO6: 539124.74 | CP6: 0 | CQ6: 0 | CR6: - | CS6: 44 | CT6: 22050009 | CU6: 14910.65 | CV6: 4891.3811 | CW6: 10019.269 | CX6: 551962.17 | CY6: 546559.61 | CZ6: 0 | DA6: 0 | DB6: - | DC6: 44 | DD6: 22515391 | DE6: 12827.395 | DF6: 5155.0348 | DG6: 7672.36 | DH6: 546946.61 | DI6: 549566.71 | DJ6: 0 | DK6: 0 | DL6: - | DM6: =S6+AC6+AM6+AW6+BG6+BQ6+CA6+CK6+CU6+DE6 | DN6: =U6+AE6+AO6+AY6+BI6+BS6+CC6+CM6+CW6+DG6 | DO6: - | DP6: =IFERROR((DE6-CU6)/CU6,"-") | DQ6: =IFERROR((DG6-CW6)/CW6,"-") | DR6: =IFERROR((DH6-CX6)/CX6,"-") | DS6: 44 | DT6: 22945488 | DU6: 11044.84 | DV6: 4120.1855 | DW6: 6924.6543 | DX6: 553187.14 | DY6: 557484.96 | DZ6: 0 | EA6: 0 | EB6: - | EC6: =S6+AC6+AM6+AW6+BG6+BQ6+CA6+CK6+CU6+DE6+DU6 | ED6: =U6+AE6+AO6+AY6+BI6+BS6+CC6+CM6+CW6+DG6+DW6 | EE6: - | EF6: =IFERROR((DU6-DE6)/DE6,"-") | EG6: =IFERROR((DW6-DG6)/DG6,"-") | EH6: =IFERROR((DX6-DH6)/DH6,"-") | EI6: - | EJ6: 45 | EK6: 23379152 | EL6: 16147.687 | EM6: 6093.5668 | EN6: 10054.12 | EO6: 505265.45 | EP6: 528059.76 | EQ6: 0 | ER6: 0 | ES6: - | ET6: =S6+AC6+AM6+AW6+BG6+BQ6+CA6+CK6+CU6+DE6+DU6+EL6 | EU6: =U6+AE6+AO6+AY6+BI6+BS6+CC6+CM6+CW6+DG6+DW6+EN6 | EV6: - | EW6: =IFERROR((EL6-DU6)/DU6,"-") | EX6: =IFERROR((EN6-DW6)/DW6,"-") | EY6: =IFERROR((EO6-DX6)/DX6,"-")
A7: Mid Cap Fund | B7: Growth/Equity Oriented Schemes | C7: Open ended Schemes | D7: Equity | E7: Equity | F7: Active Equity (incl Hybrid) | K7: =IF(OR(I7="",J7=""),"",I7-J7) | L7: 368992.08 | M7: 356671.84 | P7: - | Q7: 30 | R7: 21310959 | S7: 6748.9694 | T7: 3434.9939 | U7: 3313.9755 | V7: 383083.71 | W7: 370097.35 | X7: 0 | Y7: 0 | Z7: - | AA7: 30 | AB7: 21538476 | AC7: 6812.2399 | AD7: 4003.5601 | AE7: 2808.6797 | AF7: 408092.68 | AG7: 395846.07 | AH7: 0 | AI7: 0 | AJ7: - | AK7: 30 | AL7: 22005565 | AM7: 7539.5287 | AN7: 3785.1093 | AO7: 3754.4193 | AP7: 431699.79 | AQ7: 419404.14 | AR7: 0 | AS7: 0 | AT7: - | AU7: 30 | AV7: 22564162 | AW7: 8711.4567 | AX7: 3528.9665 | AY7: 5182.4902 | AZ7: 428582.5 | BA7: 431587.59 | BB7: 0 | BC7: 0 | BD7: - | BE7: 31 | BF7: 23000768 | BG7: 8288.3147 | BH7: 2957.6902 | BI7: 5330.6245 | BJ7: 426623.48 | BK7: 428719.14 | BL7: 0 | BM7: 0 | BN7: - | BO7: 31 | BP7: 23343247 | BQ7: 8793.4982 | BR7: 3708.1023 | BS7: 5085.3958 | BT7: 433540.25 | BU7: 439969.24 | BV7: 0 | BW7: 0 | BX7: - | BY7: 31 | BZ7: 23535313 | CA7: 8169.0274 | CB7: 4361.9156 | CC7: 3807.1118 | CD7: 454606.49 | CE7: 449162.62 | CF7: 0 | CG7: 0 | CH7: - | CI7: 31 | CJ7: 23815587 | CK7: 8226.1357 | CL7: 3739.2221 | CM7: 4486.9136 | CN7: 461830.87 | CO7: 458447.93 | CP7: 0 | CQ7: 0 | CR7: - | CS7: 31 | CT7: 23987318 | CU7: 9004.0089 | CV7: 4828.2008 | CW7: 4175.808 | CX7: 461271.23 | CY7: 458515.52 | CZ7: 0 | DA7: 0 | DB7: - | DC7: 31 | DD7: 24168250 | DE7: 8259.5798 | DF7: 5074.1054 | DG7: 3185.4744 | DH7: 449438.76 | DI7: 454270.77 | DJ7: 0 | DK7: 0 | DL7: - | DM7: =S7+AC7+AM7+AW7+BG7+BQ7+CA7+CK7+CU7+DE7 | DN7: =U7+AE7+AO7+AY7+BI7+BS7+CC7+CM7+CW7+DG7 | DO7: - | DP7: =IFERROR((DE7-CU7)/CU7,"-") | DQ7: =IFERROR((DG7-CW7)/CW7,"-") | DR7: =IFERROR((DH7-CX7)/CX7,"-") | DS7: 32 | DT7: 24460976 | DU7: 7854.608 | DV7: 3851.6136 | DW7: 4002.9945 | DX7: 462097.67 | DY7: 462469.54 | DZ7: 0 | EA7: 0 | EB7: - | EC7: =S7+AC7+AM7+AW7+BG7+BQ7+CA7+CK7+CU7+DE7+DU7 | ED7: =U7+AE7+AO7+AY7+BI7+BS7+CC7+CM7+CW7+DG7+DW7 | EE7: - | EF7: =IFERROR((DU7-DE7)/DE7,"-") | EG7: =IFERROR((DW7-DG7)/DG7,"-") | EH7: =IFERROR((DX7-DH7)/DH7,"-") | EI7: - | EJ7: 33 | EK7: 24763770 | EL7: 10769.932 | EM7: 4706.4036 | EN7: 6063.5287 | EO7: 418329.2 | EP7: 437782.59 | EQ7: 0 | ER7: 0 | ES7: - | ET7: =S7+AC7+AM7+AW7+BG7+BQ7+CA7+CK7+CU7+DE7+DU7+EL7 | EU7: =U7+AE7+AO7+AY7+BI7+BS7+CC7+CM7+CW7+DG7+DW7+EN7 | EV7: - | EW7: =IFERROR((EL7-DU7)/DU7,"-") | EX7: =IFERROR((EN7-DW7)/DW7,"-") | EY7: =IFERROR((EO7-DX7)/DX7,"-")
A8: Small Cap Fund | B8: Growth/Equity Oriented Schemes | C8: Open ended Schemes | D8: Equity | E8: Equity | F8: Active Equity (incl Hybrid) | K8: =IF(OR(I8="",J8=""),"",I8-J8) | L8: 295478.84 | M8: 288473.49 | P8: - | Q8: 30 | R8: 25141474 | S8: 7017.9 | T8: 3017.9473 | U8: 3999.9527 | V8: 307168.11 | W8: 302451.86 | X8: 0 | Y8: 0 | Z8: - | AA8: 30 | AB8: 25248991 | AC8: 6754.2126 | AD8: 3540.007 | AE8: 3214.2056 | AF8: 336005.21 | AG8: 321670.43 | AH8: 0 | AI8: 0 | AJ8: - | AK8: 30 | AL8: 25614974 | AM8: 7426.6331 | AN8: 3402.1355 | AO8: 4024.4976 | AP8: 354550.63 | AQ8: 344307.6 | AR8: 0 | AS8: 0 | AT8: - | AU8: 31 | AV8: 26255276 | AW8: 9776.2416 | AX8: 3291.8128 | AY8: 6484.4288 | AZ8: 355901.84 | BA8: 358771.3 | BB8: 0 | BC8: 0 | BD8: - | BE8: 31 | BF8: 26635485 | BG8: 7619.2617 | BH8: 2626.3521 | BI8: 4992.9096 | BJ8: 350555.21 | BK8: 352644.66 | BL8: 0 | BM8: 0 | BN8: - | BO8: 31 | BP8: 26894961 | BQ8: 8065.5209 | BR8: 3702.6071 | BS8: 4362.9138 | BT8: 356740.75 | BU8: 362741.69 | BV8: 0 | BW8: 0 | BX8: - | BY8: 31 | BZ8: 27017320 | CA8: 7660.9878 | CB8: 4184.9447 | CC8: 3476.0432 | CD8: 372362.31 | CE8: 366798.06 | CF8: 0 | CG8: 0 | CH8: - | CI8: 32 | CJ8: 27263667 | CK8: 8106.9204 | CL8: 3700.0194 | CM8: 4406.901 | CN8: 369881.92 | CO8: 370912.89 | CP8: 0 | CQ8: 0 | CR8: - | CS8: 33 | CT8: 27335457 | CU8: 8396.079 | CV8: 4572.2552 | CW8: 3823.8238 | CX8: 369003.09 | CY8: 366387.32 | CZ8: 0 | DA8: 0 | DB8: - | DC8: 34 | DD8: 27471864 | DE8: 8133.4169 | DF8: 5191.3055 | DG8: 2942.1115 | DH8: 354789.97 | DI8: 359055.59 | DJ8: 0 | DK8: 0 | DL8: - | DM8: =S8+AC8+AM8+AW8+BG8+BQ8+CA8+CK8+CU8+DE8 | DN8: =U8+AE8+AO8+AY8+BI8+BS8+CC8+CM8+CW8+DG8 | DO8: - | DP8: =IFERROR((DE8-CU8)/CU8,"-") | DQ8: =IFERROR((DG8-CW8)/CW8,"-") | DR8: =IFERROR((DH8-CX8)/CX8,"-") | DS8: 34 | DT8: 27721310 | DU8: 7591.522 | DV8: 3710.4642 | DW8: 3881.0577 | DX8: 363536.98 | DY8: 364961.07 | DZ8: 0 | EA8: 0 | EB8: - | EC8: =S8+AC8+AM8+AW8+BG8+BQ8+CA8+CK8+CU8+DE8+DU8 | ED8: =U8+AE8+AO8+AY8+BI8+BS8+CC8+CM8+CW8+DG8+DW8 | EE8: - | EF8: =IFERROR((DU8-DE8)/DE8,"-") | EG8: =IFERROR((DW8-DG8)/DG8,"-") | EH8: =IFERROR((DX8-DH8)/DH8,"-") | EI8: - | EJ8: 36 | EK8: 27995339 | EL8: 10674.845 | EM8: 4411.2848 | EN8: 6263.5603 | EO8: 334662.34 | EP8: 347116.55 | EQ8: 0 | ER8: 0 | ES8: - | ET8: =S8+AC8+AM8+AW8+BG8+BQ8+CA8+CK8+CU8+DE8+DU8+EL8 | EU8: =U8+AE8+AO8+AY8+BI8+BS8+CC8+CM8+CW8+DG8+DW8+EN8 | EV8: - | EW8: =IFERROR((EL8-DU8)/DU8,"-") | EX8: =IFERROR((EN8-DW8)/DW8,"-") | EY8: =IFERROR((EO8-DX8)/DX8,"-")
A9: Large & Mid Cap Fund | B9: Growth/Equity Oriented Schemes | C9: Open ended Schemes | D9: Equity | E9: Equity | F9: Active Equity (incl Hybrid) | K9: =IF(OR(I9="",J9=""),"",I9-J9) | L9: 263206.56 | M9: 254637.15 | P9: - | Q9: 31 | R9: 11957644 | S9: 5485.4328 | T9: 2933.3766 | U9: 2552.0562 | V9: 273258.42 | W9: 265202.48 | X9: 0 | Y9: 0 | Z9: - | AA9: 31 | AB9: 12069826 | AC9: 5352.7175 | AD9: 2662.0301 | AE9: 2690.6874 | AF9: 287392.5 | AG9: 280686.22 | AH9: 0 | AI9: 0 | AJ9: - | AK9: 32 | AL9: 12262237 | AM9: 5847.9355 | AN9: 2351.0242 | AO9: 3496.9113 | AP9: 302139.03 | AQ9: 294474.58 | AR9: 0 | AS9: 0 | AT9: - | AU9: 33 | AV9: 12511660 | AW9: 7399.657 | AX9: 2364.9434 | AY9: 5034.7136 | AZ9: 300972.11 | BA9: 302807.78 | BB9: 0 | BC9: 0 | BD9: - | BE9: 33 | BF9: 12691674 | BG9: 5501.9524 | BH9: 2176.295 | BI9: 3325.6574 | BJ9: 299335.05 | BK9: 301161.33 | BL9: 0 | BM9: 0 | BN9: - | BO9: 33 | BP9: 12853471 | BQ9: 6769.3997 | BR9: 2964.2346 | BS9: 3805.1651 | BT9: 306903.35 | BU9: 309862.4 | BV9: 0 | BW9: 0 | BX9: - | BY9: 33 | BZ9: 12989734 | CA9: 6037.2192 | CB9: 2860.1506 | CC9: 3177.0685 | CD9: 322158.21 | CE9: 317917.72 | CF9: 0 | CG9: 0 | CH9: - | CI9: 33 | CJ9: 13165462 | CK9: 6979.0164 | CL9: 2475.7016 | CM9: 4503.3148 | CN9: 329325.16 | CO9: 325878.91 | CP9: 0 | CQ9: 0 | CR9: - | CS9: 33 | CT9: 13297987 | CU9: 7079.1563 | CV9: 2985.6504 | CW9: 4093.5059 | CX9: 331287.38 | CY9: 328384.34 | CZ9: 0 | DA9: 0 | DB9: - | DC9: 33 | DD9: 13434952 | DE9: 6423.9105 | DF9: 3242.0196 | DG9: 3181.8909 | DH9: 324621.33 | DI9: 327288.02 | DJ9: 0 | DK9: 0 | DL9: - | DM9: =S9+AC9+AM9+AW9+BG9+BQ9+CA9+CK9+CU9+DE9 | DN9: =U9+AE9+AO9+AY9+BI9+BS9+CC9+CM9+CW9+DG9 | DO9: - | DP9: =IFERROR((DE9-CU9)/CU9,"-") | DQ9: =IFERROR((DG9-CW9)/CW9,"-") | DR9: =IFERROR((DH9-CX9)/CX9,"-") | DS9: 33 | DT9: 13582421 | DU9: 5841.7482 | DV9: 2704.0179 | DW9: 3137.7303 | DX9: 331893.1 | DY9: 332993.59 | DZ9: 0 | EA9: 0 | EB9: - | EC9: =S9+AC9+AM9+AW9+BG9+BQ9+CA9+CK9+CU9+DE9+DU9 | ED9: =U9+AE9+AO9+AY9+BI9+BS9+CC9+CM9+CW9+DG9+DW9 | EE9: - | EF9: =IFERROR((DU9-DE9)/DE9,"-") | EG9: =IFERROR((DW9-DG9)/DG9,"-") | EH9: =IFERROR((DX9-DH9)/DH9,"-") | EI9: - | EJ9: 33 | EK9: 13722688 | EL9: 9007.3707 | EM9: 3700.1235 | EN9: 5307.2472 | EO9: 299467.98 | EP9: 314204.09 | EQ9: 0 | ER9: 0 | ES9: - | ET9: =S9+AC9+AM9+AW9+BG9+BQ9+CA9+CK9+CU9+DE9+DU9+EL9 | EU9: =U9+AE9+AO9+AY9+BI9+BS9+CC9+CM9+CW9+DG9+DW9+EN9 | EV9: - | EW9: =IFERROR((EL9-DU9)/DU9,"-") | EX9: =IFERROR((EN9-DW9)/DW9,"-") | EY9: =IFERROR((EO9-DX9)/DX9,"-")
A10: Sectoral/Thematic Funds | B10: Growth/Equity Oriented Schemes | C10: Open ended Schemes | D10: Equity | E10: Equity | F10: Active Equity (incl Hybrid) | K10: =IF(OR(I10="",J10=""),"",I10-J10) | L10: 455088.24 | M10: 443499.84 | P10: - | Q10: 213 | R10: 30895904 | S10: 10060.067 | T10: 8059.1216 | U10: 2000.9458 | V10: 470339.04 | W10: 457166.12 | X10: 0 | Y10: 0 | Z10: - | AA10: 215 | AB10: 30982541 | AC10: 10621.097 | AD10: 8568.6122 | AE10: 2052.4844 | AF10: 492403.81 | AG10: 481284.64 | AH10: 0 | AI10: 0 | AJ10: - | AK10: 217 | AL10: 31140356 | AM10: 9633.7916 | AN10: 9158.1857 | AO10: 475.60585 | AP10: 509344.83 | AQ10: 499575.1 | AR10: 0 | AS10: 0 | AT10: - | AU10: 224 | AV10: 31771659 | AW10: 18092.629 | AX10: 8666.6032 | AY10: 9426.0262 | AZ10: 509519.21 | BA10: 509953.74 | BB10: 0 | BC10: 0 | BD10: - | BE10: 226 | BF10: 31939915 | BG10: 10929.155 | BH10: 7035.9918 | BI10: 3893.1634 | BJ10: 506571.7 | BK10: 508546.18 | BL10: 0 | BM10: 0 | BN10: - | BO10: 227 | BP10: 31889078 | BQ10: 11167.475 | BR10: 9946.5845 | BS10: 1220.891 | BT10: 513469.44 | BU10: 520090.15 | BV10: 0 | BW10: 0 | BX10: - | BY10: 231 | BZ10: 31811396 | CA10: 11776.953 | CB10: 10410.792 | CC10: 1366.1616 | CD10: 533830.68 | CE10: 527588.94 | CF10: 0 | CG10: 0 | CH10: - | CI10: 235 | CJ10: 31879923 | CK10: 10959.588 | CL10: 9094.6008 | CM10: 1864.9877 | CN10: 538180.29 | CO10: 534941.46 | CP10: 0 | CQ10: 0 | CR10: - | CS10: 238 | CT10: 31747483 | CU10: 11033.943 | CV10: 10087.956 | CW10: 945.98756 | CX10: 537666.6 | CY10: 535256.97 | CZ10: 0 | DA10: 0 | DB10: - | DC10: 240 | DD10: 31681759 | DE10: 11116.922 | DF10: 10074.358 | DG10: 1042.5646 | DH10: 523743.15 | DI10: 529376.94 | DJ10: 0 | DK10: 0 | DL10: - | DM10: =S10+AC10+AM10+AW10+BG10+BQ10+CA10+CK10+CU10+DE10 | DN10: =U10+AE10+AO10+AY10+BI10+BS10+CC10+CM10+CW10+DG10 | DO10: - | DP10: =IFERROR((DE10-CU10)/CU10,"-") | DQ10: =IFERROR((DG10-CW10)/CW10,"-") | DR10: =IFERROR((DH10-CX10)/CX10,"-") | DS10: 246 | DT10: 31953492 | DU10: 13094.129 | DV10: 10106.843 | DW10: 2987.2857 | DX10: 529804.2 | DY10: 531410.45 | DZ10: 0 | EA10: 0 | EB10: - | EC10: =S10+AC10+AM10+AW10+BG10+BQ10+CA10+CK10+CU10+DE10+DU10 | ED10: =U10+AE10+AO10+AY10+BI10+BS10+CC10+CM10+CW10+DG10+DW10 | EE10: - | EF10: =IFERROR((DU10-DE10)/DE10,"-") | EG10: =IFERROR((DW10-DG10)/DG10,"-") | EH10: =IFERROR((DX10-DH10)/DH10,"-") | EI10: - | EJ10: 250 | EK10: 32127595 | EL10: 13554.205 | EM10: 10855.382 | EN10: 2698.8231 | EO10: 477309.05 | EP10: 500854.01 | EQ10: 0 | ER10: 0 | ES10: - | ET10: =S10+AC10+AM10+AW10+BG10+BQ10+CA10+CK10+CU10+DE10+DU10+EL10 | EU10: =U10+AE10+AO10+AY10+BI10+BS10+CC10+CM10+CW10+DG10+DW10+EN10 | EV10: - | EW10: =IFERROR((EL10-DU10)/DU10,"-") | EX10: =IFERROR((EN10-DW10)/DW10,"-") | EY10: =IFERROR((EO10-DX10)/DX10,"-")
A11: Large Cap Fund | B11: Growth/Equity Oriented Schemes | C11: Open ended Schemes | D11: Equity | E11: Equity | F11: Active Equity (incl Hybrid) | K11: =IF(OR(I11="",J11=""),"",I11-J11) | L11: 359775.39 | M11: 348889.45 | P11: - | Q11: 33 | R11: 16090916 | S11: 5891.4498 | T11: 3219.9861 | U11: 2671.4636 | V11: 374519.71 | W11: 361853.46 | X11: 0 | Y11: 0 | Z11: - | AA11: 33 | AB11: 16175181 | AC11: 5240.699 | AD11: 3990.2248 | AE11: 1250.4742 | AF11: 383666.59 | AG11: 380250.63 | AH11: 0 | AI11: 0 | AJ11: - | AK11: 33 | AL11: 16304538 | AM11: 5171.3407 | AN11: 3477.0089 | AO11: 1694.3318 | AP11: 397470.47 | AQ11: 389566.41 | AR11: 0 | AS11: 0 | AT11: - | AU11: 33 | AV11: 16444374 | AW11: 5503.6666 | AX11: 3378.5763 | AY11: 2125.0903 | AZ11: 391762.73 | BA11: 394905.27 | BB11: 0 | BC11: 0 | BD11: - | BE11: 33 | BF11: 16539476 | BG11: 5475.3981 | BH11: 2640.5166 | BI11: 2834.8815 | BJ11: 389982.59 | BK11: 392379.06 | BL11: 0 | BM11: 0 | BN11: - | BO11: 33 | BP11: 16625122 | BQ11: 5576.8187 | BR11: 3257.7771 | BS11: 2319.0416 | BT11: 395093.32 | BU11: 399779.69 | BV11: 0 | BW11: 0 | BX11: - | BY11: 33 | BZ11: 16696893 | CA11: 5293.268 | CB11: 4321.296 | CC11: 971.97199 | CD11: 410156.51 | CE11: 407307.68 | CF11: 0 | CG11: 0 | CH11: - | CI11: 33 | CJ11: 16796845 | CK11: 4942.3569 | CL11: 3302.5523 | CM11: 1639.8047 | CN11: 418524.98 | CO11: 413988.88 | CP11: 0 | CQ11: 0 | CR11: - | CS11: 33 | CT11: 16870064 | CU11: 5499.6024 | CV11: 3932.1796 | CW11: 1567.4228 | CX11: 418726.65 | CY11: 417491.58 | CZ11: 0 | DA11: 0 | DB11: - | DC11: 33 | DD11: 16949451 | DE11: 5523.629 | DF11: 3518.6518 | DG11: 2004.9772 | DH11: 408303.5 | DI11: 413609.67 | DJ11: 0 | DK11: 0 | DL11: - | DM11: =S11+AC11+AM11+AW11+BG11+BQ11+CA11+CK11+CU11+DE11 | DN11: =U11+AE11+AO11+AY11+BI11+BS11+CC11+CM11+CW11+DG11 | DO11: - | DP11: =IFERROR((DE11-CU11)/CU11,"-") | DQ11: =IFERROR((DG11-CW11)/CW11,"-") | DR11: =IFERROR((DH11-CX11)/CX11,"-") | DS11: 34 | DT11: 17074655 | DU11: 5537.8692 | DV11: 3426.1937 | DW11: 2111.6755 | DX11: 411231.74 | DY11: 415950.82 | DZ11: 0 | EA11: 0 | EB11: - | EC11: =S11+AC11+AM11+AW11+BG11+BQ11+CA11+CK11+CU11+DE11+DU11 | ED11: =U11+AE11+AO11+AY11+BI11+BS11+CC11+CM11+CW11+DG11+DW11 | EE11: - | EF11: =IFERROR((DU11-DE11)/DE11,"-") | EG11: =IFERROR((DW11-DG11)/DG11,"-") | EH11: =IFERROR((DX11-DH11)/DH11,"-") | EI11: - | EJ11: 34 | EK11: 17144363 | EL11: 7209.1027 | EM11: 4211.263 | EN11: 2997.8397 | EO11: 366045.49 | EP11: 387415.68 | EQ11: 0 | ER11: 0 | ES11: - | ET11: =S11+AC11+AM11+AW11+BG11+BQ11+CA11+CK11+CU11+DE11+DU11+EL11 | EU11: =U11+AE11+AO11+AY11+BI11+BS11+CC11+CM11+CW11+DG11+DW11+EN11 | EV11: - | EW11: =IFERROR((EL11-DU11)/DU11,"-") | EX11: =IFERROR((EN11-DW11)/DW11,"-") | EY11: =IFERROR((EO11-DX11)/DX11,"-")
A12: Multi Cap Fund | B12: Growth/Equity Oriented Schemes | C12: Open ended Schemes | D12: Equity | E12: Equity | F12: Active Equity (incl Hybrid) | K12: =IF(OR(I12="",J12=""),"",I12-J12) | L12: 175724.35 | M12: 169398.9 | P12: - | Q12: 30 | R12: 9635087 | S12: 4377.9626 | T12: 1826.2546 | U12: 2551.708 | V12: 183132.81 | W12: 177702.64 | X12: 0 | Y12: 0 | Z12: - | AA12: 31 | AB12: 9826483 | AC12: 5240.159 | AD12: 2240.8731 | AE12: 2999.2859 | AF12: 195159.76 | AG12: 188891.17 | AH12: 0 | AI12: 0 | AJ12: - | AK12: 31 | AL12: 10058599 | AM12: 4717.8981 | AN12: 1923.6963 | AO12: 2794.2018 | AP12: 204689.94 | AQ12: 199461.04 | AR12: 0 | AS12: 0 | AT12: - | AU12: 32 | AV12: 10357646 | AW12: 5961.1287 | AX12: 1970.29 | AY12: 3990.8387 | AZ12: 205281.89 | BA12: 205917.39 | BB12: 0 | BC12: 0 | BD12: - | BE12: 32 | BF12: 10582438 | BG12: 4812.7817 | BH12: 1619.7267 | BI12: 3193.055 | BJ12: 205141.48 | BK12: 205535.81 | BL12: 0 | BM12: 0 | BN12: - | BO12: 32 | BP12: 10786468 | BQ12: 5783.8014 | BR12: 2224.2357 | BS12: 3559.5657 | BT12: 210368.99 | BU12: 212137.47 | BV12: 0 | BW12: 0 | BX12: - | BY12: 32 | BZ12: 10912552 | CA12: 4903.9412 | CB12: 2403.5084 | CC12: 2500.4328 | CD12: 220254.63 | CE12: 217508.32 | CF12: 0 | CG12: 0 | CH12: - | CI12: 32 | CJ12: 11066021 | CK12: 5011.8538 | CL12: 2549.0088 | CM12: 2462.845 | CN12: 222749.03 | CO12: 221497.62 | CP12: 0 | CQ12: 0 | CR12: - | CS12: 32 | CT12: 11173881 | CU12: 5163.2837 | CV12: 2908.3303 | CW12: 2254.9533 | CX12: 223101.79 | CY12: 221480.12 | CZ12: 0 | DA12: 0 | DB12: - | DC12: 32 | DD12: 11272944 | DE12: 5043.0453 | DF12: 3047.8132 | DG12: 1995.2321 | DH12: 216445.39 | DI12: 218817.58 | DJ12: 0 | DK12: 0 | DL12: - | DM12: =S12+AC12+AM12+AW12+BG12+BQ12+CA12+CK12+CU12+DE12 | DN12: =U12+AE12+AO12+AY12+BI12+BS12+CC12+CM12+CW12+DG12 | DO12: - | DP12: =IFERROR((DE12-CU12)/CU12,"-") | DQ12: =IFERROR((DG12-CW12)/CW12,"-") | DR12: =IFERROR((DH12-CX12)/CX12,"-") | DS12: 32 | DT12: 11374795 | DU12: 4387.9214 | DV12: 2454.3875 | DW12: 1933.5339 | DX12: 221586.09 | DY12: 222464.01 | DZ12: 0 | EA12: 0 | EB12: - | EC12: =S12+AC12+AM12+AW12+BG12+BQ12+CA12+CK12+CU12+DE12+DU12 | ED12: =U12+AE12+AO12+AY12+BI12+BS12+CC12+CM12+CW12+DG12+DW12 | EE12: - | EF12: =IFERROR((DU12-DE12)/DE12,"-") | EG12: =IFERROR((DW12-DG12)/DG12,"-") | EH12: =IFERROR((DX12-DH12)/DH12,"-") | EI12: - | EJ12: 32 | EK12: 11482274 | EL12: 5819.8736 | EM12: 2838.3248 | EN12: 2981.5487 | EO12: 200439.13 | EP12: 210283.52 | EQ12: 0 | ER12: 0 | ES12: - | ET12: =S12+AC12+AM12+AW12+BG12+BQ12+CA12+CK12+CU12+DE12+DU12+EL12 | EU12: =U12+AE12+AO12+AY12+BI12+BS12+CC12+CM12+CW12+DG12+DW12+EN12 | EV12: - | EW12: =IFERROR((EL12-DU12)/DU12,"-") | EX12: =IFERROR((EN12-DW12)/DW12,"-") | EY12: =IFERROR((EO12-DX12)/DX12,"-")
A13: Dynamic Asset Allocation/Balanced Advantage Fund | B13: Hybrid Schemes | C13: Open ended Schemes | D13: Equity | E13: Equity-Hybrid Schemes | F13: Active Equity (incl Hybrid) | K13: =IF(OR(I13="",J13=""),"",I13-J13) | L13: 283673.4 | M13: 279386.23 | P13: - | Q13: 35 | R13: 5252235 | S13: 4010.2015 | T13: 3128.9677 | U13: 881.23381 | V13: 292549.95 | W13: 286751.76 | X13: 0 | Y13: 0 | Z13: - | AA13: 35 | AB13: 5288342 | AC13: 4438.8758 | AD13: 3302.7596 | AE13: 1136.1162 | AF13: 299506.76 | AG13: 296512.19 | AH13: 0 | AI13: 0 | AJ13: - | AK13: 35 | AL13: 5342869 | AM13: 4913.1381 | AN13: 3027.6082 | AO13: 1885.5299 | AP13: 306648.51 | AQ13: 303164.82 | AR13: 0 | AS13: 0 | AT13: - | AU13: 35 | AV13: 5425213 | AW13: 5996.0994 | AX13: 3384.9118 | AY13: 2611.1876 | AZ13: 305086.55 | BA13: 307392.82 | BB13: 0 | BC13: 0 | BD13: - | BE13: 35 | BF13: 5474637 | BG13: 4809.9566 | BH13: 2493.472 | BI13: 2316.4846 | BJ13: 304727.5 | BK13: 306186.21 | BL13: 0 | BM13: 0 | BN13: - | BO13: 35 | BP13: 5509198 | BQ13: 5003.9812 | BR13: 3315.4256 | BS13: 1688.5556 | BT13: 309385.04 | BU13: 311226.53 | BV13: 0 | BW13: 0 | BX13: - | BY13: 35 | BZ13: 5530506 | CA13: 4233.7801 | CB13: 3694.1281 | CC13: 539.65205 | CD13: 318121.66 | CE13: 316548.77 | CF13: 0 | CG13: 0 | CH13: - | CI13: 35 | CJ13: 5565740 | CK13: 4482.1312 | CL13: 3072.127 | CM13: 1410.0042 | CN13: 322208.64 | CO13: 320995.1 | CP13: 0 | CQ13: 0 | CR13: - | CS13: 35 | CT13: 5595687 | CU13: 4660.7802 | CV13: 3563.5837 | CW13: 1097.1965 | CX13: 323324.83 | CY13: 323093.25 | CZ13: 0 | DA13: 0 | DB13: - | DC13: 35 | DD13: 5624351 | DE13: 5279.5107 | DF13: 3440.096 | DG13: 1839.4147 | DH13: 319902.64 | DI13: 322414.84 | DJ13: 0 | DK13: 0 | DL13: - | DM13: =S13+AC13+AM13+AW13+BG13+BQ13+CA13+CK13+CU13+DE13 | DN13: =U13+AE13+AO13+AY13+BI13+BS13+CC13+CM13+CW13+DG13 | DO13: - | DP13: =IFERROR((DE13-CU13)/CU13,"-") | DQ13: =IFERROR((DG13-CW13)/CW13,"-") | DR13: =IFERROR((DH13-CX13)/CX13,"-") | DS13: 36 | DT13: 5670757 | DU13: 4745.2108 | DV13: 3223.6398 | DW13: 1521.571 | DX13: 323655.44 | DY13: 325355.67 | DZ13: 0 | EA13: 0 | EB13: - | EC13: =S13+AC13+AM13+AW13+BG13+BQ13+CA13+CK13+CU13+DE13+DU13 | ED13: =U13+AE13+AO13+AY13+BI13+BS13+CC13+CM13+CW13+DG13+DW13 | EE13: - | EF13: =IFERROR((DU13-DE13)/DE13,"-") | EG13: =IFERROR((DW13-DG13)/DG13,"-") | EH13: =IFERROR((DX13-DH13)/DH13,"-") | EI13: - | EJ13: 36 | EK13: 5704774 | EL13: 4570.4626 | EM13: 4852.976 | EN13: -282.51341 | EO13: 299019.05 | EP13: 311460.77 | EQ13: 0 | ER13: 0 | ES13: - | ET13: =S13+AC13+AM13+AW13+BG13+BQ13+CA13+CK13+CU13+DE13+DU13+EL13 | EU13: =U13+AE13+AO13+AY13+BI13+BS13+CC13+CM13+CW13+DG13+DW13+EN13 | EV13: - | EW13: =IFERROR((EL13-DU13)/DU13,"-") | EX13: =IFERROR((EN13-DW13)/DW13,"-") | EY13: =IFERROR((EO13-DX13)/DX13,"-")
A14: Balanced Hybrid Fund/Aggressive Hybrid Fund | B14: Hybrid Schemes | C14: Open ended Schemes | D14: Equity | E14: Equity-Hybrid Schemes | F14: Active Equity (incl Hybrid) | K14: =IF(OR(I14="",J14=""),"",I14-J14) | L14: 219203.86 | M14: 214953.73 | P14: - | Q14: 31 | R14: 5786464 | S14: 2442.8369 | T14: 2594.3097 | U14: -151.47279 | V14: 226008.04 | W14: 221668.36 | X14: 1 | Y14: 0 | Z14: - | AA14: 31 | AB14: 5805601 | AC14: 2625.0926 | AD14: 2283.7023 | AE14: 341.39031 | AF14: 231900.98 | AG14: 229986.39 | AH14: 1 | AI14: 0 | AJ14: - | AK14: 31 | AL14: 5847771 | AM14: 3323.3975 | AN14: 1991.8972 | AO14: 1331.5003 | AP14: 238686.36 | AQ14: 236080.74 | AR14: 1 | AS14: 0 | AT14: - | AU14: 31 | AV14: 5912528 | AW14: 4305.6945 | AX14: 1942.1303 | AY14: 2363.5642 | AZ14: 237969.21 | BA14: 240277.48 | BB14: 1 | BC14: 0 | BD14: - | BE14: 31 | BF14: 5964898 | BG14: 3519.381 | BH14: 1648.9855 | BI14: 1870.3955 | BJ14: 236817.91 | BK14: 238877.01 | BL14: 1 | BM14: 0 | BN14: - | BO14: 31 | BP14: 6011535 | BQ14: 4032.0308 | BR14: 2018.2965 | BS14: 2013.7343 | BT14: 241559.83 | BU14: 243393.86 | BV14: 1 | BW14: 0 | BX14: - | BY14: 31 | BZ14: 6044444 | CA14: 3282.7882 | CB14: 2143.6117 | CC14: 1139.1765 | CD14: 250052.41 | CE14: 249009.9 | CF14: 1 | CG14: 0 | CH14: - | CI14: 31 | CJ14: 6089957 | CK14: 3551.1003 | CL14: 2165.7635 | CM14: 1385.3368 | CN14: 253121.18 | CO14: 252228.24 | CP14: 1 | CQ14: 0 | CR14: - | CS14: 31 | CT14: 6134634 | CU14: 3824.21 | CV14: 2310.3507 | CW14: 1513.8592 | CX14: 253233.73 | CY14: 253602.36 | CZ14: 1 | DA14: 0 | DB14: - | DC14: 31 | DD14: 6177349 | DE14: 3973.708 | DF14: 2295.5444 | DG14: 1678.1636 | DH14: 249182.03 | DI14: 252120.47 | DJ14: 1 | DK14: 0 | DL14: - | DM14: =S14+AC14+AM14+AW14+BG14+BQ14+CA14+CK14+CU14+DE14 | DN14: =U14+AE14+AO14+AY14+BI14+BS14+CC14+CM14+CW14+DG14 | DO14: - | DP14: =IFERROR((DE14-CU14)/CU14,"-") | DQ14: =IFERROR((DG14-CW14)/CW14,"-") | DR14: =IFERROR((DH14-CX14)/CX14,"-") | DS14: 31 | DT14: 6219899 | DU14: 3464.7082 | DV14: 2045.5003 | DW14: 1419.2079 | DX14: 252393.86 | DY14: 254563.79 | DZ14: 1 | EA14: 0 | EB14: - | EC14: =S14+AC14+AM14+AW14+BG14+BQ14+CA14+CK14+CU14+DE14+DU14 | ED14: =U14+AE14+AO14+AY14+BI14+BS14+CC14+CM14+CW14+DG14+DW14 | EE14: - | EF14: =IFERROR((DU14-DE14)/DE14,"-") | EG14: =IFERROR((DW14-DG14)/DG14,"-") | EH14: =IFERROR((DX14-DH14)/DH14,"-") | EI14: - | EJ14: 31 | EK14: 6254655 | EL14: 3527.2116 | EM14: 2532.681 | EN14: 994.53053 | EO14: 232005.53 | EP14: 242445.83 | EQ14: 1 | ER14: 0 | ES14: - | ET14: =S14+AC14+AM14+AW14+BG14+BQ14+CA14+CK14+CU14+DE14+DU14+EL14 | EU14: =U14+AE14+AO14+AY14+BI14+BS14+CC14+CM14+CW14+DG14+DW14+EN14 | EV14: - | EW14: =IFERROR((EL14-DU14)/DU14,"-") | EX14: =IFERROR((EN14-DW14)/DW14,"-") | EY14: =IFERROR((EO14-DX14)/DX14,"-")
A15: Focused Fund | B15: Growth/Equity Oriented Schemes | C15: Open ended Schemes | D15: Equity | E15: Equity | F15: Active Equity (incl Hybrid) | K15: =IF(OR(I15="",J15=""),"",I15-J15) | L15: 144791.04 | M15: 139975.78 | P15: - | Q15: 28 | R15: 5233413 | S15: 2409.0274 | T15: 1524.2699 | U15: 884.75752 | V15: 150223.05 | W15: 145808.93 | X15: 0 | Y15: 0 | Z15: - | AA15: 28 | AB15: 5246530 | AC15: 2715.7808 | AD15: 1768.6016 | AE15: 947.17915 | AF15: 155870.44 | AG15: 153127.92 | AH15: 0 | AI15: 0 | AJ15: - | AK15: 28 | AL15: 5270077 | AM15: 2338.9052 | AN15: 1373.8587 | AO15: 965.04642 | AP15: 162172.57 | AQ15: 158520.26 | AR15: 0 | AS15: 0 | AT15: - | AU15: 28 | AV15: 5298700 | AW15: 2981.6852 | AX15: 1375.7235 | AY15: 1605.9617 | AZ15: 160567.18 | BA15: 161580.85 | BB15: 0 | BC15: 0 | BD15: - | BE15: 28 | BF15: 5325168 | BG15: 2315.8985 | BH15: 1160.7197 | BI15: 1155.1788 | BJ15: 159952.07 | BK15: 160556.69 | BL15: 0 | BM15: 0 | BN15: - | BO15: 28 | BP15: 5346169 | BQ15: 2866.8032 | BR15: 1459.5757 | BS15: 1407.2275 | BT15: 162968.75 | BU15: 164734.32 | BV15: 0 | BW15: 0 | BX15: - | BY15: 28 | BZ15: 5359834 | CA15: 2538.6933 | CB15: 1599.6349 | CC15: 939.05832 | CD15: 170127.72 | CE15: 168387.2 | CF15: 0 | CG15: 0 | CH15: - | CI15: 28 | CJ15: 5386533 | CK15: 3575.7648 | CL15: 1536.0301 | CM15: 2039.7347 | CN15: 174618.42 | CO15: 172377.76 | CP15: 0 | CQ15: 0 | CR15: - | CS15: 28 | CT15: 5415223 | CU15: 2720.2336 | CV15: 1663.4089 | CW15: 1056.8247 | CX15: 174834.13 | CY15: 174196.74 | CZ15: 0 | DA15: 0 | DB15: - | DC15: 28 | DD15: 5450285 | DE15: 3280.799 | DF15: 1723.8435 | DG15: 1556.9555 | DH15: 171535.16 | DI15: 173290.06 | DJ15: 0 | DK15: 0 | DL15: - | DM15: =S15+AC15+AM15+AW15+BG15+BQ15+CA15+CK15+CU15+DE15 | DN15: =U15+AE15+AO15+AY15+BI15+BS15+CC15+CM15+CW15+DG15 | DO15: - | DP15: =IFERROR((DE15-CU15)/CU15,"-") | DQ15: =IFERROR((DG15-CW15)/CW15,"-") | DR15: =IFERROR((DH15-CX15)/CX15,"-") | DS15: 28 | DT15: 5487816 | DU15: 2467.1431 | DV15: 1566.4257 | DW15: 900.71734 | DX15: 172879.66 | DY15: 174581.19 | DZ15: 0 | EA15: 0 | EB15: - | EC15: =S15+AC15+AM15+AW15+BG15+BQ15+CA15+CK15+CU15+DE15+DU15 | ED15: =U15+AE15+AO15+AY15+BI15+BS15+CC15+CM15+CW15+DG15+DW15 | EE15: - | EF15: =IFERROR((DU15-DE15)/DE15,"-") | EG15: =IFERROR((DW15-DG15)/DG15,"-") | EH15: =IFERROR((DX15-DH15)/DH15,"-") | EI15: - | EJ15: 28 | EK15: 5514885 | EL15: 4371.4559 | EM15: 1946.8701 | EN15: 2424.5858 | EO15: 155861.22 | EP15: 163751.3 | EQ15: 0 | ER15: 0 | ES15: - | ET15: =S15+AC15+AM15+AW15+BG15+BQ15+CA15+CK15+CU15+DE15+DU15+EL15 | EU15: =U15+AE15+AO15+AY15+BI15+BS15+CC15+CM15+CW15+DG15+DW15+EN15 | EV15: - | EW15: =IFERROR((EL15-DU15)/DU15,"-") | EX15: =IFERROR((EN15-DW15)/DW15,"-") | EY15: =IFERROR((EO15-DX15)/DX15,"-")
A16: Value Fund/Contra Fund | B16: Growth/Equity Oriented Schemes | C16: Open ended Schemes | D16: Equity | E16: Equity | F16: Active Equity (incl Hybrid) | K16: =IF(OR(I16="",J16=""),"",I16-J16) | L16: 183906.07 | M16: 178490.57 | P16: - | Q16: 24 | R16: 8307959 | S16: 2713.7138 | T16: 1640.5 | U16: 1073.2138 | V16: 190856.6 | W16: 184757.15 | X16: 0 | Y16: 0 | Z16: - | AA16: 24 | AB16: 8368668 | AC16: 2812.71 | AD16: 2904.9896 | AE16: -92.279532 | AF16: 196339.39 | AG16: 193702.93 | AH16: 0 | AI16: 0 | AJ16: - | AK16: 24 | AL16: 8450603 | AM16: 2803.5817 | AN16: 1644.1425 | AO16: 1159.4391 | AP16: 203756.28 | AQ16: 199511.25 | AR16: 0 | AS16: 0 | AT16: - | AU16: 24 | AV16: 8547004 | AW16: 3135.2837 | AX16: 1665.276 | AY16: 1470.0076 | AZ16: 201203.79 | BA16: 203431.48 | BB16: 0 | BC16: 0 | BD16: - | BE16: 24 | BF16: 8612986 | BG16: 2576.5061 | BH16: 1435.4749 | BI16: 1141.0312 | BJ16: 198969.56 | BK16: 200275.63 | BL16: 0 | BM16: 0 | BN16: - | BO16: 25 | BP16: 8785142 | BQ16: 4033.7858 | BR16: 1925.8548 | BS16: 2107.931 | BT16: 204298.58 | BU16: 205770.81 | BV16: 0 | BW16: 0 | BX16: - | BY16: 25 | BZ16: 8788244 | CA16: 2590.6719 | CB16: 2222.2821 | CC16: 368.3898 | CD16: 213021.35 | CE16: 210507.57 | CF16: 0 | CG16: 0 | CH16: - | CI16: 25 | CJ16: 8830956 | CK16: 3215.108 | CL16: 1995.6639 | CM16: 1219.4441 | CN16: 217555.44 | CO16: 215017.29 | CP16: 0 | CQ16: 0 | CR16: - | CS16: 25 | CT16: 8857029 | CU16: 3444.8385 | CV16: 2356.3282 | CW16: 1088.5103 | CX16: 219127.72 | CY16: 217176.2 | CZ16: 0 | DA16: 0 | DB16: - | DC16: 25 | DD16: 8885986 | DE16: 3054.7944 | DF16: 2061.9068 | DG16: 992.88753 | DH16: 214214.78 | DI16: 215977.28 | DJ16: 0 | DK16: 0 | DL16: - | DM16: =S16+AC16+AM16+AW16+BG16+BQ16+CA16+CK16+CU16+DE16 | DN16: =U16+AE16+AO16+AY16+BI16+BS16+CC16+CM16+CW16+DG16 | DO16: - | DP16: =IFERROR((DE16-CU16)/CU16,"-") | DQ16: =IFERROR((DG16-CW16)/CW16,"-") | DR16: =IFERROR((DH16-CX16)/CX16,"-") | DS16: 25 | DT16: 8927937 | DU16: 2566.1783 | DV16: 1839.1124 | DW16: 727.06595 | DX16: 215264.76 | DY16: 216730.33 | DZ16: 0 | EA16: 0 | EB16: - | EC16: =S16+AC16+AM16+AW16+BG16+BQ16+CA16+CK16+CU16+DE16+DU16 | ED16: =U16+AE16+AO16+AY16+BI16+BS16+CC16+CM16+CW16+DG16+DW16 | EE16: - | EF16: =IFERROR((DU16-DE16)/DE16,"-") | EG16: =IFERROR((DW16-DG16)/DG16,"-") | EH16: =IFERROR((DX16-DH16)/DH16,"-") | EI16: - | EJ16: 25 | EK16: 8965112 | EL16: 4281.0469 | EM16: 2125.4932 | EN16: 2155.5537 | EO16: 193985.76 | EP16: 203829.55 | EQ16: 0 | ER16: 0 | ES16: - | ET16: =S16+AC16+AM16+AW16+BG16+BQ16+CA16+CK16+CU16+DE16+DU16+EL16 | EU16: =U16+AE16+AO16+AY16+BI16+BS16+CC16+CM16+CW16+DG16+DW16+EN16 | EV16: - | EW16: =IFERROR((EL16-DU16)/DU16,"-") | EX16: =IFERROR((EN16-DW16)/DW16,"-") | EY16: =IFERROR((EO16-DX16)/DX16,"-")
... A19: Retirement Fund | B19: Solution Oriented Schemes | C19: Open ended Schemes | D19: Equity | E19: Equity | F19: Active Equity (incl Hybrid) | K19: =IF(OR(I19="",J19=""),"",I19-J19) | L19: 29104.498 | M19: 28388.195 | P19: - | Q19: 29 | R19: 2999887 | S19: 254.96061 | T19: 178.95675 | U19: 76.003861 | V19: 29996.207 | W19: 29245.262 | X19: 0 | Y19: 0 | Z19: - | AA19: 29 | AB19: 3003234 | AC19: 251.43797 | AD19: 198.5286 | AE19: 52.909369 | AF19: 31006.982 | AG19: 30588.372 | AH19: 0 | AI19: 0 | AJ19: - | AK19: 29 | AL19: 3009203 | AM19: 271.58925 | AN19: 193.11502 | AO19: 78.474223 | AP19: 31973.265 | AQ19: 31446.293 | AR19: 0 | AS19: 0 | AT19: - | AU19: 29 | AV19: 3016170 | AW19: 316.2963 | AX19: 197.39611 | AY19: 118.9002 | AZ19: 31415.747 | BA19: 31812.873 | BB19: 0 | BC19: 0 | BD19: - | BE19: 29 | BF19: 3022062 | BG19: 274.72057 | BH19: 140.24966 | BI19: 134.47092 | BJ19: 31058.435 | BK19: 31359.242 | BL19: 0 | BM19: 0 | BN19: - | BO19: 29 | BP19: 3027172 | BQ19: 291.37091 | BR19: 194.55248 | BS19: 96.818428 | BT19: 31454.415 | BU19: 31800.743 | BV19: 0 | BW19: 0 | BX19: - | BY19: 29 | BZ19: 3032112 | CA19: 274.53561 | CB19: 170.50777 | CC19: 104.02784 | CD19: 32512.298 | CE19: 32307.958 | CF19: 0 | CG19: 0 | CH19: - | CI19: 29 | CJ19: 3037674 | CK19: 268.39014 | CL19: 162.00462 | CM19: 106.38552 | CN19: 32835.333 | CO19: 32694.491 | CP19: 0 | CQ19: 0 | CR19: - | CS19: 29 | CT19: 3042915 | CU19: 299.89411 | CV19: 178.89782 | CW19: 120.99629 | CX19: 32828.506 | CY19: 32711.556 | CZ19: 0 | DA19: 0 | DB19: - | DC19: 29 | DD19: 3049871 | DE19: 279.23073 | DF19: 174.71369 | DG19: 104.51704 | DH19: 32044.113 | DI19: 32448.643 | DJ19: 0 | DK19: 0 | DL19: - | DM19: =S19+AC19+AM19+AW19+BG19+BQ19+CA19+CK19+CU19+DE19 | DN19: =U19+AE19+AO19+AY19+BI19+BS19+CC19+CM19+CW19+DG19 | DO19: - | DP19: =IFERROR((DE19-CU19)/CU19,"-") | DQ19: =IFERROR((DG19-CW19)/CW19,"-") | DR19: =IFERROR((DH19-CX19)/CX19,"-") | DS19: 29 | DT19: 3055597 | DU19: 293.78622 | DV19: 275.41609 | DW19: 18.370133 | DX19: 32229.114 | DY19: 32619.675 | DZ19: 0 | EA19: 0 | EB19: - | EC19: =S19+AC19+AM19+AW19+BG19+BQ19+CA19+CK19+CU19+DE19+DU19 | ED19: =U19+AE19+AO19+AY19+BI19+BS19+CC19+CM19+CW19+DG19+DW19 | EE19: - | EF19: =IFERROR((DU19-DE19)/DE19,"-") | EG19: =IFERROR((DW19-DG19)/DG19,"-") | EH19: =IFERROR((DX19-DH19)/DH19,"-") | EI19: - | EJ19: 29 | EK19: 3059924 | EL19: 252.81952 | EM19: 224.12636 | EN19: 28.693163 | EO19: 29275.013 | EP19: 30709.12 | EQ19: 0 | ER19: 0 | ES19: - | ET19: =S19+AC19+AM19+AW19+BG19+BQ19+CA19+CK19+CU19+DE19+DU19+EL19 | EU19: =U19+AE19+AO19+AY19+BI19+BS19+CC19+CM19+CW19+DG19+DW19+EN19 | EV19: - | EW19: =IFERROR((EL19-DU19)/DU19,"-") | EX19: =IFERROR((EN19-DW19)/DW19,"-") | EY19: =IFERROR((EO19-DX19)/DX19,"-")
A20: Other Equity Schemes | B20: Growth/Equity Oriented Schemes | C20: Close Ended Schemes | D20: Equity | E20: Equity | F20: Active Equity (incl Hybrid) | K20: =IF(OR(I20="",J20=""),"",I20-J20) | L20: 0 | M20: 0 | P20: - | Q20: 0 | R20: 0 | S20: 0 | T20: 0 | U20: 0 | V20: 0 | W20: 0 | X20: 0 | Y20: 0 | Z20: - | AA20: 0 | AB20: 0 | AC20: 0 | AD20: 0 | AE20: 0 | AF20: 0 | AG20: 0 | AH20: 0 | AI20: 0 | AJ20: - | AK20: 0 | AL20: 0 | AM20: 0 | AN20: 0 | AO20: 0 | AP20: 0 | AQ20: 0 | AR20: 0 | AS20: 0 | AT20: - | AU20: 0 | AV20: 0 | AW20: 0 | AX20: 0 | AY20: 0 | AZ20: 0 | BA20: 0 | BB20: 0 | BC20: 0 | BD20: - | BE20: 0 | BF20: 0 | BG20: 0 | BH20: 0 | BI20: 0 | BJ20: 0 | BK20: 0 | BL20: 0 | BM20: 0 | BN20: - | BO20: 0 | BP20: 0 | BQ20: 0 | BR20: 0 | BS20: 0 | BT20: 0 | BU20: 0 | BV20: 0 | BW20: 0 | BX20: - | BY20: 0 | BZ20: 0 | CA20: 0 | CB20: 0 | CC20: 0 | CD20: 0 | CE20: 0 | CF20: 0 | CG20: 0 | CH20: - | CI20: 0 | CJ20: 0 | CK20: 0 | CL20: 0 | CM20: 0 | CN20: 0 | CO20: 0 | CP20: 0 | CQ20: 0 | CR20: - | CS20: 0 | CT20: 0 | CU20: 0 | CV20: 0 | CW20: 0 | CX20: 0 | CY20: 0 | CZ20: 0 | DA20: 0 | DB20: - | DC20: 0 | DD20: 0 | DE20: 0 | DF20: 0 | DG20: 0 | DH20: 0 | DI20: 0 | DJ20: 0 | DK20: 0 | DL20: - | DM20: =S20+AC20+AM20+AW20+BG20+BQ20+CA20+CK20+CU20+DE20 | DN20: =U20+AE20+AO20+AY20+BI20+BS20+CC20+CM20+CW20+DG20 | DO20: - | DP20: - | DQ20: - | DR20: - | DS20: 0 | DT20: 0 | DU20: 0 | DV20: 0 | DW20: 0 | DX20: 0 | DY20: 0 | DZ20: 0 | EA20: 0 | EB20: - | EC20: =S20+AC20+AM20+AW20+BG20+BQ20+CA20+CK20+CU20+DE20+DU20 | ED20: =U20+AE20+AO20+AY20+BI20+BS20+CC20+CM20+CW20+DG20+DW20 | EE20: - | EF20: =IFERROR((DU20-DE20)/DE20,"-") | EG20: =IFERROR((DW20-DG20)/DG20,"-") | EH20: =IFERROR((DX20-DH20)/DH20,"-") | EI20: - | EJ20: 0 | EK20: 0 | EL20: 0 | EM20: 0 | EN20: 0 | EO20: 0 | EP20: 0 | EQ20: 0 | ER20: 0 | ES20: - | ET20: =S20+AC20+AM20+AW20+BG20+BQ20+CA20+CK20+CU20+DE20+DU20+EL20 | EU20: =U20+AE20+AO20+AY20+BI20+BS20+CC20+CM20+CW20+DG20+DW20+EN20 | EV20: - | EW20: =IFERROR((EL20-DU20)/DU20,"-") | EX20: =IFERROR((EN20-DW20)/DW20,"-") | EY20: =IFERROR((EO20-DX20)/DX20,"-")
A21: Other Schemes | B21: Other Schemes | C21: Close Ended Schemes | D21: Equity | E21: Equity | F21: Active Equity (incl Hybrid) | K21: =IF(OR(I21="",J21=""),"",I21-J21) | L21: 0 | M21: 0 | P21: - | Q21: 0 | R21: 0 | S21: 0 | T21: 0 | U21: 0 | V21: 0 | W21: 0 | X21: 0 | Y21: 0 | Z21: - | AA21: 0 | AB21: 0 | AC21: 0 | AD21: 0 | AE21: 0 | AF21: 0 | AG21: 0 | AH21: 0 | AI21: 0 | AJ21: - | AK21: 0 | AL21: 0 | AM21: 0 | AN21: 0 | AO21: 0 | AP21: 0 | AQ21: 0 | AR21: 0 | AS21: 0 | AT21: - | AU21: 0 | AV21: 0 | AW21: 0 | AX21: 0 | AY21: 0 | AZ21: 0 | BA21: 0 | BB21: 0 | BC21: 0 | BD21: - | BE21: 0 | BF21: 0 | BG21: 0 | BH21: 0 | BI21: 0 | BJ21: 0 | BK21: 0 | BL21: 0 | BM21: 0 | BN21: - | BO21: 0 | BP21: 0 | BQ21: 0 | BR21: 0 | BS21: 0 | BT21: 0 | BU21: 0 | BV21: 0 | BW21: 0 | BX21: - | BY21: 0 | BZ21: 0 | CA21: 0 | CB21: 0 | CC21: 0 | CD21: 0 | CE21: 0 | CF21: 0 | CG21: 0 | CH21: - | CI21: 0 | CJ21: 0 | CK21: 0 | CL21: 0 | CM21: 0 | CN21: 0 | CO21: 0 | CP21: 0 | CQ21: 0 | CR21: - | CS21: 0 | CT21: 0 | CU21: 0 | CV21: 0 | CW21: 0 | CX21: 0 | CY21: 0 | CZ21: 0 | DA21: 0 | DB21: - | DC21: 0 | DD21: 0 | DE21: 0 | DF21: 0 | DG21: 0 | DH21: 0 | DI21: 0 | DJ21: 0 | DK21: 0 | DL21: - | DM21: =S21+AC21+AM21+AW21+BG21+BQ21+CA21+CK21+CU21+DE21 | DN21: =U21+AE21+AO21+AY21+BI21+BS21+CC21+CM21+CW21+DG21 | DO21: - | DP21: 0 | DQ21: 0 | DR21: 0 | DS21: 0 | DT21: 0 | DU21: 0 | DV21: 0 | DW21: 0 | DX21: 0 | DY21: 0 | DZ21: 0 | EA21: 0 | EB21: - | EC21: =S21+AC21+AM21+AW21+BG21+BQ21+CA21+CK21+CU21+DE21+DU21 | ED21: =U21+AE21+AO21+AY21+BI21+BS21+CC21+CM21+CW21+DG21+DW21 | EE21: - | EF21: =IFERROR((DU21-DE21)/DE21,"-") | EG21: =IFERROR((DW21-DG21)/DG21,"-") | EH21: =IFERROR((DX21-DH21)/DH21,"-") | EI21: - | EJ21: 0 | EK21: 0 | EL21: 0 | EM21: 0 | EN21: 0 | EO21: 0 | EP21: 0 | EQ21: 0 | ER21: 0 | ES21: - | ET21: =S21+AC21+AM21+AW21+BG21+BQ21+CA21+CK21+CU21+DE21+DU21+EL21 | EU21: =U21+AE21+AO21+AY21+BI21+BS21+CC21+CM21+CW21+DG21+DW21+EN21 | EV21: - | EW21: =IFERROR((EL21-DU21)/DU21,"-") | EX21: =IFERROR((EN21-DW21)/DW21,"-") | EY21: =IFERROR((EO21-DX21)/DX21,"-")
A22: Other Schemes | B22: Interval Schemes | C22: - | D22: - | E22: - | F22: Active Equity (incl Hybrid) | K22: =IF(OR(I22="",J22=""),"",I22-J22) | L22: 0 | M22: 0 | P22: - | Q22: 0 | R22: 0 | S22: 0 | T22: 0 | U22: 0 | V22: 0 | W22: 0 | X22: 0 | Y22: 0 | Z22: - | AA22: 0 | AB22: 0 | AC22: 0 | AD22: 0 | AE22: 0 | AF22: 0 | AG22: 0 | AH22: 0 | AI22: 0 | AJ22: - | AK22: 0 | AL22: 0 | AM22: 0 | AN22: 0 | AO22: 0 | AP22: 0 | AQ22: 0 | AR22: 0 | AS22: 0 | AT22: - | AU22: 0 | AV22: 0 | AW22: 0 | AX22: 0 | AY22: 0 | AZ22: 0 | BA22: 0 | BB22: 0 | BC22: 0 | BD22: - | BE22: 0 | BF22: 0 | BG22: 0 | BH22: 0 | BI22: 0 | BJ22: 0 | BK22: 0 | BL22: 0 | BM22: 0 | BN22: - | BO22: 0 | BP22: 0 | BQ22: 0 | BR22: 0 | BS22: 0 | BT22: 0 | BU22: 0 | BV22: 0 | BW22: 0 | BX22: - | BY22: 0 | BZ22: 0 | CA22: 0 | CB22: 0 | CC22: 0 | CD22: 0 | CE22: 0 | CF22: 0 | CG22: 0 | CH22: - | CI22: 0 | CJ22: 0 | CK22: 0 | CL22: 0 | CM22: 0 | CN22: 0 | CO22: 0 | CP22: 0 | CQ22: 0 | CR22: - | CS22: 0 | CT22: 0 | CU22: 0 | CV22: 0 | CW22: 0 | CX22: 0 | CY22: 0 | CZ22: 0 | DA22: 0 | DB22: - | DC22: 0 | DD22: 0 | DE22: 0 | DF22: 0 | DG22: 0 | DH22: 0 | DI22: 0 | DJ22: 0 | DK22: 0 | DL22: - | DM22: =S22+AC22+AM22+AW22+BG22+BQ22+CA22+CK22+CU22+DE22 | DN22: =U22+AE22+AO22+AY22+BI22+BS22+CC22+CM22+CW22+DG22 | DO22: - | DP22: 0 | DQ22: 0 | DR22: 0 | DS22: 0 | DT22: 0 | DU22: 0 | DV22: 0 | DW22: 0 | DX22: 0 | DY22: 0 | DZ22: 0 | EA22: 0 | EB22: - | EC22: =S22+AC22+AM22+AW22+BG22+BQ22+CA22+CK22+CU22+DE22+DU22 | ED22: =U22+AE22+AO22+AY22+BI22+BS22+CC22+CM22+CW22+DG22+DW22 | EE22: - | EF22: =IFERROR((DU22-DE22)/DE22,"-") | EG22: =IFERROR((DW22-DG22)/DG22,"-") | EH22: =IFERROR((DX22-DH22)/DH22,"-") | EI22: - | EJ22: 0 | EK22: 0 | EL22: 0 | EM22: 0 | EN22: 0 | EO22: 0 | EP22: 0 | EQ22: 0 | ER22: 0 | ES22: - | ET22: =S22+AC22+AM22+AW22+BG22+BQ22+CA22+CK22+CU22+DE22+DU22+EL22 | EU22: =U22+AE22+AO22+AY22+BI22+BS22+CC22+CM22+CW22+DG22+DW22+EN22 | EV22: - | EW22: =IFERROR((EL22-DU22)/DU22,"-") | EX22: =IFERROR((EN22-DW22)/DW22,"-") | EY22: =IFERROR((EO22-DX22)/DX22,"-")
A23: ELSS-Close Ended | B23: Growth/Equity Oriented Schemes | C23: Close Ended Schemes | D23: Equity | E23: Equity | F23: Active Equity (incl Hybrid) | K23: =IF(OR(I23="",J23=""),"",I23-J23) | L23: 4034.5205 | M23: 3977.8897 | P23: - | Q23: 15 | R23: 258637 | S23: 0 | T23: 15.599505 | U23: -15.599505 | V23: 4174.2777 | W23: 4052.9507 | X23: 0 | Y23: 0 | Z23: - | AA23: 15 | AB23: 257771 | AC23: 0 | AD23: 18.563769 | AE23: -18.563769 | AF23: 4272.9353 | AG23: 4227.2002 | AH23: 0 | AI23: 0 | AJ23: - | AK23: 15 | AL23: 256846 | AM23: 0 | AN23: 19.118207 | AO23: -19.118207 | AP23: 4398.6399 | AQ23: 4324.4088 | AR23: 0 | AS23: 0 | AT23: - | AU23: 15 | AV23: 255907 | AW23: 0 | AX23: 29.724395 | AY23: -29.724395 | AZ23: 4275.5324 | BA23: 4342.108 | BB23: 0 | BC23: 0 | BD23: - | BE23: 15 | BF23: 255243 | BG23: 0 | BH23: 13.0443 | BI23: -13.0443 | BJ23: 4219.1556 | BK23: 4244.9541 | BL23: 0 | BM23: 0 | BN23: - | BO23: 15 | BP23: 254488 | BQ23: 0 | BR23: 16.916785 | BS23: -16.916785 | BT23: 4230.7822 | BU23: 4297.0679 | BV23: 0 | BW23: 0 | BX23: - | BY23: 15 | BZ23: 253748 | CA23: 0 | CB23: 18.716928 | CC23: -18.716928 | CD23: 4346.9907 | CE23: 4332.3777 | CF23: 0 | CG23: 0 | CH23: - | CI23: 15 | CJ23: 252978 | CK23: 0 | CL23: 17.437278 | CM23: -17.437278 | CN23: 4370.847 | CO23: 4347.76 | CP23: 0 | CQ23: 0 | CR23: - | CS23: 15 | CT23: 252071 | CU23: 0 | CV23: 19.251978 | CW23: -19.251978 | CX23: 4342.8818 | CY23: 4334.9311 | CZ23: 0 | DA23: 0 | DB23: - | DC23: 15 | DD23: 251406 | DE23: 0 | DF23: 15.424995 | DG23: -15.424995 | DH23: 4196.2202 | DI23: 4258.5084 | DJ23: 0 | DK23: 0 | DL23: - | DM23: =S23+AC23+AM23+AW23+BG23+BQ23+CA23+CK23+CU23+DE23 | DN23: =U23+AE23+AO23+AY23+BI23+BS23+CC23+CM23+CW23+DG23 | DO23: - | DP23: 0 | DQ23: =IFERROR((DG23-CW23)/CW23,"-") | DR23: =IFERROR((DH23-CX23)/CX23,"-") | DS23: 15 | DT23: 250763 | DU23: 0 | DV23: 12.836447 | DW23: -12.836447 | DX23: 4153.951 | DY23: 4220.3996 | DZ23: 0 | EA23: 0 | EB23: - | EC23: =S23+AC23+AM23+AW23+BG23+BQ23+CA23+CK23+CU23+DE23+DU23 | ED23: =U23+AE23+AO23+AY23+BI23+BS23+CC23+CM23+CW23+DG23+DW23 | EE23: - | EF23: =IFERROR((DU23-DE23)/DE23,"-") | EG23: =IFERROR((DW23-DG23)/DG23,"-") | EH23: =IFERROR((DX23-DH23)/DH23,"-") | EI23: - | EJ23: 13 | EK23: 247165 | EL23: 0 | EM23: 84.294009 | EN23: -84.294009 | EO23: 3558.3566 | EP23: 3868.1608 | EQ23: - | ER23: - | ES23: - | ET23: =S23+AC23+AM23+AW23+BG23+BQ23+CA23+CK23+CU23+DE23+DU23+EL23 | EU23: =U23+AE23+AO23+AY23+BI23+BS23+CC23+CM23+CW23+DG23+DW23+EN23 | EV23: - | EW23: =IFERROR((EL23-DU23)/DU23,"-") | EX23: =IFERROR((EN23-DW23)/DW23,"-") | EY23: =IFERROR((EO23-DX23)/DX23,"-")
A24: ELSS | B24: Growth/Equity Oriented Schemes | C24: Open ended Schemes | D24: Equity | E24: Equity | F24: Active Equity (incl Hybrid) | K24: =IF(OR(I24="",J24=""),"",I24-J24) | L24: 232245.47 | M24: 225225.53 | P24: - | Q24: 43 | R24: 16974967 | S24: 1642.7846 | T24: 2014.7841 | U24: -371.99958 | V24: 239050.62 | W24: 232312.33 | X24: 0 | Y24: 0 | Z24: - | AA24: 43 | AB24: 16919934 | AC24: 1443.5895 | AD24: 2121.6952 | AE24: -678.10568 | AF24: 246293.05 | AG24: 242700.55 | AH24: 0 | AI24: 0 | AJ24: - | AK24: 43 | AL24: 16894182 | AM24: 1553.6433 | AN24: 2109.7554 | AO24: -556.11212 | AP24: 253585.36 | AQ24: 249033.13 | AR24: 0 | AS24: 0 | AT24: - | AU24: 43 | AV24: 16873721 | AW24: 1662.7395 | AX24: 2030.9233 | AY24: -368.18383 | AZ24: 248202.52 | BA24: 251295.47 | BB24: 0 | BC24: 0 | BD24: - | BE24: 43 | BF24: 16859956 | BG24: 1522.4071 | BH24: 1463.2531 | BI24: 59.15395 | BJ24: 243981.86 | BK24: 246466.98 | BL24: 0 | BM24: 0 | BN24: - | BO24: 42 | BP24: 16690290 | BQ24: 1554.0615 | BR24: 1861.9851 | BS24: -307.92367 | BT24: 244774.58 | BU24: 248332.09 | BV24: 0 | BW24: 0 | BX24: - | BY24: 42 | BZ24: 16644818 | CA24: 1376.3037 | CB24: 2041.9604 | CC24: -665.65678 | CD24: 253264.09 | CE24: 251624.34 | CF24: 0 | CG24: 0 | CH24: - | CI24: 42 | CJ24: 16604897 | CK24: 1337.4156 | CL24: 1907.5851 | CM24: -570.16944 | CN24: 254888.17 | CO24: 253628.45 | CP24: 0 | CQ24: 0 | CR24: - | CS24: 42 | CT24: 16556812 | CU24: 1431.5892 | CV24: 2149.3192 | CW24: -717.73009 | CX24: 252700.01 | CY24: 252252.97 | CZ24: 0 | DA24: 0 | DB24: - | DC24: 41 | DD24: 16501822 | DE24: 1479.0463 | DF24: 2072.7388 | DG24: -593.6925 | DH24: 244287.64 | DI24: 247617.18 | DJ24: 0 | DK24: 0 | DL24: - | DM24: =S24+AC24+AM24+AW24+BG24+BQ24+CA24+CK24+CU24+DE24 | DN24: =U24+AE24+AO24+AY24+BI24+BS24+CC24+CM24+CW24+DG24 | DO24: - | DP24: =IFERROR((DE24-CU24)/CU24,"-") | DQ24: =IFERROR((DG24-CW24)/CW24,"-") | DR24: =IFERROR((DH24-CX24)/CX24,"-") | DS24: 41 | DT24: 16468213 | DU24: 1295.0443 | DV24: 1945.069 | DW24: -650.02475 | DX24: 245351.54 | DY24: 248089.14 | DZ24: 0 | EA24: 0 | EB24: - | EC24: =S24+AC24+AM24+AW24+BG24+BQ24+CA24+CK24+CU24+DE24+DU24 | ED24: =U24+AE24+AO24+AY24+BI24+BS24+CC24+CM24+CW24+DG24+DW24 | EE24: - | EF24: =IFERROR((DU24-DE24)/DE24,"-") | EG24: =IFERROR((DW24-DG24)/DG24,"-") | EH24: =IFERROR((DX24-DH24)/DH24,"-") | EI24: - | EJ24: 41 | EK24: 16433567 | EL24: 1599.2709 | EM24: 2036.608 | EN24: -437.33712 | EO24: 217309.84 | EP24: 229714.69 | EQ24: 0 | ER24: 0 | ES24: - | ET24: =S24+AC24+AM24+AW24+BG24+BQ24+CA24+CK24+CU24+DE24+DU24+EL24 | EU24: =U24+AE24+AO24+AY24+BI24+BS24+CC24+CM24+CW24+DG24+DW24+EN24 | EV24: - | EW24: =IFERROR((EL24-DU24)/DU24,"-") | EX24: =IFERROR((EN24-DW24)/DW24,"-") | EY24: =IFERROR((EO24-DX24)/DX24,"-")
A25: Total for Active Equity (incl Hybrid) | G25: =SUM(G5:G24) | H25: =SUM(H5:H24) | I25: =SUM(I5:I24) | J25: =SUM(J5:J24) | K25: =SUM(K5:K24) | L25: =SUM(L5:L24) | M25: =SUM(M5:M24) | N25: =SUM(N5:N24) | O25: =SUM(O5:O24) | Q25: =SUM(Q5:Q24) | R25: =SUM(R5:R24) | S25: =SUM(S5:S24) | T25: =SUM(T5:T24) | U25: =SUM(U5:U24) | V25: =SUM(V5:V24) | W25: =SUM(W5:W24) | X25: =SUM(X5:X24) | Y25: =SUM(Y5:Y24) | AA25: =SUM(AA5:AA24) | AB25: =SUM(AB5:AB24) | AC25: =SUM(AC5:AC24) | AD25: =SUM(AD5:AD24) | AE25: =SUM(AE5:AE24) | AF25: =SUM(AF5:AF24) | AG25: =SUM(AG5:AG24) | AH25: =SUM(AH5:AH24) | AI25: =SUM(AI5:AI24) | AK25: =SUM(AK5:AK24) | AL25: =SUM(AL5:AL24) | AM25: =SUM(AM5:AM24) | AN25: =SUM(AN5:AN24) | AO25: =SUM(AO5:AO24) | AP25: =SUM(AP5:AP24) | AQ25: =SUM(AQ5:AQ24) | AR25: =SUM(AR5:AR24) | AS25: =SUM(AS5:AS24) | AU25: =SUM(AU5:AU24) | AV25: =SUM(AV5:AV24) | AW25: =SUM(AW5:AW24) | AX25: =SUM(AX5:AX24) | AY25: =SUM(AY5:AY24) | AZ25: =SUM(AZ5:AZ24) | BA25: =SUM(BA5:BA24) | BB25: =SUM(BB5:BB24) | BC25: =SUM(BC5:BC24) | BE25: =SUM(BE5:BE24) | BF25: =SUM(BF5:BF24) | BG25: =SUM(BG5:BG24) | BH25: =SUM(BH5:BH24) | BI25: =SUM(BI5:BI24) | BJ25: =SUM(BJ5:BJ24) | BK25: =SUM(BK5:BK24) | BL25: =SUM(BL5:BL24) | BM25: =SUM(BM5:BM24) | BO25: =SUM(BO5:BO24) | BP25: =SUM(BP5:BP24) | BQ25: =SUM(BQ5:BQ24) | BR25: =SUM(BR5:BR24) | BS25: =SUM(BS5:BS24) | BT25: =SUM(BT5:BT24) | BU25: =SUM(BU5:BU24) | BV25: =SUM(BV5:BV24) | BW25: =SUM(BW5:BW24) | BY25: =SUM(BY5:BY24) | BZ25: =SUM(BZ5:BZ24) | CA25: =SUM(CA5:CA24) | CB25: =SUM(CB5:CB24) | CC25: =SUM(CC5:CC24) | CD25: =SUM(CD5:CD24) | CE25: =SUM(CE5:CE24) | CF25: =SUM(CF5:CF24) | CG25: =SUM(CG5:CG24) | CI25: =SUM(CI5:CI24) | CJ25: =SUM(CJ5:CJ24) | CK25: =SUM(CK5:CK24) | CL25: =SUM(CL5:CL24) | CM25: =SUM(CM5:CM24) | CN25: =SUM(CN5:CN24) | CO25: =SUM(CO5:CO24) | CP25: =SUM(CP5:CP24) | CQ25: =SUM(CQ5:CQ24) | CS25: =SUM(CS5:CS24) | CT25: =SUM(CT5:CT24) | CU25: =SUM(CU5:CU24) | CV25: =SUM(CV5:CV24) | CW25: =SUM(CW5:CW24) | CX25: =SUM(CX5:CX24) | CY25: =SUM(CY5:CY24) | CZ25: =SUM(CZ5:CZ24) | DA25: =SUM(DA5:DA24) | DC25: =SUM(DC5:DC24) | DD25: =SUM(DD5:DD24) | DE25: =SUM(DE5:DE24) | DF25: =SUM(DF5:DF24) | DG25: =SUM(DG5:DG24) | DH25: =SUM(DH5:DH24) | DI25: =SUM(DI5:DI24) | DJ25: =SUM(DJ5:DJ24) | DK25: =SUM(DK5:DK24) | DM25: =SUM(DM5:DM24) | DN25: =SUM(DN5:DN24) | DP25: =IFERROR((DE25-CU25)/CU25,"-") | DQ25: =IFERROR((DG25-CW25)/CW25,"-") | DR25: =IFERROR((DH25-CX25)/CX25,"-") | DS25: =SUM(DS5:DS24) | DT25: =SUM(DT5:DT24) | DU25: =SUM(DU5:DU24) | DV25: =SUM(DV5:DV24) | DW25: =SUM(DW5:DW24) | DX25: =SUM(DX5:DX24) | DY25: =SUM(DY5:DY24) | DZ25: =SUM(DZ5:DZ24) | EA25: =SUM(EA5:EA24) | EC25: =SUM(EC5:EC24) | ED25: =SUM(ED5:ED24) | EF25: =IFERROR((DU25-DE25)/DE25,"-") | EG25: =IFERROR((DW25-DG25)/DG25,"-") | EH25: =IFERROR((DX25-DH25)/DH25,"-") | EJ25: =SUM(EJ5:EJ24) | EK25: =SUM(EK5:EK24) | EL25: =SUM(EL5:EL24) | EM25: =SUM(EM5:EM24) | EN25: =SUM(EN5:EN24) | EO25: =SUM(EO5:EO24) | EP25: =SUM(EP5:EP24) | EQ25: =SUM(EQ5:EQ24) | ER25: =SUM(ER5:ER24) | ET25: =SUM(ET5:ET24) | EU25: =SUM(EU5:EU24) | EW25: =IFERROR((EL25-DU25)/DU25,"-") | EX25: =IFERROR((EN25-DW25)/DW25,"-") | EY25: =IFERROR((EO25-DX25)/DX25,"-")
A26: Arb/ESF
A27: Arbitrage Fund | B27: Hybrid Schemes | C27: Open ended Schemes | D27: Equity | E27: Arbitrage | F27: Arb/ESF | K27: =IF(OR(I27="",J27=""),"",I27-J27) | L27: 204086.88 | M27: 246994.06 | P27: - | Q27: 32 | R27: 613752 | S27: 27058.802 | T27: 15268.432 | U27: 11790.369 | V27: 213013.58 | W27: 254278.64 | X27: 0 | Y27: 0 | Z27: - | AA27: 32 | AB27: 631630 | AC27: 29587.695 | AD27: 13885.722 | AE27: 15701.973 | AF27: 233962.92 | AG27: 269464.05 | AH27: 0 | AI27: 0 | AJ27: - | AK27: 32 | AL27: 647318 | AM27: 33989.863 | AN27: 18405.29 | AO27: 15584.572 | AP27: 249364.93 | AQ27: 285570.19 | AR27: 0 | AS27: 0 | AT27: - | AU27: 32 | AV27: 664338 | AW27: 29743.402 | AX27: 22447.702 | AY27: 7295.7003 | AZ27: 256675.49 | BA27: 300840.52 | BB27: 0 | BC27: 0 | BD27: - | BE27: 33 | BF27: 681565 | BG27: 27877.671 | BH27: 21211.17 | BI27: 6666.5007 | BJ27: 258923.35 | BK27: 306405.45 | BL27: 0 | BM27: 0 | BN27: - | BO27: 33 | BP27: 693596 | BQ27: 29529.796 | BR27: 30518.046 | BS27: -988.25013 | BT27: 263757.18 | BU27: 310801.91 | BV27: 0 | BW27: 0 | BX27: - | BY27: 34 | BZ27: 705317 | CA27: 29165.922 | CB27: 22246.155 | CC27: 6919.7672 | CD27: 271401.97 | CE27: 316817.82 | CF27: 0 | CG27: 0 | CH27: - | CI27: 35 | CJ27: 718209 | CK27: 22238.096 | CL27: 18046.189 | CM27: 4191.9067 | CN27: 274612.25 | CO27: 324252.2 | CP27: 0 | CQ27: 0 | CR27: - | CS27: 36 | CT27: 741825 | CU27: 26537.849 | CV27: 26411.536 | CW27: 126.31321 | CX27: 278127.94 | CY27: 326834.54 | CZ27: 0 | DA27: 0 | DB27: - | DC27: 36 | DD27: 762151 | DE27: 27817.439 | DF27: 24524.139 | DG27: 3293.2996 | DH27: 276654.07 | DI27: 333040.48 | DJ27: 0 | DK27: 0 | DL27: - | DM27: =S27+AC27+AM27+AW27+BG27+BQ27+CA27+CK27+CU27+DE27 | DN27: =U27+AE27+AO27+AY27+BI27+BS27+CC27+CM27+CW27+DG27 | DO27: - | DP27: =IFERROR((DE27-CU27)/CU27,"-") | DQ27: =IFERROR((DG27-CW27)/CW27,"-") | DR27: =IFERROR((DH27-CX27)/CX27,"-") | DS27: 36 | DT27: 783210 | DU27: 20387.38 | DV27: 19795.531 | DW27: 591.84848 | DX27: 273568.73 | DY27: 333631.83 | DZ27: 0 | EA27: 0 | EB27: - | EC27: =S27+AC27+AM27+AW27+BG27+BQ27+CA27+CK27+CU27+DE27+DU27 | ED27: =U27+AE27+AO27+AY27+BI27+BS27+CC27+CM27+CW27+DG27+DW27 | EE27: - | EF27: =IFERROR((DU27-DE27)/DE27,"-") | EG27: =IFERROR((DW27-DG27)/DG27,"-") | EH27: =IFERROR((DX27-DH27)/DH27,"-") | EI27: - | EJ27: 38 | EK27: 790453 | EL27: 19596.213 | EM27: 40709.91 | EN27: -21113.698 | EO27: 253637.44 | EP27: 325819.16 | EQ27: 0 | ER27: 0 | ES27: - | ET27: =S27+AC27+AM27+AW27+BG27+BQ27+CA27+CK27+CU27+DE27+DU27+EL27 | EU27: =U27+AE27+AO27+AY27+BI27+BS27+CC27+CM27+CW27+DG27+DW27+EN27 | EV27: - | EW27: =IFERROR((EL27-DU27)/DU27,"-") | EX27: =IFERROR((EN27-DW27)/DW27,"-") | EY27: =IFERROR((EO27-DX27)/DX27,"-")
A28: Equity Savings Fund | B28: Hybrid Schemes | C28: Open ended Schemes | D28: Equity | E28: Equity Savings Fund | F28: Arb/ESF | K28: =IF(OR(I28="",J28=""),"",I28-J28) | L28: 41260.387 | M28: 43262.126 | P28: - | Q28: 23 | R28: 480108 | S28: 1438.939 | T28: 1580.8625 | U28: -141.92352 | V28: 41880.94 | W28: 43776.742 | X28: 1 | Y28: 0 | Z28: - | AA28: 23 | AB28: 482654 | AC28: 1906.428 | AD28: 1336.9634 | AE28: 569.46459 | AF28: 43012.566 | AG28: 44756.329 | AH28: 1 | AI28: 0 | AJ28: - | AK28: 23 | AL28: 487952 | AM28: 2453.4676 | AN28: 1380.5713 | AO28: 1072.8963 | AP28: 44639.455 | AQ28: 46181.22 | AR28: 1 | AS28: 0 | AT28: - | AU28: 24 | AV28: 500437 | AW28: 3577.8007 | AX28: 1474.172 | AY28: 2103.6287 | AZ28: 45727.487 | BA28: 48143.708 | BB28: 1 | BC28: 0 | BD28: - | BE28: 25 | BF28: 510097 | BG28: 2450.1994 | BH28: 1581.4113 | BI28: 868.78811 | BJ28: 46236.229 | BK28: 49345.621 | BL28: 1 | BM28: 0 | BN28: - | BO28: 25 | BP28: 515464 | BQ28: 3261.0214 | BR28: 1514.0552 | BS28: 1746.9662 | BT28: 48300.279 | BU28: 51243.411 | BV28: 1 | BW28: 0 | BX28: - | BY28: 25 | BZ28: 517166 | CA28: 2043.1138 | CB28: 1831.3347 | CC28: 211.77912 | CD28: 49251.121 | CE28: 52601.995 | CF28: 1 | CG28: 0 | CH28: - | CI28: 25 | CJ28: 521328 | CK28: 2590.4839 | CL28: 1498.9244 | CM28: 1091.5595 | CN28: 50672.791 | CO28: 53587.605 | CP28: 1 | CQ28: 0 | CR28: - | CS28: 25 | CT28: 525857 | CU28: 2578.1744 | CV28: 1867.5571 | CW28: 710.6173 | CX28: 51235.168 | CY28: 54928.033 | CZ28: 1 | DA28: 0 | DB28: - | DC28: 25 | DD28: 528385 | DE28: 1981.8468 | DF28: 1844.8762 | DG28: 136.97061 | DH28: 50740.466 | DI28: 55314.779 | DJ28: 1 | DK28: 0 | DL28: - | DM28: =S28+AC28+AM28+AW28+BG28+BQ28+CA28+CK28+CU28+DE28 | DN28: =U28+AE28+AO28+AY28+BI28+BS28+CC28+CM28+CW28+DG28 | DO28: - | DP28: =IFERROR((DE28-CU28)/CU28,"-") | DQ28: =IFERROR((DG28-CW28)/CW28,"-") | DR28: =IFERROR((DH28-CX28)/CX28,"-") | DS28: 24 | DT28: 526295 | DU28: 1748.1517 | DV28: 1705.7927 | DW28: 42.359049 | DX28: 50498.048 | DY28: 55250.272 | DZ28: 1 | EA28: 0 | EB28: - | EC28: =S28+AC28+AM28+AW28+BG28+BQ28+CA28+CK28+CU28+DE28+DU28 | ED28: =U28+AE28+AO28+AY28+BI28+BS28+CC28+CM28+CW28+DG28+DW28 | EE28: - | EF28: =IFERROR((DU28-DE28)/DE28,"-") | EG28: =IFERROR((DW28-DG28)/DG28,"-") | EH28: =IFERROR((DX28-DH28)/DH28,"-") | EI28: - | EJ28: 24 | EK28: 526001 | EL28: 1771.5266 | EM28: 2902.7042 | EN28: -1131.1776 | EO28: 47701.174 | EP28: 53499.598 | EQ28: 1 | ER28: 0 | ES28: - | ET28: =S28+AC28+AM28+AW28+BG28+BQ28+CA28+CK28+CU28+DE28+DU28+EL28 | EU28: =U28+AE28+AO28+AY28+BI28+BS28+CC28+CM28+CW28+DG28+DW28+EN28 | EV28: - | EW28: =IFERROR((EL28-DU28)/DU28,"-") | EX28: =IFERROR((EN28-DW28)/DW28,"-") | EY28: =IFERROR((EO28-DX28)/DX28,"-")
A29: Total for Arb/ESF | G29: =SUM(G27:G28) | H29: =SUM(H27:H28) | I29: =SUM(I27:I28) | J29: =SUM(J27:J28) | K29: =SUM(K27:K28) | L29: =SUM(L27:L28) | M29: =SUM(M27:M28) | N29: =SUM(N27:N28) | O29: =SUM(O27:O28) | Q29: =SUM(Q27:Q28) | R29: =SUM(R27:R28) | S29: =SUM(S27:S28) | T29: =SUM(T27:T28) | U29: =SUM(U27:U28) | V29: =SUM(V27:V28) | W29: =SUM(W27:W28) | X29: =SUM(X27:X28) | Y29: =SUM(Y27:Y28) | AA29: =SUM(AA27:AA28) | AB29: =SUM(AB27:AB28) | AC29: =SUM(AC27:AC28) | AD29: =SUM(AD27:AD28) | AE29: =SUM(AE27:AE28) | AF29: =SUM(AF27:AF28) | AG29: =SUM(AG27:AG28) | AH29: =SUM(AH27:AH28) | AI29: =SUM(AI27:AI28) | AK29: =SUM(AK27:AK28) | AL29: =SUM(AL27:AL28) | AM29: =SUM(AM27:AM28) | AN29: =SUM(AN27:AN28) | AO29: =SUM(AO27:AO28) | AP29: =SUM(AP27:AP28) | AQ29: =SUM(AQ27:AQ28) | AR29: =SUM(AR27:AR28) | AS29: =SUM(AS27:AS28) | AU29: =SUM(AU27:AU28) | AV29: =SUM(AV27:AV28) | AW29: =SUM(AW27:AW28) | AX29: =SUM(AX27:AX28) | AY29: =SUM(AY27:AY28) | AZ29: =SUM(AZ27:AZ28) | BA29: =SUM(BA27:BA28) | BB29: =SUM(BB27:BB28) | BC29: =SUM(BC27:BC28) | BE29: =SUM(BE27:BE28) | BF29: =SUM(BF27:BF28) | BG29: =SUM(BG27:BG28) | BH29: =SUM(BH27:BH28) | BI29: =SUM(BI27:BI28) | BJ29: =SUM(BJ27:BJ28) | BK29: =SUM(BK27:BK28) | BL29: =SUM(BL27:BL28) | BM29: =SUM(BM27:BM28) | BO29: =SUM(BO27:BO28) | BP29: =SUM(BP27:BP28) | BQ29: =SUM(BQ27:BQ28) | BR29: =SUM(BR27:BR28) | BS29: =SUM(BS27:BS28) | BT29: =SUM(BT27:BT28) | BU29: =SUM(BU27:BU28) | BV29: =SUM(BV27:BV28) | BW29: =SUM(BW27:BW28) | BY29: =SUM(BY27:BY28) | BZ29: =SUM(BZ27:BZ28) | CA29: =SUM(CA27:CA28) | CB29: =SUM(CB27:CB28) | CC29: =SUM(CC27:CC28) | CD29: =SUM(CD27:CD28) | CE29: =SUM(CE27:CE28) | CF29: =SUM(CF27:CF28) | CG29: =SUM(CG27:CG28) | CI29: =SUM(CI27:CI28) | CJ29: =SUM(CJ27:CJ28) | CK29: =SUM(CK27:CK28) | CL29: =SUM(CL27:CL28) | CM29: =SUM(CM27:CM28) | CN29: =SUM(CN27:CN28) | CO29: =SUM(CO27:CO28) | CP29: =SUM(CP27:CP28) | CQ29: =SUM(CQ27:CQ28) | CS29: =SUM(CS27:CS28) | CT29: =SUM(CT27:CT28) | CU29: =SUM(CU27:CU28) | CV29: =SUM(CV27:CV28) | CW29: =SUM(CW27:CW28) | CX29: =SUM(CX27:CX28) | CY29: =SUM(CY27:CY28) | CZ29: =SUM(CZ27:CZ28) | DA29: =SUM(DA27:DA28) | DC29: =SUM(DC27:DC28) | DD29: =SUM(DD27:DD28) | DE29: =SUM(DE27:DE28) | DF29: =SUM(DF27:DF28) | DG29: =SUM(DG27:DG28) | DH29: =SUM(DH27:DH28) | DI29: =SUM(DI27:DI28) | DJ29: =SUM(DJ27:DJ28) | DK29: =SUM(DK27:DK28) | DM29: =SUM(DM27:DM28) | DN29: =SUM(DN27:DN28) | DP29: =IFERROR((DE29-CU29)/CU29,"-") | DQ29: =IFERROR((DG29-CW29)/CW29,"-") | DR29: =IFERROR((DH29-CX29)/CX29,"-") | DS29: =SUM(DS27:DS28) | DT29: =SUM(DT27:DT28) | DU29: =SUM(DU27:DU28) | DV29: =SUM(DV27:DV28) | DW29: =SUM(DW27:DW28) | DX29: =SUM(DX27:DX28) | DY29: =SUM(DY27:DY28) | DZ29: =SUM(DZ27:DZ28) | EA29: =SUM(EA27:EA28) | EC29: =SUM(EC27:EC28) | ED29: =SUM(ED27:ED28) | EF29: =IFERROR((DU29-DE29)/DE29,"-") | EG29: =IFERROR((DW29-DG29)/DG29,"-") | EH29: =IFERROR((DX29-DH29)/DH29,"-") | EJ29: =SUM(EJ27:EJ28) | EK29: =SUM(EK27:EK28) | EL29: =SUM(EL27:EL28) | EM29: =SUM(EM27:EM28) | EN29: =SUM(EN27:EN28) | EO29: =SUM(EO27:EO28) | EP29: =SUM(EP27:EP28) | EQ29: =SUM(EQ27:EQ28) | ER29: =SUM(ER27:ER28) | ET29: =SUM(ET27:ET28) | EU29: =SUM(EU27:EU28) | EW29: =IFERROR((EL29-DU29)/DU29,"-") | EX29: =IFERROR((EN29-DW29)/DW29,"-") | EY29: =IFERROR((EO29-DX29)/DX29,"-")
A30: Active Debt (incl Hybrid)
A31: Money Market Fund | B31: Income/Debt Oriented Schemes | C31: Open ended Schemes | D31: Debt | E31: TD | F31: Active Debt (incl Hybrid) | K31: =IF(OR(I31="",J31=""),"",I31-J31) | L31: 232662.84 | M31: 243546.04 | P31: - | Q31: 24 | R31: 441187 | S31: 81737.292 | T31: 50230.25 | U31: 31507.041 | V31: 266389.93 | W31: 262306.59 | X31: 1 | Y31: 0 | Z31: - | AA31: 24 | AB31: 445926 | AC31: 63772.293 | AD31: 52549.212 | AE31: 11223.081 | AF31: 279475.78 | AG31: 273313.49 | AH31: 1 | AI31: 0 | AJ31: - | AK31: 24 | AL31: 450098 | AM31: 93866.453 | AN31: 84382.161 | AO31: 9484.2919 | AP31: 290723.82 | AQ31: 278402.59 | AR31: 1 | AS31: 0 | AT31: - | AU31: 25 | AV31: 509995 | AW31: 115459.51 | AX31: 70885.905 | AY31: 44573.604 | AZ31: 337161.18 | BA31: 332443.33 | BB31: 1 | BC31: 0 | BD31: - | BE31: 25 | BF31: 516255 | BG31: 63472.651 | BH31: 61262.124 | BI31: 2210.5279 | BJ31: 340867.69 | BK31: 339739.89 | BL31: 1 | BM31: 0 | BN31: - | BO31: 25 | BP31: 515392 | BQ31: 99827.93 | BR31: 117727.83 | BS31: -17899.896 | BT31: 324657.1 | BU31: 329551.5 | BV31: 1 | BW31: 0 | BX31: - | BY31: 25 | BZ31: 518211 | CA31: 84507.062 | CB31: 66590.625 | CC31: 17916.437 | CD31: 344278.89 | CE31: 335800.69 | CF31: 1 | CG31: 0 | CH31: - | CI31: 26 | CJ31: 524263 | CK31: 58229.831 | CL31: 47125.459 | CM31: 11104.373 | CN31: 357101.16 | CO31: 349189.41 | CP31: 1 | CQ31: 0 | CR31: - | CS31: 26 | CT31: 524338 | CU31: 82193.008 | CV31: 122657.36 | CW31: -40464.357 | CX31: 318352.49 | CY31: 343897 | CZ31: 1 | DA31: 0 | DB31: - | DC31: 27 | DD31: 523717 | DE31: 69043.593 | DF31: 56280.121 | DG31: 12763.472 | DH31: 332151.98 | DI31: 328273.71 | DJ31: 1 | DK31: 0 | DL31: - | DM31: =S31+AC31+AM31+AW31+BG31+BQ31+CA31+CK31+CU31+DE31 | DN31: =U31+AE31+AO31+AY31+BI31+BS31+CC31+CM31+CW31+DG31 | DO31: - | DP31: =IFERROR((DE31-CU31)/CU31,"-") | DQ31: =IFERROR((DG31-CW31)/CW31,"-") | DR31: =IFERROR((DH31-CX31)/CX31,"-") | DS31: 27 | DT31: 530343 | DU31: 72589.164 | DV31: 66322.656 | DW31: 6266.5085 | DX31: 340401.47 | DY31: 339011.21 | DZ31: 1 | EA31: 0 | EB31: - | EC31: =S31+AC31+AM31+AW31+BG31+BQ31+CA31+CK31+CU31+DE31+DU31 | ED31: =U31+AE31+AO31+AY31+BI31+BS31+CC31+CM31+CW31+DG31+DW31 | EE31: - | EF31: =IFERROR((DU31-DE31)/DE31,"-") | EG31: =IFERROR((DW31-DG31)/DG31,"-") | EH31: =IFERROR((DX31-DH31)/DH31,"-") | EI31: - | EJ31: 27 | EK31: 529089 | EL31: 88255.239 | EM31: 117462.22 | EN31: -29206.984 | EO31: 312294.19 | EP31: 314312.21 | EQ31: 1 | ER31: 0 | ES31: - | ET31: =S31+AC31+AM31+AW31+BG31+BQ31+CA31+CK31+CU31+DE31+DU31+EL31 | EU31: =U31+AE31+AO31+AY31+BI31+BS31+CC31+CM31+CW31+DG31+DW31+EN31 | EV31: - | EW31: =IFERROR((EL31-DU31)/DU31,"-") | EX31: =IFERROR((EN31-DW31)/DW31,"-") | EY31: =IFERROR((EO31-DX31)/DX31,"-")
A32: Low Duration Fund | B32: Income/Debt Oriented Schemes | C32: Open ended Schemes | D32: Debt | E32: TD | F32: Active Debt (incl Hybrid) | K32: =IF(OR(I32="",J32=""),"",I32-J32) | L32: 112928.33 | M32: 113669.59 | P32: - | Q32: 22 | R32: 838798 | S32: 22423.13 | T32: 13052.505 | U32: 9370.6247 | V32: 123442.34 | W32: 119553.61 | X32: 0 | Y32: 0 | Z32: - | AA32: 22 | AB32: 846370 | AC32: 13952.958 | AD32: 10819.359 | AE32: 3133.5991 | AF32: 127552.76 | AG32: 126308.64 | AH32: 0 | AI32: 0 | AJ32: - | AK32: 22 | AL32: 849791 | AM32: 21118.171 | AN32: 17981.77 | AO32: 3136.4017 | AP32: 131414.89 | AQ32: 129766.89 | AR32: 0 | AS32: 0 | AT32: - | AU32: 23 | AV32: 854453 | AW32: 27694.835 | AX32: 17928.619 | AY32: 9766.2163 | AZ32: 141985.62 | BA32: 139357.62 | BB32: 0 | BC32: 0 | BD32: - | BE32: 23 | BF32: 857058 | BG32: 17277.481 | BH32: 16800.682 | BI32: 476.79906 | BJ32: 142933.65 | BK32: 145670.67 | BL32: 0 | BM32: 0 | BN32: - | BO32: 23 | BP32: 851734 | BQ32: 26196.109 | BR32: 27449.332 | BS32: -1253.2226 | BT32: 142510.49 | BU32: 141908.54 | BV32: 0 | BW32: 0 | BX32: - | BY32: 23 | BZ32: 850992 | CA32: 21152.528 | CB32: 13635.96 | CC32: 7516.5675 | CD32: 150904.84 | CE32: 149824.38 | CF32: 0 | CG32: 0 | CH32: - | CI32: 23 | CJ32: 852413 | CK32: 20416.172 | CL32: 15435.523 | CM32: 4980.6486 | CN32: 156704.98 | CO32: 154517.11 | CP32: 0 | CQ32: 0 | CR32: - | CS32: 23 | CT32: 851239 | CU32: 16806.604 | CV32: 27052.596 | CW32: -10245.992 | CX32: 147063.58 | CY32: 154652.67 | CZ32: 0 | DA32: 0 | DB32: - | DC32: 24 | DD32: 847633 | DE32: 22871.922 | DF32: 18092.741 | DG32: 4779.1811 | DH32: 152176.23 | DI32: 149428.32 | DJ32: 0 | DK32: 0 | DL32: - | DM32: =S32+AC32+AM32+AW32+BG32+BQ32+CA32+CK32+CU32+DE32 | DN32: =U32+AE32+AO32+AY32+BI32+BS32+CC32+CM32+CW32+DG32 | DO32: - | DP32: =IFERROR((DE32-CU32)/CU32,"-") | DQ32: =IFERROR((DG32-CW32)/CW32,"-") | DR32: =IFERROR((DH32-CX32)/CX32,"-") | DS32: 25 | DT32: 851082 | DU32: 18390.857 | DV32: 16062.111 | DW32: 2328.7458 | DX32: 155468.48 | DY32: 152626.36 | DZ32: 0 | EA32: 0 | EB32: - | EC32: =S32+AC32+AM32+AW32+BG32+BQ32+CA32+CK32+CU32+DE32+DU32 | ED32: =U32+AE32+AO32+AY32+BI32+BS32+CC32+CM32+CW32+DG32+DW32 | EE32: - | EF32: =IFERROR((DU32-DE32)/DE32,"-") | EG32: =IFERROR((DW32-DG32)/DG32,"-") | EH32: =IFERROR((DX32-DH32)/DH32,"-") | EI32: - | EJ32: 25 | EK32: 849973 | EL32: 12597.691 | EM32: 37825.155 | EN32: -25227.465 | EO32: 130570.05 | EP32: 140756.34 | EQ32: 0 | ER32: 0 | ES32: - | ET32: =S32+AC32+AM32+AW32+BG32+BQ32+CA32+CK32+CU32+DE32+DU32+EL32 | EU32: =U32+AE32+AO32+AY32+BI32+BS32+CC32+CM32+CW32+DG32+DW32+EN32 | EV32: - | EW32: =IFERROR((EL32-DU32)/DU32,"-") | EX32: =IFERROR((EN32-DW32)/DW32,"-") | EY32: =IFERROR((EO32-DX32)/DX32,"-")
A33: Fund of funds investing overseas | B33: Other Schemes | C33: Open ended Schemes | D33: Debt | E33: TD | F33: Active Debt (incl Hybrid) | K33: =IF(OR(I33="",J33=""),"",I33-J33) | L33: 25030.809 | M33: 26287.872 | P33: - | Q33: 53 | R33: 1382180 | S33: 334.90833 | T33: 711.73128 | U33: -376.82295 | V33: 24836.171 | W33: 24101.525 | X33: 0 | Y33: 0 | Z33: - | AA33: 53 | AB33: 1377236 | AC33: 394.07504 | AD33: 351.24607 | AE33: 42.828968 | AF33: 27014.149 | AG33: 26413.733 | AH33: 0 | AI33: 0 | AJ33: - | AK33: 52 | AL33: 1375052 | AM33: 406.33591 | AN33: 377.53758 | AO33: 28.798328 | AP33: 28695.428 | AQ33: 27984.342 | AR33: 0 | AS33: 0 | AT33: - | AU33: 52 | AV33: 1391034 | AW33: 562.11439 | AX33: 365.51825 | AY33: 196.59614 | AZ33: 30167.654 | BA33: 29233.809 | BB33: 0 | BC33: 0 | BD33: - | BE33: 52 | BF33: 1415559 | BG33: 789.70459 | BH33: 289.10396 | BI33: 500.60063 | BJ33: 31358.494 | BK33: 30632.01 | BL33: 0 | BM33: 0 | BN33: - | BO33: 52 | BP33: 1483745 | BQ33: 1375.0281 | BR33: 413.09121 | BS33: 961.93688 | BT33: 34424.154 | BU33: 33100.71 | BV33: 0 | BW33: 0 | BX33: - | BY33: 52 | BZ33: 1558989 | CA33: 1333.6908 | CB33: 519.58062 | CC33: 814.11014 | CD33: 36090.864 | CE33: 35039.366 | CF33: 0 | CG33: 0 | CH33: - | CI33: 52 | CJ33: 1612175 | CK33: 753.80522 | CL33: 558.12624 | CM33: 195.67898 | CN33: 35964.968 | CO33: 35287.95 | CP33: 0 | CQ33: 0 | CR33: - | CS33: 52 | CT33: 1638654 | CU33: 829.61513 | CV33: 683.04617 | CW33: 146.56896 | CX33: 36584.529 | CY33: 36466.873 | CZ33: 0 | DA33: 0 | DB33: - | DC33: 52 | DD33: 1682977 | DE33: 1285.5201 | DF33: 404.01517 | DG33: 881.5049 | DH33: 39229.082 | DI33: 38154.742 | DJ33: 0 | DK33: 0 | DL33: - | DM33: =S33+AC33+AM33+AW33+BG33+BQ33+CA33+CK33+CU33+DE33 | DN33: =U33+AE33+AO33+AY33+BI33+BS33+CC33+CM33+CW33+DG33 | DO33: - | DP33: =IFERROR((DE33-CU33)/CU33,"-") | DQ33: =IFERROR((DG33-CW33)/CW33,"-") | DR33: =IFERROR((DH33-CX33)/CX33,"-") | DS33: 52 | DT33: 1727097 | DU33: 1412.5386 | DV33: 508.76545 | DW33: 903.77311 | DX33: 39595.609 | DY33: 38666.724 | DZ33: 0 | EA33: 0 | EB33: - | EC33: =S33+AC33+AM33+AW33+BG33+BQ33+CA33+CK33+CU33+DE33+DU33 | ED33: =U33+AE33+AO33+AY33+BI33+BS33+CC33+CM33+CW33+DG33+DW33 | EE33: - | EF33: =IFERROR((DU33-DE33)/DE33,"-") | EG33: =IFERROR((DW33-DG33)/DG33,"-") | EH33: =IFERROR((DX33-DH33)/DH33,"-") | EI33: - | EJ33: 52 | EK33: 1743628 | EL33: 953.79582 | EM33: 423.04875 | EN33: 530.74707 | EO33: 38286.584 | EP33: 38809.77 | EQ33: 0 | ER33: 0 | ES33: - | ET33: =S33+AC33+AM33+AW33+BG33+BQ33+CA33+CK33+CU33+DE33+DU33+EL33 | EU33: =U33+AE33+AO33+AY33+BI33+BS33+CC33+CM33+CW33+DG33+DW33+EN33 | EV33: - | EW33: =IFERROR((EL33-DU33)/DU33,"-") | EX33: =IFERROR((EN33-DW33)/DW33,"-") | EY33: =IFERROR((EO33-DX33)/DX33,"-")
A34: Fixed Term Plan | B34: Income/Debt Oriented Schemes | C34: Close Ended Schemes | D34: Debt | E34: FMP | F34: Active Debt (incl Hybrid) | K34: =IF(OR(I34="",J34=""),"",I34-J34) | L34: 16140.373 | M34: 16106.762 | P34: - | Q34: 78 | R34: 63022 | S34: 0 | T34: 1202.7044 | U34: -1202.7044 | V34: 15106.624 | W34: 16201.649 | X34: 0 | Y34: 0 | Z34: - | AA34: 76 | AB34: 62288 | AC34: 0 | AD34: 104.25379 | AE34: -104.25379 | AF34: 15121.303 | AG34: 15111.559 | AH34: 0 | AI34: 0 | AJ34: - | AK34: 75 | AL34: 61624 | AM34: 0 | AN34: 144.79821 | AO34: -144.79821 | AP34: 15041.584 | AQ34: 15133.099 | AR34: 0 | AS34: 0 | AT34: - | AU34: 74 | AV34: 60773 | AW34: 0 | AX34: 48.208023 | AY34: -48.208023 | AZ34: 15072.448 | BA34: 15083.256 | BB34: 0 | BC34: 0 | BD34: - | BE34: 74 | BF34: 60773 | BG34: 0 | BH34: 0 | BI34: 0 | BJ34: 15106.009 | BK34: 15091.776 | BL34: 0 | BM34: 0 | BN34: - | BO34: 72 | BP34: 59389 | BQ34: 0 | BR34: 268.76726 | BS34: -268.76726 | BT34: 14896.983 | BU34: 15113.74 | BV34: 0 | BW34: 0 | BX34: - | BY34: 72 | BZ34: 59390 | CA34: 0 | CB34: 0 | CC34: 0 | CD34: 14980.591 | CE34: 14945.837 | CF34: 0 | CG34: 0 | CH34: - | CI34: 71 | CJ34: 56322 | CK34: 0 | CL34: 412.77263 | CM34: -412.77263 | CN34: 14632.225 | CO34: 14728.47 | CP34: 0 | CQ34: 0 | CR34: - | CS34: 71 | CT34: 56328 | CU34: 0 | CV34: 4.9999926e-08 | CW34: -4.9999926e-08 | CX34: 14701.993 | CY34: 14669.487 | CZ34: 0 | DA34: 0 | DB34: - | DC34: 71 | DD34: 56325 | DE34: 0 | DF34: 0 | DG34: 0 | DH34: 14760.993 | DI34: 14731.161 | DJ34: 0 | DK34: 0 | DL34: - | DM34: =S34+AC34+AM34+AW34+BG34+BQ34+CA34+CK34+CU34+DE34 | DN34: =U34+AE34+AO34+AY34+BI34+BS34+CC34+CM34+CW34+DG34 | DO34: - | DP34: 0 | DQ34: =IFERROR((DG34-CW34)/CW34,"-") | DR34: =IFERROR((DH34-CX34)/CX34,"-") | DS34: 72 | DT34: 56636 | DU34: 378.30388 | DV34: 0 | DW34: 378.30388 | DX34: 15215.48 | DY34: 14868.386 | DZ34: 0 | EA34: 0 | EB34: - | EC34: =S34+AC34+AM34+AW34+BG34+BQ34+CA34+CK34+CU34+DE34+DU34 | ED34: =U34+AE34+AO34+AY34+BI34+BS34+CC34+CM34+CW34+DG34+DW34 | EE34: - | EF34: =IFERROR((DU34-DE34)/DE34,"-") | EG34: =IFERROR((DW34-DG34)/DG34,"-") | EH34: =IFERROR((DX34-DH34)/DH34,"-") | EI34: - | EJ34: 73 | EK34: 56845 | EL34: 242.2312 | EM34: 0 | EN34: 242.2312 | EO34: 15506.456 | EP34: 15399.029 | EQ34: 0 | ER34: 0 | ES34: - | ET34: =S34+AC34+AM34+AW34+BG34+BQ34+CA34+CK34+CU34+DE34+DU34+EL34 | EU34: =U34+AE34+AO34+AY34+BI34+BS34+CC34+CM34+CW34+DG34+DW34+EN34 | EV34: - | EW34: =IFERROR((EL34-DU34)/DU34,"-") | EX34: =IFERROR((EN34-DW34)/DW34,"-") | EY34: =IFERROR((EO34-DX34)/DX34,"-")
A35: Gilt Fund with 10 year constant duration | B35: Income/Debt Oriented Schemes | C35: Open ended Schemes | D35: Debt | E35: TD | F35: Active Debt (incl Hybrid) | K35: =IF(OR(I35="",J35=""),"",I35-J35) | L35: 4938.4416 | M35: 4936.3402 | P35: - | Q35: 5 | R35: 36986 | S35: 102.20558 | T35: 140.94137 | U35: -38.735789 | V35: 5006.8885 | W35: 4972.3252 | X35: 0 | Y35: 0 | Z35: - | AA35: 5 | AB35: 37854 | AC35: 118.43985 | AD35: 76.895241 | AE35: 41.544612 | AF35: 5101.4759 | AG35: 5056.9568 | AH35: 0 | AI35: 0 | AJ35: - | AK35: 5 | AL35: 38371 | AM35: 50.872601 | AN35: 192.66065 | AO35: -141.78805 | AP35: 4935.0928 | AQ35: 5024.9166 | AR35: 0 | AS35: 0 | AT35: - | AU35: 5 | AV35: 39036 | AW35: 88.131893 | AX35: 214.33523 | AY35: -126.20334 | AZ35: 4821.7917 | BA35: 4856.6346 | BB35: 0 | BC35: 0 | BD35: - | BE35: 5 | BF35: 39073 | BG35: 328.06059 | BH35: 159.88855 | BI35: 168.17204 | BJ35: 4934.7261 | BK35: 4746.7638 | BL35: 0 | BM35: 0 | BN35: - | BO35: 5 | BP35: 38766 | BQ35: 124.37167 | BR35: 125.89467 | BS35: -1.5230069 | BT35: 4977.9383 | BU35: 5007.8981 | BV35: 0 | BW35: 0 | BX35: - | BY35: 5 | BZ35: 38270 | CA35: 38.579552 | CB35: 63.193693 | CC35: -24.614141 | CD35: 4986.5626 | CE35: 4999.7334 | CF35: 0 | CG35: 0 | CH35: - | CI35: 5 | CJ35: 38070 | CK35: 41.886067 | CL35: 86.081763 | CM35: -44.195696 | CN35: 4973.6862 | CO35: 4981.3776 | CP35: 0 | CQ35: 0 | CR35: - | CS35: 5 | CT35: 37606 | CU35: 43.563285 | CV35: 146.63695 | CW35: -103.07367 | CX35: 4877.1061 | CY35: 4929.8494 | CZ35: 0 | DA35: 0 | DB35: - | DC35: 5 | DD35: 37098 | DE35: 67.392472 | DF35: 80.447911 | DG35: -13.055439 | DH35: 4865.294 | DI35: 4889.2695 | DJ35: 0 | DK35: 0 | DL35: - | DM35: =S35+AC35+AM35+AW35+BG35+BQ35+CA35+CK35+CU35+DE35 | DN35: =U35+AE35+AO35+AY35+BI35+BS35+CC35+CM35+CW35+DG35 | DO35: - | DP35: =IFERROR((DE35-CU35)/CU35,"-") | DQ35: =IFERROR((DG35-CW35)/CW35,"-") | DR35: =IFERROR((DH35-CX35)/CX35,"-") | DS35: 5 | DT35: 36717 | DU35: 350.07922 | DV35: 275.4604 | DW35: 74.618821 | DX35: 4988.1517 | DY35: 4976.548 | DZ35: 0 | EA35: 0 | EB35: - | EC35: =S35+AC35+AM35+AW35+BG35+BQ35+CA35+CK35+CU35+DE35+DU35 | ED35: =U35+AE35+AO35+AY35+BI35+BS35+CC35+CM35+CW35+DG35+DW35 | EE35: - | EF35: =IFERROR((DU35-DE35)/DE35,"-") | EG35: =IFERROR((DW35-DG35)/DG35,"-") | EH35: =IFERROR((DX35-DH35)/DH35,"-") | EI35: - | EJ35: 5 | EK35: 36229 | EL35: 57.984926 | EM35: 439.74713 | EN35: -381.76221 | EO35: 4520.886 | EP35: 4691.2435 | EQ35: 0 | ER35: 0 | ES35: - | ET35: =S35+AC35+AM35+AW35+BG35+BQ35+CA35+CK35+CU35+DE35+DU35+EL35 | EU35: =U35+AE35+AO35+AY35+BI35+BS35+CC35+CM35+CW35+DG35+DW35+EN35 | EV35: - | EW35: =IFERROR((EL35-DU35)/DU35,"-") | EX35: =IFERROR((EN35-DW35)/DW35,"-") | EY35: =IFERROR((EO35-DX35)/DX35,"-")
A36: Floater Fund | B36: Income/Debt Oriented Schemes | C36: Open ended Schemes | D36: Debt | E36: TD | F36: Active Debt (incl Hybrid) | K36: =IF(OR(I36="",J36=""),"",I36-J36) | L36: 49822.039 | M36: 50232.151 | P36: - | Q36: 12 | R36: 197464 | S36: 2171.3677 | T36: 1600.9596 | U36: 570.40814 | V36: 50979.751 | W36: 50844.966 | X36: 0 | Y36: 0 | Z36: - | AA36: 12 | AB36: 198875 | AC36: 1315.7082 | AD36: 1569.7703 | AE36: -254.06211 | AF36: 51205.423 | AG36: 51047.241 | AH36: 0 | AI36: 0 | AJ36: - | AK36: 12 | AL36: 199600 | AM36: 2667.5625 | AN36: 2436.838 | AO36: 230.72446 | AP36: 51668.082 | AQ36: 51830.598 | AR36: 0 | AS36: 0 | AT36: - | AU36: 12 | AV36: 199862 | AW36: 2042.5989 | AX36: 1878.4346 | AY36: 164.16432 | AZ36: 52161.957 | BA36: 51992.376 | BB36: 0 | BC36: 0 | BD36: - | BE36: 12 | BF36: 200291 | BG36: 1737.8239 | BH36: 1942.5393 | BI36: -204.71541 | BJ36: 52030.546 | BK36: 52456.254 | BL36: 0 | BM36: 0 | BN36: - | BO36: 12 | BP36: 199240 | BQ36: 984.69171 | BR36: 2510.776 | BS36: -1526.0843 | BT36: 50821.355 | BU36: 51615.005 | BV36: 0 | BW36: 0 | BX36: - | BY36: 12 | BZ36: 198921 | CA36: 1266.3228 | CB36: 1528.8646 | CC36: -262.54177 | CD36: 50931.096 | CE36: 50918.404 | CF36: 0 | CG36: 0 | CH36: - | CI36: 12 | CJ36: 199167 | CK36: 1477.7135 | CL36: 1385.8314 | CM36: 91.882139 | CN36: 51333.579 | CO36: 51199.961 | CP36: 0 | CQ36: 0 | CR36: - | CS36: 12 | CT36: 198710 | CU36: 2723.2888 | CV36: 2000.853 | CW36: 722.43576 | CX36: 52217.242 | CY36: 51726.613 | CZ36: 0 | DA36: 0 | DB36: - | DC36: 12 | DD36: 197564 | DE36: 1890.3955 | DF36: 1621.9802 | DG36: 268.4153 | DH36: 52573.192 | DI36: 52680.265 | DJ36: 0 | DK36: 0 | DL36: - | DM36: =S36+AC36+AM36+AW36+BG36+BQ36+CA36+CK36+CU36+DE36 | DN36: =U36+AE36+AO36+AY36+BI36+BS36+CC36+CM36+CW36+DG36 | DO36: - | DP36: =IFERROR((DE36-CU36)/CU36,"-") | DQ36: =IFERROR((DG36-CW36)/CW36,"-") | DR36: =IFERROR((DH36-CX36)/CX36,"-") | DS36: 12 | DT36: 198069 | DU36: 1368.0794 | DV36: 1312.197 | DW36: 55.882415 | DX36: 53026.734 | DY36: 52822.787 | DZ36: 0 | EA36: 0 | EB36: - | EC36: =S36+AC36+AM36+AW36+BG36+BQ36+CA36+CK36+CU36+DE36+DU36 | ED36: =U36+AE36+AO36+AY36+BI36+BS36+CC36+CM36+CW36+DG36+DW36 | EE36: - | EF36: =IFERROR((DU36-DE36)/DE36,"-") | EG36: =IFERROR((DW36-DG36)/DG36,"-") | EH36: =IFERROR((DX36-DH36)/DH36,"-") | EI36: - | EJ36: 12 | EK36: 197183 | EL36: 1960.8524 | EM36: 3750.5745 | EN36: -1789.7221 | EO36: 51283.188 | EP36: 51967.37 | EQ36: 0 | ER36: 0 | ES36: - | ET36: =S36+AC36+AM36+AW36+BG36+BQ36+CA36+CK36+CU36+DE36+DU36+EL36 | EU36: =U36+AE36+AO36+AY36+BI36+BS36+CC36+CM36+CW36+DG36+DW36+EN36 | EV36: - | EW36: =IFERROR((EL36-DU36)/DU36,"-") | EX36: =IFERROR((EN36-DW36)/DW36,"-") | EY36: =IFERROR((EO36-DX36)/DX36,"-")
A37: Capital Protection Oriented Schemes | B37: Income/Debt Oriented Schemes | C37: Close Ended Schemes | D37: Debt | E37: TD | F37: Active Debt (incl Hybrid) | K37: =IF(OR(I37="",J37=""),"",I37-J37) | L37: 0 | M37: 0 | P37: - | Q37: 0 | R37: 0 | S37: 0 | T37: 0 | U37: 0 | V37: 0 | W37: 0 | X37: 0 | Y37: 0 | Z37: - | AA37: 0 | AB37: 0 | AC37: 0 | AD37: 0 | AE37: 0 | AF37: 0 | AG37: 0 | AH37: 0 | AI37: 0 | AJ37: - | AK37: 0 | AL37: 0 | AM37: 0 | AN37: 0 | AO37: 0 | AP37: 0 | AQ37: 0 | AR37: 0 | AS37: 0 | AT37: - | AU37: 0 | AV37: 0 | AW37: 0 | AX37: 0 | AY37: 0 | AZ37: 0 | BA37: 0 | BB37: 0 | BC37: 0 | BD37: - | BE37: 0 | BF37: 0 | BG37: 0 | BH37: 0 | BI37: 0 | BJ37: 0 | BK37: 0 | BL37: 0 | BM37: 0 | BN37: - | BO37: 0 | BP37: 0 | BQ37: 0 | BR37: 0 | BS37: 0 | BT37: 0 | BU37: 0 | BV37: 0 | BW37: 0 | BX37: - | BY37: 0 | BZ37: 0 | CA37: 0 | CB37: 0 | CC37: 0 | CD37: 0 | CE37: 0 | CF37: 0 | CG37: 0 | CH37: - | CI37: 0 | CJ37: 0 | CK37: 0 | CL37: 0 | CM37: 0 | CN37: 0 | CO37: 0 | CP37: 0 | CQ37: 0 | CR37: - | CS37: 0 | CT37: 0 | CU37: 0 | CV37: 0 | CW37: 0 | CX37: 0 | CY37: 0 | CZ37: 0 | DA37: 0 | DB37: - | DC37: 0 | DD37: 0 | DE37: 0 | DF37: 0 | DG37: 0 | DH37: 0 | DI37: 0 | DJ37: 0 | DK37: 0 | DL37: - | DM37: =S37+AC37+AM37+AW37+BG37+BQ37+CA37+CK37+CU37+DE37 | DN37: =U37+AE37+AO37+AY37+BI37+BS37+CC37+CM37+CW37+DG37 | DO37: - | DP37: 0 | DQ37: 0 | DR37: 0 | DS37: 0 | DT37: 0 | DU37: 0 | DV37: 0 | DW37: 0 | DX37: 0 | DY37: 0 | DZ37: 0 | EA37: 0 | EB37: - | EC37: =S37+AC37+AM37+AW37+BG37+BQ37+CA37+CK37+CU37+DE37+DU37 | ED37: =U37+AE37+AO37+AY37+BI37+BS37+CC37+CM37+CW37+DG37+DW37 | EE37: - | EF37: =IFERROR((DU37-DE37)/DE37,"-") | EG37: =IFERROR((DW37-DG37)/DG37,"-") | EH37: =IFERROR((DX37-DH37)/DH37,"-") | EI37: - | EJ37: 0 | EK37: 0 | EL37: 0 | EM37: 0 | EN37: 0 | EO37: 0 | EP37: 0 | EQ37: 0 | ER37: 0 | ES37: - | ET37: =S37+AC37+AM37+AW37+BG37+BQ37+CA37+CK37+CU37+DE37+DU37+EL37 | EU37: =U37+AE37+AO37+AY37+BI37+BS37+CC37+CM37+CW37+DG37+DW37+EN37 | EV37: - | EW37: =IFERROR((EL37-DU37)/DU37,"-") | EX37: =IFERROR((EN37-DW37)/DW37,"-") | EY37: =IFERROR((EO37-DX37)/DX37,"-")
A38: Infrastructure Debt Fund | B38: Income/Debt Oriented Schemes | C38: Close Ended Schemes | D38: Debt | E38: TD | F38: Active Debt (incl Hybrid) | K38: =IF(OR(I38="",J38=""),"",I38-J38) | L38: 1112.5221 | M38: 1109.2021 | P38: - | Q38: 4 | R38: 30 | S38: 0 | T38: 0 | U38: 0 | V38: 1119.267 | W38: 1116.0066 | X38: 0 | Y38: 0 | Z38: - | AA38: 3 | AB38: 19 | AC38: 0 | AD38: 261.85378 | AE38: -261.85378 | AF38: 862.96336 | AG38: 1122.1403 | AH38: 0 | AI38: 0 | AJ38: - | AK38: 3 | AL38: 19 | AM38: 0 | AN38: 0 | AO38: 0 | AP38: 868.08375 | AQ38: 865.59715 | AR38: 0 | AS38: 0 | AT38: - | AU38: 3 | AV38: 19 | AW38: 0 | AX38: 0 | AY38: 0 | AZ38: 875.15735 | BA38: 871.00643 | BB38: 0 | BC38: 0 | BD38: - | BE38: 3 | BF38: 19 | BG38: 0 | BH38: 0 | BI38: 0 | BJ38: 881.18048 | BK38: 878.15887 | BL38: 0 | BM38: 0 | BN38: - | BO38: 3 | BP38: 19 | BQ38: 0 | BR38: 0 | BS38: 0 | BT38: 887.20392 | BU38: 884.70204 | BV38: 0 | BW38: 0 | BX38: - | BY38: 3 | BZ38: 19 | CA38: 0 | CB38: 0 | CC38: 0 | CD38: 893.52669 | CE38: 890.96574 | CF38: 0 | CG38: 0 | CH38: - | CI38: 3 | CJ38: 19 | CK38: 0 | CL38: 0 | CM38: 0 | CN38: 898.53745 | CO38: 896.11789 | CP38: 0 | CQ38: 0 | CR38: - | CS38: 3 | CT38: 19 | CU38: 0 | CV38: 0 | CW38: 0 | CX38: 903.44919 | CY38: 901.08086 | CZ38: 0 | DA38: 0 | DB38: - | DC38: 3 | DD38: 19 | DE38: 0 | DF38: 0 | DG38: 0 | DH38: 908.4087 | DI38: 906.00816 | DJ38: 0 | DK38: 0 | DL38: - | DM38: =S38+AC38+AM38+AW38+BG38+BQ38+CA38+CK38+CU38+DE38 | DN38: =U38+AE38+AO38+AY38+BI38+BS38+CC38+CM38+CW38+DG38 | DO38: - | DP38: 0 | DQ38: 0 | DR38: =IFERROR((DH38-CX38)/CX38,"-") | DS38: 3 | DT38: 19 | DU38: 0 | DV38: 0 | DW38: 0 | DX38: 913.73542 | DY38: 910.84038 | DZ38: 0 | EA38: 0 | EB38: - | EC38: =S38+AC38+AM38+AW38+BG38+BQ38+CA38+CK38+CU38+DE38+DU38 | ED38: =U38+AE38+AO38+AY38+BI38+BS38+CC38+CM38+CW38+DG38+DW38 | EE38: - | EF38: =IFERROR((DU38-DE38)/DE38,"-") | EG38: =IFERROR((DW38-DG38)/DG38,"-") | EH38: =IFERROR((DX38-DH38)/DH38,"-") | EI38: - | EJ38: 3 | EK38: 19 | EL38: 0 | EM38: 0 | EN38: 0 | EO38: 919.61535 | EP38: 916.84842 | EQ38: 0 | ER38: 0 | ES38: - | ET38: =S38+AC38+AM38+AW38+BG38+BQ38+CA38+CK38+CU38+DE38+DU38+EL38 | EU38: =U38+AE38+AO38+AY38+BI38+BS38+CC38+CM38+CW38+DG38+DW38+EN38 | EV38: - | EW38: =IFERROR((EL38-DU38)/DU38,"-") | EX38: =IFERROR((EN38-DW38)/DW38,"-") | EY38: =IFERROR((EO38-DX38)/DX38,"-")
A39: Income/Debt Oriented Schemes | B39: Interval Schemes | C39: - | D39: Debt | E39: FMP | F39: Active Debt (incl Hybrid) | K39: =IF(OR(I39="",J39=""),"",I39-J39) | L39: 97.3424 | M39: 114.2623 | P39: - | Q39: 4 | R39: 1007 | S39: 0.0003 | T39: 0.0533 | U39: -0.053 | V39: 66.1936 | W39: 94.2621 | X39: 0 | Y39: 0 | Z39: - | AA39: 4 | AB39: 998 | AC39: 0 | AD39: 27.2701 | AE39: -27.2701 | AF39: 43.8637 | AG39: 78.4893 | AH39: 0 | AI39: 0 | AJ39: - | AK39: 4 | AL39: 998 | AM39: 0 | AN39: 0 | AO39: 0 | AP39: 44.0718 | AQ39: 60.0781 | AR39: 0 | AS39: 0 | AT39: - | AU39: 4 | AV39: 998 | AW39: 0 | AX39: 0 | AY39: 0 | AZ39: 44.2663 | BA39: 60.3538 | BB39: 0 | BC39: 0 | BD39: - | BE39: 4 | BF39: 989 | BG39: 0 | BH39: 11.4379 | BI39: -11.4379 | BJ39: 40.7116 | BK39: 51.7732 | BL39: 0 | BM39: 0 | BN39: - | BO39: 4 | BP39: 939 | BQ39: 0 | BR39: 2.52 | BS39: -2.52 | BT39: 38.3777 | BU39: 47.5938 | BV39: 0 | BW39: 0 | BX39: - | BY39: 4 | BZ39: 938 | CA39: 0 | CB39: 0 | CC39: 0 | CD39: 38.5598 | CE39: 47.1089 | CF39: 0 | CG39: 0 | CH39: - | CI39: 3 | CJ39: 914 | CK39: 0 | CL39: 0.03 | CM39: -0.03 | CN39: 30.0186 | CO39: 45.6389 | CP39: 0 | CQ39: 0 | CR39: - | CS39: 3 | CT39: 914 | CU39: 0 | CV39: 0 | CW39: 0 | CX39: 30.1637 | CY39: 39.1507 | CZ39: 0 | DA39: 0 | DB39: - | DC39: 3 | DD39: 914 | DE39: 0 | DF39: 0 | DG39: 0 | DH39: 30.1637 | DI39: 39.1507 | DJ39: 0 | DK39: 0 | DL39: - | DM39: =S39+AC39+AM39+AW39+BG39+BQ39+CA39+CK39+CU39+DE39 | DN39: =U39+AE39+AO39+AY39+BI39+BS39+CC39+CM39+CW39+DG39 | DO39: - | DP39: 0 | DQ39: 0 | DR39: =IFERROR((DH39-CX39)/CX39,"-") | DS39: 3 | DT39: 911 | DU39: 0 | DV39: 0.2005 | DW39: -0.2005 | DX39: 30.3325 | DY39: 39.3426 | DZ39: 0 | EA39: 0 | EB39: - | EC39: =S39+AC39+AM39+AW39+BG39+BQ39+CA39+CK39+CU39+DE39+DU39 | ED39: =U39+AE39+AO39+AY39+BI39+BS39+CC39+CM39+CW39+DG39+DW39 | EE39: - | EF39: =IFERROR((DU39-DE39)/DE39,"-") | EG39: =IFERROR((DW39-DG39)/DG39,"-") | EH39: =IFERROR((DX39-DH39)/DH39,"-") | EI39: - | EJ39: 0 | EK39: 0 | EL39: 0 | EM39: 0 | EN39: 0 | EO39: 0 | EP39: 0 | EQ39: 0 | ER39: 0 | ES39: - | ET39: =S39+AC39+AM39+AW39+BG39+BQ39+CA39+CK39+CU39+DE39+DU39+EL39 | EU39: =U39+AE39+AO39+AY39+BI39+BS39+CC39+CM39+CW39+DG39+DW39+EN39 | EV39: - | EW39: =IFERROR((EL39-DU39)/DU39,"-") | EX39: =IFERROR((EN39-DW39)/DW39,"-") | EY39: =IFERROR((EO39-DX39)/DX39,"-")
A40: Gilt Fund | B40: Income/Debt Oriented Schemes | C40: Open ended Schemes | D40: Debt | E40: TD | F40: Active Debt (incl Hybrid) | K40: =IF(OR(I40="",J40=""),"",I40-J40) | L40: 40989.936 | M40: 40630.628 | P40: - | Q40: 22 | R40: 223026 | S40: 2544.9733 | T40: 2970.023 | U40: -425.04971 | V40: 41428.662 | W40: 41038.384 | X40: 0 | Y40: 0 | Z40: - | AA40: 23 | AB40: 232237 | AC40: 2738.6612 | AD40: 1352.7321 | AE40: 1385.929 | AF40: 43000.141 | AG40: 42256.264 | AH40: 0 | AI40: 0 | AJ40: - | AK40: 23 | AL40: 232057 | AM40: 1562.0074 | AN40: 2519.3305 | AO40: -957.3231 | AP40: 41449.723 | AQ40: 42294.944 | AR40: 0 | AS40: 0 | AT40: - | AU40: 23 | AV40: 232098 | AW40: 1929.8526 | AX40: 1769.8023 | AY40: 160.05027 | AZ40: 41789.563 | BA40: 42149.903 | BB40: 0 | BC40: 0 | BD40: - | BE40: 23 | BF40: 229584 | BG40: 2330.755 | BH40: 3259.1759 | BI40: -928.42093 | BJ40: 40089.971 | BK40: 40439.257 | BL40: 0 | BM40: 0 | BN40: - | BO40: 23 | BP40: 225769 | BQ40: 2178.0677 | BR40: 2793.0571 | BS40: -614.98936 | BT40: 40055.168 | BU40: 40635.104 | BV40: 0 | BW40: 0 | BX40: - | BY40: 23 | BZ40: 222590 | CA40: 507.6834 | CB40: 1438.671 | CC40: -930.98758 | CD40: 39325.017 | CE40: 39916.685 | CF40: 0 | CG40: 0 | CH40: - | CI40: 23 | CJ40: 219637 | CK40: 499.72913 | CL40: 676.27553 | CM40: -176.5464 | CN40: 39160.963 | CO40: 39290.829 | CP40: 0 | CQ40: 0 | CR40: - | CS40: 23 | CT40: 215424 | CU40: 516.58775 | CV40: 1312.7819 | CW40: -796.19414 | CX40: 38514.725 | CY40: 38808.925 | CZ40: 0 | DA40: 0 | DB40: - | DC40: 23 | DD40: 211129 | DE40: 459.22893 | DF40: 1887.7218 | DG40: -1428.4928 | DH40: 37115.927 | DI40: 37810.513 | DJ40: 0 | DK40: 0 | DL40: - | DM40: =S40+AC40+AM40+AW40+BG40+BQ40+CA40+CK40+CU40+DE40 | DN40: =U40+AE40+AO40+AY40+BI40+BS40+CC40+CM40+CW40+DG40 | DO40: - | DP40: =IFERROR((DE40-CU40)/CU40,"-") | DQ40: =IFERROR((DG40-CW40)/CW40,"-") | DR40: =IFERROR((DH40-CX40)/CX40,"-") | DS40: 23 | DT40: 208248 | DU40: 1263.9571 | DV40: 1272.8628 | DW40: -8.9056685 | DX40: 37363.217 | DY40: 36854.201 | DZ40: 0 | EA40: 0 | EB40: - | EC40: =S40+AC40+AM40+AW40+BG40+BQ40+CA40+CK40+CU40+DE40+DU40 | ED40: =U40+AE40+AO40+AY40+BI40+BS40+CC40+CM40+CW40+DG40+DW40 | EE40: - | EF40: =IFERROR((DU40-DE40)/DE40,"-") | EG40: =IFERROR((DW40-DG40)/DG40,"-") | EH40: =IFERROR((DX40-DH40)/DH40,"-") | EI40: - | EJ40: 23 | EK40: 203580 | EL40: 907.17009 | EM40: 3985.5693 | EN40: -3078.3992 | EO40: 33620.532 | EP40: 35383.493 | EQ40: 0 | ER40: 0 | ES40: - | ET40: =S40+AC40+AM40+AW40+BG40+BQ40+CA40+CK40+CU40+DE40+DU40+EL40 | EU40: =U40+AE40+AO40+AY40+BI40+BS40+CC40+CM40+CW40+DG40+DW40+EN40 | EV40: - | EW40: =IFERROR((EL40-DU40)/DU40,"-") | EX40: =IFERROR((EN40-DW40)/DW40,"-") | EY40: =IFERROR((EO40-DX40)/DX40,"-")
A41: Other Debt Scheme | B41: Income/Debt Oriented Schemes | C41: Close Ended Schemes | D41: Debt | E41: TD | F41: Active Debt (incl Hybrid) | K41: =IF(OR(I41="",J41=""),"",I41-J41) | L41: 5319.12 | M41: 5265.41 | P41: - | Q41: 1 | R41: 190744 | S41: 18.4 | T41: 61.28 | U41: -42.88 | V41: 5434.4 | W41: 5382.59 | X41: 0 | Y41: 0 | Z41: - | AA41: 1 | AB41: 189044 | AC41: 15.43 | AD41: 68.14 | AE41: -52.71 | AF41: 5451.34 | AG41: 5457.69 | AH41: 0 | AI41: 0 | AJ41: - | AK41: 1 | AL41: 187506 | AM41: 15.55 | AN41: 58.91 | AO41: -43.36 | AP41: 5472.76 | AQ41: 5464.72 | AR41: 0 | AS41: 0 | AT41: - | AU41: 1 | AV41: 185895 | AW41: 15.79 | AX41: 68.66 | AY41: -52.87 | AZ41: 5361.28 | BA41: 5445.48 | BB41: 0 | BC41: 0 | BD41: - | BE41: 1 | BF41: 184690 | BG41: 14.32 | BH41: 48.19 | BI41: -33.87 | BJ41: 5287.88 | BK41: 5358.01 | BL41: 0 | BM41: 0 | BN41: - | BO41: 1 | BP41: 183213 | BQ41: 15.3 | BR41: 57.76 | BS41: -42.46 | BT41: 5278.36 | BU41: 5363.34 | BV41: 0 | BW41: 0 | BX41: - | BY41: 1 | BZ41: 181974 | CA41: 14.53 | CB41: 73.26 | CC41: -58.73 | CD41: 5307.27 | CE41: 5349.38 | CF41: 0 | CG41: 0 | CH41: - | CI41: 1 | CJ41: 180825 | CK41: 14.16 | CL41: 51.23 | CM41: -37.07 | CN41: 5284.85 | CO41: 5309.67 | CP41: 0 | CQ41: 0 | CR41: - | CS41: 1 | CT41: 179801 | CU41: 15.74 | CV41: 55.01 | CW41: -39.27 | CX41: 5195.84 | CY41: 5243.3 | CZ41: 0 | DA41: 0 | DB41: - | DC41: 1 | DD41: 178857 | DE41: 15.41 | DF41: 49.47 | DG41: -34.06 | DH41: 5067.75 | DI41: 5149.78 | DJ41: 0 | DK41: 0 | DL41: - | DM41: =S41+AC41+AM41+AW41+BG41+BQ41+CA41+CK41+CU41+DE41 | DN41: =U41+AE41+AO41+AY41+BI41+BS41+CC41+CM41+CW41+DG41 | DO41: - | DP41: =IFERROR((DE41-CU41)/CU41,"-") | DQ41: =IFERROR((DG41-CW41)/CW41,"-") | DR41: =IFERROR((DH41-CX41)/CX41,"-") | DS41: 1 | DT41: 177809 | DU41: 14.99 | DV41: 44.27 | DW41: -29.28 | DX41: 5019.12 | DY41: 5088.88 | DZ41: 0 | EA41: 0 | EB41: - | EC41: =S41+AC41+AM41+AW41+BG41+BQ41+CA41+CK41+CU41+DE41+DU41 | ED41: =U41+AE41+AO41+AY41+BI41+BS41+CC41+CM41+CW41+DG41+DW41 | EE41: - | EF41: =IFERROR((DU41-DE41)/DE41,"-") | EG41: =IFERROR((DW41-DG41)/DG41,"-") | EH41: =IFERROR((DX41-DH41)/DH41,"-") | EI41: - | EJ41: 1 | EK41: 176949 | EL41: 19.47 | EM41: 35.91 | EN41: -16.44 | EO41: 4748.07 | EP41: 4891.44 | EQ41: 0 | ER41: 0 | ES41: - | ET41: =S41+AC41+AM41+AW41+BG41+BQ41+CA41+CK41+CU41+DE41+DU41+EL41 | EU41: =U41+AE41+AO41+AY41+BI41+BS41+CC41+CM41+CW41+DG41+DW41+EN41 | EV41: - | EW41: =IFERROR((EL41-DU41)/DU41,"-") | EX41: =IFERROR((EN41-DW41)/DW41,"-") | EY41: =IFERROR((EO41-DX41)/DX41,"-")
A42: Conservative Hybrid Fund | B42: Hybrid Schemes | C42: Open ended Schemes | D42: Debt | E42: Debt-Hybrid Schemes | F42: Active Debt (incl Hybrid) | K42: =IF(OR(I42="",J42=""),"",I42-J42) | L42: 28124.486 | M42: 27918.753 | P42: - | Q42: 18 | R42: 550659 | S42: 311.47521 | T42: 547.87967 | U42: -236.40447 | V42: 28359.406 | W42: 28180.969 | X42: 1 | Y42: 0 | Z42: - | AA42: 18 | AB42: 555080 | AC42: 470.82033 | AD42: 381.51205 | AE42: 89.308282 | AF42: 28825.348 | AG42: 28579.258 | AH42: 1 | AI42: 0 | AJ42: - | AK42: 18 | AL42: 560827 | AM42: 496.8487 | AN42: 358.6726 | AO42: 138.1761 | AP42: 29084.829 | AQ42: 28953.165 | AR42: 1 | AS42: 0 | AT42: - | AU42: 18 | AV42: 566649 | AW42: 738.40746 | AX42: 430.23693 | AY42: 308.17053 | AZ42: 29421.042 | BA42: 29335.745 | BB42: 1 | BC42: 0 | BD42: - | BE42: 18 | BF42: 570583 | BG42: 390.5968 | BH42: 346.97811 | BI42: 43.618684 | BJ42: 29268.178 | BK42: 29406.615 | BL42: 1 | BM42: 0 | BN42: - | BO42: 18 | BP42: 572447 | BQ42: 400.75326 | BR42: 446.74662 | BS42: -45.993352 | BT42: 29492.114 | BU42: 29523.281 | BV42: 1 | BW42: 0 | BX42: - | BY42: 18 | BZ42: 573771 | CA42: 479.64239 | CB42: 477.80318 | CC42: 1.8392094 | CD42: 29877.701 | CE42: 29834.404 | CF42: 1 | CG42: 0 | CH42: - | CI42: 18 | CJ42: 575592 | CK42: 367.15741 | CL42: 461.62356 | CM42: -94.466143 | CN42: 29936.938 | CO42: 29947.102 | CP42: 1 | CQ42: 0 | CR42: - | CS42: 18 | CT42: 575909 | CU42: 381.58755 | CV42: 499.98232 | CW42: -118.39477 | CX42: 29769.236 | CY42: 29829.432 | CZ42: 1 | DA42: 0 | DB42: - | DC42: 18 | DD42: 576220 | DE42: 424.27987 | DF42: 501.49357 | DG42: -77.213703 | DH42: 29527.204 | DI42: 29674.297 | DJ42: 1 | DK42: 0 | DL42: - | DM42: =S42+AC42+AM42+AW42+BG42+BQ42+CA42+CK42+CU42+DE42 | DN42: =U42+AE42+AO42+AY42+BI42+BS42+CC42+CM42+CW42+DG42 | DO42: - | DP42: =IFERROR((DE42-CU42)/CU42,"-") | DQ42: =IFERROR((DG42-CW42)/CW42,"-") | DR42: =IFERROR((DH42-CX42)/CX42,"-") | DS42: 18 | DT42: 579547 | DU42: 369.64113 | DV42: 437.50884 | DW42: -67.867707 | DX42: 29737.158 | DY42: 29744.412 | DZ42: 1 | EA42: 0 | EB42: - | EC42: =S42+AC42+AM42+AW42+BG42+BQ42+CA42+CK42+CU42+DE42+DU42 | ED42: =U42+AE42+AO42+AY42+BI42+BS42+CC42+CM42+CW42+DG42+DW42 | EE42: - | EF42: =IFERROR((DU42-DE42)/DE42,"-") | EG42: =IFERROR((DW42-DG42)/DG42,"-") | EH42: =IFERROR((DX42-DH42)/DH42,"-") | EI42: - | EJ42: 18 | EK42: 580399 | EL42: 354.21965 | EM42: 572.56668 | EN42: -218.34703 | EO42: 28648.537 | EP42: 29226.46 | EQ42: 1 | ER42: 0 | ES42: - | ET42: =S42+AC42+AM42+AW42+BG42+BQ42+CA42+CK42+CU42+DE42+DU42+EL42 | EU42: =U42+AE42+AO42+AY42+BI42+BS42+CC42+CM42+CW42+DG42+DW42+EN42 | EV42: - | EW42: =IFERROR((EL42-DU42)/DU42,"-") | EX42: =IFERROR((EN42-DW42)/DW42,"-") | EY42: =IFERROR((EO42-DX42)/DX42,"-")
A43: Medium Duration Fund | B43: Income/Debt Oriented Schemes | C43: Open ended Schemes | D43: Debt | E43: TD | F43: Active Debt (incl Hybrid) | K43: =IF(OR(I43="",J43=""),"",I43-J43) | L43: 24666.495 | M43: 24832.793 | P43: - | Q43: 13 | R43: 219285 | S43: 665.09614 | T43: 530.96891 | U43: 134.12722 | V43: 25163.719 | W43: 25082.716 | X43: 2 | Y43: 0 | Z43: - | AA43: 13 | AB43: 223104 | AC43: 345.6711 | AD43: 392.77687 | AE43: -47.10577 | AF43: 25365.585 | AG43: 25294.927 | AH43: 2 | AI43: 0 | AJ43: - | AK43: 13 | AL43: 226670 | AM43: 378.53568 | AN43: 439.51408 | AO43: -60.978397 | AP43: 25335.977 | AQ43: 25330.049 | AR43: 2 | AS43: 0 | AT43: - | AU43: 13 | AV43: 230916 | AW43: 582.91793 | AX43: 558.94179 | AY43: 23.97614 | AZ43: 25513.38 | BA43: 25549.304 | BB43: 2 | BC43: 0 | BD43: - | BE43: 13 | BF43: 233423 | BG43: 502.31552 | BH43: 390.34262 | BI43: 111.9729 | BJ43: 25590.072 | BK43: 25600.142 | BL43: 2 | BM43: 0 | BN43: - | BO43: 13 | BP43: 234720 | BQ43: 794.73203 | BR43: 951.57533 | BS43: -156.8433 | BT43: 25661.931 | BU43: 25664.171 | BV43: 2 | BW43: 0 | BX43: - | BY43: 13 | BZ43: 236962 | CA43: 684.79692 | CB43: 295.27872 | CC43: 389.5182 | CD43: 26254.412 | CE43: 26080.473 | CF43: 2 | CG43: 0 | CH43: - | CI43: 13 | CJ43: 239520 | CK43: 385.63071 | CL43: 399.25632 | CM43: -13.625614 | CN43: 26406.047 | CO43: 26318.324 | CP43: 2 | CQ43: 0 | CR43: - | CS43: 13 | CT43: 240819 | CU43: 412.92307 | CV43: 642.23622 | CW43: -229.31315 | CX43: 26252.287 | CY43: 26375.754 | CZ43: 2 | DA43: 0 | DB43: - | DC43: 13 | DD43: 240538 | DE43: 276.48161 | DF43: 384.11134 | DG43: -107.62972 | DH43: 26229.008 | DI43: 26273.4 | DJ43: 2 | DK43: 0 | DL43: - | DM43: =S43+AC43+AM43+AW43+BG43+BQ43+CA43+CK43+CU43+DE43 | DN43: =U43+AE43+AO43+AY43+BI43+BS43+CC43+CM43+CW43+DG43 | DO43: - | DP43: =IFERROR((DE43-CU43)/CU43,"-") | DQ43: =IFERROR((DG43-CW43)/CW43,"-") | DR43: =IFERROR((DH43-CX43)/CX43,"-") | DS43: 13 | DT43: 241737 | DU43: 387.83615 | DV43: 458.09266 | DW43: -70.256516 | DX43: 26376.919 | DY43: 26281.138 | DZ43: 2 | EA43: 0 | EB43: - | EC43: =S43+AC43+AM43+AW43+BG43+BQ43+CA43+CK43+CU43+DE43+DU43 | ED43: =U43+AE43+AO43+AY43+BI43+BS43+CC43+CM43+CW43+DG43+DW43 | EE43: - | EF43: =IFERROR((DU43-DE43)/DE43,"-") | EG43: =IFERROR((DW43-DG43)/DG43,"-") | EH43: =IFERROR((DX43-DH43)/DH43,"-") | EI43: - | EJ43: 13 | EK43: 240909 | EL43: 1728.8406 | EM43: 2443.1519 | EN43: -714.3113 | EO43: 25528.54 | EP43: 25990.305 | EQ43: 2 | ER43: 0 | ES43: - | ET43: =S43+AC43+AM43+AW43+BG43+BQ43+CA43+CK43+CU43+DE43+DU43+EL43 | EU43: =U43+AE43+AO43+AY43+BI43+BS43+CC43+CM43+CW43+DG43+DW43+EN43 | EV43: - | EW43: =IFERROR((EL43-DU43)/DU43,"-") | EX43: =IFERROR((EN43-DW43)/DW43,"-") | EY43: =IFERROR((EO43-DX43)/DX43,"-")
A44: Credit Risk Fund | B44: Income/Debt Oriented Schemes | C44: Open ended Schemes | D44: Debt | E44: TD | F44: Active Debt (incl Hybrid) | K44: =IF(OR(I44="",J44=""),"",I44-J44) | L44: 20462.727 | M44: 20507.47 | P44: - | Q44: 14 | R44: 181652 | S44: 71.228381 | T44: 372.91809 | U44: -301.68971 | V44: 20485.355 | W44: 20475.684 | X44: 4 | Y44: 0 | Z44: - | AA44: 14 | AB44: 182494 | AC44: 59.359964 | AD44: 307.29462 | AE44: -247.93465 | AF44: 20437.001 | AG44: 20457.269 | AH44: 4 | AI44: 0 | AJ44: - | AK44: 14 | AL44: 183524 | AM44: 103.10758 | AN44: 271.28981 | AO44: -168.18222 | AP44: 20349.89 | AQ44: 20396.086 | AR44: 4 | AS44: 0 | AT44: - | AU44: 14 | AV44: 185095 | AW44: 81.487468 | AX44: 353.00245 | AY44: -271.51498 | AZ44: 20229.413 | BA44: 20304.908 | BB44: 4 | BC44: 0 | BD44: - | BE44: 14 | BF44: 186961 | BG44: 86.343821 | BH44: 329.91117 | BI44: -243.56735 | BJ44: 20028.426 | BK44: 20110.692 | BL44: 4 | BM44: 0 | BN44: - | BO44: 14 | BP44: 188983 | BQ44: 95.337441 | BR44: 350.99378 | BS44: -255.65634 | BT44: 19949.78 | BU44: 20018.727 | BV44: 4 | BW44: 0 | BX44: - | BY44: 14 | BZ44: 191121 | CA44: 254.11933 | CB44: 337.90036 | CC44: -83.781032 | CD44: 20018.427 | CE44: 20050.959 | CF44: 4 | CG44: 0 | CH44: - | CI44: 14 | CJ44: 193115 | CK44: 118.46636 | CL44: 236.3367 | CM44: -117.87034 | CN44: 20028.149 | CO44: 20016.615 | CP44: 4 | CQ44: 0 | CR44: - | CS44: 14 | CT44: 194207 | CU44: 130.15949 | CV44: 302.77149 | CW44: -172.612 | CX44: 19929.945 | CY44: 19965.059 | CZ44: 4 | DA44: 0 | DB44: - | DC44: 14 | DD44: 196410 | DE44: 172.69281 | DF44: 298.54252 | DG44: -125.84971 | DH44: 19893.225 | DI44: 19933.059 | DJ44: 4 | DK44: 0 | DL44: - | DM44: =S44+AC44+AM44+AW44+BG44+BQ44+CA44+CK44+CU44+DE44 | DN44: =U44+AE44+AO44+AY44+BI44+BS44+CC44+CM44+CW44+DG44 | DO44: - | DP44: =IFERROR((DE44-CU44)/CU44,"-") | DQ44: =IFERROR((DG44-CW44)/CW44,"-") | DR44: =IFERROR((DH44-CX44)/CX44,"-") | DS44: 14 | DT44: 199856 | DU44: 167.7283 | DV44: 261.91829 | DW44: -94.189989 | DX44: 19966.418 | DY44: 19934.924 | DZ44: 4 | EA44: 0 | EB44: - | EC44: =S44+AC44+AM44+AW44+BG44+BQ44+CA44+CK44+CU44+DE44+DU44 | ED44: =U44+AE44+AO44+AY44+BI44+BS44+CC44+CM44+CW44+DG44+DW44 | EE44: - | EF44: =IFERROR((DU44-DE44)/DE44,"-") | EG44: =IFERROR((DW44-DG44)/DG44,"-") | EH44: =IFERROR((DX44-DH44)/DH44,"-") | EI44: - | EJ44: 14 | EK44: 201026 | EL44: 189.65385 | EM44: 519.20336 | EN44: -329.54951 | EO44: 19611.236 | EP44: 19769.038 | EQ44: 4 | ER44: 0 | ES44: - | ET44: =S44+AC44+AM44+AW44+BG44+BQ44+CA44+CK44+CU44+DE44+DU44+EL44 | EU44: =U44+AE44+AO44+AY44+BI44+BS44+CC44+CM44+CW44+DG44+DW44+EN44 | EV44: - | EW44: =IFERROR((EL44-DU44)/DU44,"-") | EX44: =IFERROR((EN44-DW44)/DW44,"-") | EY44: =IFERROR((EO44-DX44)/DX44,"-")
A45: Medium to Long Duration Fund | B45: Income/Debt Oriented Schemes | C45: Open ended Schemes | D45: Debt | E45: TD | F45: Active Debt (incl Hybrid) | K45: =IF(OR(I45="",J45=""),"",I45-J45) | L45: 11553.685 | M45: 11605.298 | P45: - | Q45: 13 | R45: 103165 | S45: 310.38203 | T45: 210.34638 | U45: 100.03565 | V45: 11859.044 | W45: 11767.791 | X45: 0 | Y45: 0 | Z45: - | AA45: 13 | AB45: 104030 | AC45: 155.87826 | AD45: 111.74407 | AE45: 44.134193 | AF45: 11999.016 | AG45: 11934.71 | AH45: 0 | AI45: 0 | AJ45: - | AK45: 13 | AL45: 104283 | AM45: 162.22432 | AN45: 227.99319 | AO45: -65.768869 | AP45: 11852.051 | AQ45: 11934.073 | AR45: 0 | AS45: 0 | AT45: - | AU45: 13 | AV45: 104610 | AW45: 119.4443 | AX45: 340.89715 | AY45: -221.45285 | AZ45: 11687.03 | BA45: 11799.956 | BB45: 0 | BC45: 0 | BD45: - | BE45: 13 | BF45: 104533 | BG45: 53.287901 | BH45: 81.174598 | BI45: -27.886696 | BJ45: 11520.332 | BK45: 11601.784 | BL45: 0 | BM45: 0 | BN45: - | BO45: 13 | BP45: 103999 | BQ45: 249.43866 | BR45: 146.04761 | BS45: 103.39105 | BT45: 11734.901 | BU45: 11591.962 | BV45: 0 | BW45: 0 | BX45: - | BY45: 13 | BZ45: 103489 | CA45: 219.47798 | CB45: 202.74744 | CC45: 16.730536 | CD45: 11825.915 | CE45: 11845.598 | CF45: 0 | CG45: 0 | CH45: - | CI45: 13 | CJ45: 102988 | CK45: 107.98126 | CL45: 116.60898 | CM45: -8.6277176 | CN45: 11855.911 | CO45: 11875.318 | CP45: 0 | CQ45: 0 | CR45: - | CS45: 13 | CT45: 102111 | CU45: 61.098461 | CV45: 249.05716 | CW45: -187.9587 | CX45: 11692.14 | CY45: 11771.089 | CZ45: 0 | DA45: 0 | DB45: - | DC45: 13 | DD45: 101359 | DE45: 41.956201 | DF45: 216.33058 | DG45: -174.37438 | DH45: 11512.902 | DI45: 11555.99 | DJ45: 0 | DK45: 0 | DL45: - | DM45: =S45+AC45+AM45+AW45+BG45+BQ45+CA45+CK45+CU45+DE45 | DN45: =U45+AE45+AO45+AY45+BI45+BS45+CC45+CM45+CW45+DG45 | DO45: - | DP45: =IFERROR((DE45-CU45)/CU45,"-") | DQ45: =IFERROR((DG45-CW45)/CW45,"-") | DR45: =IFERROR((DH45-CX45)/CX45,"-") | DS45: 13 | DT45: 101256 | DU45: 28.214792 | DV45: 299.43259 | DW45: -271.2178 | DX45: 11321.514 | DY45: 11432.118 | DZ45: 0 | EA45: 0 | EB45: - | EC45: =S45+AC45+AM45+AW45+BG45+BQ45+CA45+CK45+CU45+DE45+DU45 | ED45: =U45+AE45+AO45+AY45+BI45+BS45+CC45+CM45+CW45+DG45+DW45 | EE45: - | EF45: =IFERROR((DU45-DE45)/DE45,"-") | EG45: =IFERROR((DW45-DG45)/DG45,"-") | EH45: =IFERROR((DX45-DH45)/DH45,"-") | EI45: - | EJ45: 13 | EK45: 100704 | EL45: 107.54066 | EM45: 515.15857 | EN45: -407.6179 | EO45: 10769.245 | EP45: 11113.121 | EQ45: 0 | ER45: 0 | ES45: - | ET45: =S45+AC45+AM45+AW45+BG45+BQ45+CA45+CK45+CU45+DE45+DU45+EL45 | EU45: =U45+AE45+AO45+AY45+BI45+BS45+CC45+CM45+CW45+DG45+DW45+EN45 | EV45: - | EW45: =IFERROR((EL45-DU45)/DU45,"-") | EX45: =IFERROR((EN45-DW45)/DW45,"-") | EY45: =IFERROR((EO45-DX45)/DX45,"-")
A46: Dynamic Bond Fund | B46: Income/Debt Oriented Schemes | C46: Open ended Schemes | D46: Debt | E46: TD | F46: Active Debt (incl Hybrid) | K46: =IF(OR(I46="",J46=""),"",I46-J46) | L46: 35591.653 | M46: 35527.224 | P46: - | Q46: 22 | R46: 230028 | S46: 943.7691 | T46: 953.99736 | U46: -10.228257 | V46: 36231.288 | W46: 35961.974 | X46: 0 | Y46: 0 | Z46: - | AA46: 22 | AB46: 234872 | AC46: 1256.2398 | AD46: 689.5047 | AE46: 566.73511 | AF46: 37087.946 | AG46: 36676.611 | AH46: 0 | AI46: 0 | AJ46: - | AK46: 22 | AL46: 236833 | AM46: 741.05261 | AN46: 697.02166 | AO46: 44.030942 | AP46: 36912.296 | AQ46: 37020.314 | AR46: 0 | AS46: 0 | AT46: - | AU46: 22 | AV46: 239570 | AW46: 729.20336 | AX46: 666.65727 | AY46: 62.54609 | AZ46: 37174.041 | BA46: 37095.503 | BB46: 0 | BC46: 0 | BD46: - | BE46: 22 | BF46: 240006 | BG46: 547.0951 | BH46: 941.75012 | BI46: -394.65502 | BJ46: 36424.155 | BK46: 36872.253 | BL46: 0 | BM46: 0 | BN46: - | BO46: 22 | BP46: 239543 | BQ46: 1364.2719 | BR46: 844.85945 | BS46: 519.41246 | BT46: 37322.667 | BU46: 36649.087 | BV46: 0 | BW46: 0 | BX46: - | BY46: 22 | BZ46: 237849 | CA46: 686.53434 | CB46: 919.22148 | CC46: -232.68714 | CD46: 37333.959 | CE46: 37527.746 | CF46: 0 | CG46: 0 | CH46: - | CI46: 22 | CJ46: 235965 | CK46: 328.92697 | CL46: 935.4877 | CM46: -606.56073 | CN46: 36857.416 | CO46: 37067.959 | CP46: 0 | CQ46: 0 | CR46: - | CS46: 22 | CT46: 232827 | CU46: 440.37437 | CV46: 1283.4509 | CW46: -843.0765 | CX46: 36108.335 | CY46: 36540.312 | CZ46: 0 | DA46: 0 | DB46: - | DC46: 22 | DD46: 229369 | DE46: 202.80745 | DF46: 1637.7607 | DG46: -1434.9533 | DH46: 34718.258 | DI46: 35462.874 | DJ46: 0 | DK46: 0 | DL46: - | DM46: =S46+AC46+AM46+AW46+BG46+BQ46+CA46+CK46+CU46+DE46 | DN46: =U46+AE46+AO46+AY46+BI46+BS46+CC46+CM46+CW46+DG46 | DO46: - | DP46: =IFERROR((DE46-CU46)/CU46,"-") | DQ46: =IFERROR((DG46-CW46)/CW46,"-") | DR46: =IFERROR((DH46-CX46)/CX46,"-") | DS46: 22 | DT46: 227542 | DU46: 214.3177 | DV46: 765.80627 | DW46: -551.48857 | DX46: 34439.093 | DY46: 34448.31 | DZ46: 0 | EA46: 0 | EB46: - | EC46: =S46+AC46+AM46+AW46+BG46+BQ46+CA46+CK46+CU46+DE46+DU46 | ED46: =U46+AE46+AO46+AY46+BI46+BS46+CC46+CM46+CW46+DG46+DW46 | EE46: - | EF46: =IFERROR((DU46-DE46)/DE46,"-") | EG46: =IFERROR((DW46-DG46)/DG46,"-") | EH46: =IFERROR((DX46-DH46)/DH46,"-") | EI46: - | EJ46: 22 | EK46: 224312 | EL46: 289.84313 | EM46: 2030.8877 | EN46: -1741.0446 | EO46: 32385.866 | EP46: 33601.975 | EQ46: 0 | ER46: 0 | ES46: - | ET46: =S46+AC46+AM46+AW46+BG46+BQ46+CA46+CK46+CU46+DE46+DU46+EL46 | EU46: =U46+AE46+AO46+AY46+BI46+BS46+CC46+CM46+CW46+DG46+DW46+EN46 | EV46: - | EW46: =IFERROR((EL46-DU46)/DU46,"-") | EX46: =IFERROR((EN46-DW46)/DW46,"-") | EY46: =IFERROR((EO46-DX46)/DX46,"-")
A47: Long Duration Fund | B47: Income/Debt Oriented Schemes | C47: Open ended Schemes | D47: Debt | E47: TD | F47: Active Debt (incl Hybrid) | K47: =IF(OR(I47="",J47=""),"",I47-J47) | L47: 20344.32 | M47: 20342.764 | P47: - | Q47: 11 | R47: 94353 | S47: 874.43265 | T47: 792.44604 | U47: 81.986611 | V47: 20873.892 | W47: 20835.252 | X47: 0 | Y47: 0 | Z47: - | AA47: 11 | AB47: 97786 | AC47: 875.20307 | AD47: 409.06861 | AE47: 466.13446 | AF47: 21415.249 | AG47: 21119.185 | AH47: 0 | AI47: 0 | AJ47: - | AK47: 11 | AL47: 96767 | AM47: 594.44027 | AN47: 1040.3227 | AO47: -445.88241 | AP47: 20538.598 | AQ47: 20907.171 | AR47: 0 | AS47: 0 | AT47: - | AU47: 11 | AV47: 96032 | AW47: 291.87645 | AX47: 708.3591 | AY47: -416.48266 | AZ47: 20260.148 | BA47: 20350.742 | BB47: 0 | BC47: 0 | BD47: - | BE47: 11 | BF47: 94316 | BG47: 697.87571 | BH47: 760.06026 | BI47: -62.184551 | BJ47: 19719.614 | BK47: 19860.45 | BL47: 0 | BM47: 0 | BN47: - | BO47: 11 | BP47: 91968 | BQ47: 767.11969 | BR47: 705.82628 | BS47: 61.293412 | BT47: 20069.37 | BU47: 20076.98 | BV47: 0 | BW47: 0 | BX47: - | BY47: 11 | BZ47: 89830 | CA47: 99.845843 | CB47: 1042.5572 | CC47: -942.71133 | CD47: 19194.203 | CE47: 19723.739 | CF47: 0 | CG47: 0 | CH47: - | CI47: 11 | CJ47: 87932 | CK47: 232.05932 | CL47: 598.50695 | CM47: -366.44763 | CN47: 18856.545 | CO47: 19028.931 | CP47: 0 | CQ47: 0 | CR47: - | CS47: 11 | CT47: 85438 | CU47: 70.762279 | CV47: 1373.9293 | CW47: -1303.167 | CX47: 17608.271 | CY47: 17965.21 | CZ47: 0 | DA47: 0 | DB47: - | DC47: 11 | DD47: 82999 | DE47: 28.911015 | DF47: 1365.2405 | DG47: -1336.3295 | DH47: 16221.172 | DI47: 16754.337 | DJ47: 0 | DK47: 0 | DL47: - | DM47: =S47+AC47+AM47+AW47+BG47+BQ47+CA47+CK47+CU47+DE47 | DN47: =U47+AE47+AO47+AY47+BI47+BS47+CC47+CM47+CW47+DG47 | DO47: - | DP47: =IFERROR((DE47-CU47)/CU47,"-") | DQ47: =IFERROR((DG47-CW47)/CW47,"-") | DR47: =IFERROR((DH47-CX47)/CX47,"-") | DS47: 11 | DT47: 81398 | DU47: 153.20961 | DV47: 782.13664 | DW47: -628.92703 | DX47: 15671.683 | DY47: 15806.698 | DZ47: 0 | EA47: 0 | EB47: - | EC47: =S47+AC47+AM47+AW47+BG47+BQ47+CA47+CK47+CU47+DE47+DU47 | ED47: =U47+AE47+AO47+AY47+BI47+BS47+CC47+CM47+CW47+DG47+DW47 | EE47: - | EF47: =IFERROR((DU47-DE47)/DE47,"-") | EG47: =IFERROR((DW47-DG47)/DG47,"-") | EH47: =IFERROR((DX47-DH47)/DH47,"-") | EI47: - | EJ47: 11 | EK47: 79190 | EL47: 244.31827 | EM47: 1291.6757 | EN47: -1047.3575 | EO47: 14158.73 | EP47: 15132.481 | EQ47: 0 | ER47: 0 | ES47: - | ET47: =S47+AC47+AM47+AW47+BG47+BQ47+CA47+CK47+CU47+DE47+DU47+EL47 | EU47: =U47+AE47+AO47+AY47+BI47+BS47+CC47+CM47+CW47+DG47+DW47+EN47 | EV47: - | EW47: =IFERROR((EL47-DU47)/DU47,"-") | EX47: =IFERROR((EN47-DW47)/DW47,"-") | EY47: =IFERROR((EO47-DX47)/DX47,"-")
A48: Banking and PSU Fund | B48: Income/Debt Oriented Schemes | C48: Open ended Schemes | D48: Debt | E48: TD | F48: Active Debt (incl Hybrid) | K48: =IF(OR(I48="",J48=""),"",I48-J48) | L48: 78850.098 | M48: 78721.834 | P48: - | Q48: 22 | R48: 237042 | S48: 2069.1923 | T48: 1433.3049 | U48: 635.88737 | V48: 80597.862 | W48: 79692.997 | X48: 0 | Y48: 0 | Z48: - | AA48: 22 | AB48: 238455 | AC48: 1608.1267 | AD48: 1123.993 | AE48: 484.1337 | AF48: 81949.603 | AG48: 81268.731 | AH48: 0 | AI48: 0 | AJ48: - | AK48: 22 | AL48: 239295 | AM48: 1969.7849 | AN48: 1731.1866 | AO48: 238.59835 | AP48: 82228.636 | AQ48: 82588.27 | AR48: 0 | AS48: 0 | AT48: - | AU48: 22 | AV48: 240020 | AW48: 1295.2429 | AX48: 1956.973 | AY48: -661.73014 | AZ48: 82041.636 | BA48: 81868.294 | BB48: 0 | BC48: 0 | BD48: - | BE48: 22 | BF48: 240524 | BG48: 947.25648 | BH48: 1747.7056 | BI48: -800.44908 | BJ48: 81161.204 | BK48: 81717.485 | BL48: 0 | BM48: 0 | BN48: - | BO48: 22 | BP48: 239947 | BQ48: 742.07849 | BR48: 2709.388 | BS48: -1967.3095 | BT48: 79724.098 | BU48: 80533.193 | BV48: 0 | BW48: 0 | BX48: - | BY48: 21 | BZ48: 239409 | CA48: 1534.7932 | CB48: 1322.5205 | CC48: 212.27278 | CD48: 80699.626 | CE48: 79815.887 | CF48: 0 | CG48: 0 | CH48: - | CI48: 21 | CJ48: 240003 | CK48: 509.09094 | CL48: 1361.1872 | CM48: -852.09631 | CN48: 80299.52 | CO48: 80543.606 | CP48: 0 | CQ48: 0 | CR48: - | CS48: 21 | CT48: 239818 | CU48: 769.56581 | CV48: 1745.6603 | CW48: -976.09444 | CX48: 79417.259 | CY48: 79512.417 | CZ48: 0 | DA48: 0 | DB48: - | DC48: 21 | DD48: 239116 | DE48: 514.35412 | DF48: 1733.2348 | DG48: -1218.8807 | DH48: 78169.944 | DI48: 78906.718 | DJ48: 0 | DK48: 0 | DL48: - | DM48: =S48+AC48+AM48+AW48+BG48+BQ48+CA48+CK48+CU48+DE48 | DN48: =U48+AE48+AO48+AY48+BI48+BS48+CC48+CM48+CW48+DG48 | DO48: - | DP48: =IFERROR((DE48-CU48)/CU48,"-") | DQ48: =IFERROR((DG48-CW48)/CW48,"-") | DR48: =IFERROR((DH48-CX48)/CX48,"-") | DS48: 20 | DT48: 239763 | DU48: 447.0919 | DV48: 1919.8583 | DW48: -1472.7664 | DX48: 77138.937 | DY48: 77708.442 | DZ48: 0 | EA48: 0 | EB48: - | EC48: =S48+AC48+AM48+AW48+BG48+BQ48+CA48+CK48+CU48+DE48+DU48 | ED48: =U48+AE48+AO48+AY48+BI48+BS48+CC48+CM48+CW48+DG48+DW48 | EE48: - | EF48: =IFERROR((DU48-DE48)/DE48,"-") | EG48: =IFERROR((DW48-DG48)/DG48,"-") | EH48: =IFERROR((DX48-DH48)/DH48,"-") | EI48: - | EJ48: 20 | EK48: 239277 | EL48: 425.15845 | EM48: 2699.2349 | EN48: -2274.0765 | EO48: 74619.678 | EP48: 75970.218 | EQ48: 0 | ER48: 0 | ES48: - | ET48: =S48+AC48+AM48+AW48+BG48+BQ48+CA48+CK48+CU48+DE48+DU48+EL48 | EU48: =U48+AE48+AO48+AY48+BI48+BS48+CC48+CM48+CW48+DG48+DW48+EN48 | EV48: - | EW48: =IFERROR((EL48-DU48)/DU48,"-") | EX48: =IFERROR((EN48-DW48)/DW48,"-") | EY48: =IFERROR((EO48-DX48)/DX48,"-")
A49: Short Duration Fund | B49: Income/Debt Oriented Schemes | C49: Open ended Schemes | D49: Debt | E49: TD | F49: Active Debt (incl Hybrid) | K49: =IF(OR(I49="",J49=""),"",I49-J49) | L49: 113320.86 | M49: 112254.19 | P49: - | Q49: 24 | R49: 463334 | S49: 10139.495 | T49: 5376.2797 | U49: 4763.215 | V49: 119708.54 | W49: 118413.3 | X49: 0 | Y49: 0 | Z49: - | AA49: 24 | AB49: 475177 | AC49: 7633.7644 | AD49: 5843.9763 | AE49: 1789.7881 | AF49: 122759.56 | AG49: 121092 | AH49: 0 | AI49: 0 | AJ49: - | AK49: 24 | AL49: 488358 | AM49: 20113.176 | AN49: 9836.4277 | AO49: 10276.748 | AP49: 133337 | AQ49: 132173.68 | AR49: 0 | AS49: 0 | AT49: - | AU49: 24 | AV49: 506036 | AW49: 6866.8996 | AX49: 5037.5701 | AY49: 1829.3295 | AZ49: 136020.58 | BA49: 136121.88 | BB49: 0 | BC49: 0 | BD49: - | BE49: 24 | BF49: 517942 | BG49: 4807.2552 | BH49: 4241.9949 | BI49: 565.26035 | BJ49: 136582.75 | BK49: 136154 | BL49: 0 | BM49: 0 | BN49: - | BO49: 24 | BP49: 525052 | BQ49: 4069.7225 | BR49: 6242.9567 | BS49: -2173.2341 | BT49: 135290.95 | BU49: 136485.12 | BV49: 0 | BW49: 0 | BX49: - | BY49: 24 | BZ49: 539194 | CA49: 6049.251 | CB49: 3279.7361 | CC49: 2769.5149 | CD49: 139124.76 | CE49: 137918.12 | CF49: 0 | CG49: 0 | CH49: - | CI49: 24 | CJ49: 553771 | CK49: 4756.08 | CL49: 2650.4558 | CM49: 2105.6242 | CN49: 142040.84 | CO49: 140524.54 | CP49: 0 | CQ49: 0 | CR49: - | CS49: 24 | CT49: 561636 | CU49: 3648.4231 | CV49: 9338.0294 | CW49: -5689.6063 | CX49: 136600.71 | CY49: 140221.98 | CZ49: 0 | DA49: 0 | DB49: - | DC49: 25 | DD49: 563688 | DE49: 5931.1645 | DF49: 8819.7132 | DG49: -2888.5486 | DH49: 133810.21 | DI49: 136139.32 | DJ49: 0 | DK49: 0 | DL49: - | DM49: =S49+AC49+AM49+AW49+BG49+BQ49+CA49+CK49+CU49+DE49 | DN49: =U49+AE49+AO49+AY49+BI49+BS49+CC49+CM49+CW49+DG49 | DO49: - | DP49: =IFERROR((DE49-CU49)/CU49,"-") | DQ49: =IFERROR((DG49-CW49)/CW49,"-") | DR49: =IFERROR((DH49-CX49)/CX49,"-") | DS49: 25 | DT49: 569039 | DU49: 2456.4586 | DV49: 4373.2682 | DW49: -1916.8095 | DX49: 133399.04 | DY49: 133295.52 | DZ49: 0 | EA49: 0 | EB49: - | EC49: =S49+AC49+AM49+AW49+BG49+BQ49+CA49+CK49+CU49+DE49+DU49 | ED49: =U49+AE49+AO49+AY49+BI49+BS49+CC49+CM49+CW49+DG49+DW49 | EE49: - | EF49: =IFERROR((DU49-DE49)/DE49,"-") | EG49: =IFERROR((DW49-DG49)/DG49,"-") | EH49: =IFERROR((DX49-DH49)/DH49,"-") | EI49: - | EJ49: 25 | EK49: 567436 | EL49: 13663.234 | EM49: 35856.735 | EN49: -22193.501 | EO49: 110851.25 | EP49: 123966.82 | EQ49: 0 | ER49: 0 | ES49: - | ET49: =S49+AC49+AM49+AW49+BG49+BQ49+CA49+CK49+CU49+DE49+DU49+EL49 | EU49: =U49+AE49+AO49+AY49+BI49+BS49+CC49+CM49+CW49+DG49+DW49+EN49 | EV49: - | EW49: =IFERROR((EL49-DU49)/DU49,"-") | EX49: =IFERROR((EN49-DW49)/DW49,"-") | EY49: =IFERROR((EO49-DX49)/DX49,"-")
A50: Corporate Bond Fund | B50: Income/Debt Oriented Schemes | C50: Open ended Schemes | D50: Debt | E50: TD | F50: Active Debt (incl Hybrid) | K50: =IF(OR(I50="",J50=""),"",I50-J50) | L50: 175800.18 | M50: 172372.74 | P50: - | Q50: 21 | R50: 534052 | S50: 12529.964 | T50: 9071.5467 | U50: 3458.4168 | V50: 181953.76 | W50: 181608.56 | X50: 0 | Y50: 0 | Z50: - | AA50: 21 | AB50: 541227 | AC50: 15313.767 | AD50: 3330.4126 | AE50: 11983.354 | AF50: 195987.39 | AG50: 188971.47 | AH50: 0 | AI50: 0 | AJ50: - | AK50: 21 | AL50: 546232 | AM50: 13196.209 | AN50: 6071.7273 | AO50: 7124.4816 | AP50: 203199.04 | AQ50: 201197.79 | AR50: 0 | AS50: 0 | AT50: - | AU50: 21 | AV50: 560211 | AW50: 8478.3697 | AX50: 7056.8027 | AY50: 1421.567 | AZ50: 205891.36 | BA50: 205113.74 | BB50: 0 | BC50: 0 | BD50: - | BE50: 21 | BF50: 565827 | BG50: 4102.5745 | BH50: 4927.5729 | BI50: -824.9984 | BJ50: 204712.23 | BK50: 205196.62 | BL50: 0 | BM50: 0 | BN50: - | BO50: 21 | BP50: 567992 | BQ50: 5884.5804 | BR50: 7328.188 | BS50: -1443.6076 | BT50: 204656.55 | BU50: 204969.02 | BV50: 0 | BW50: 0 | BX50: - | BY50: 21 | BZ50: 573717 | CA50: 9118.1466 | CB50: 3996.2352 | CC50: 5121.9114 | CD50: 211442.33 | CE50: 208944.82 | CF50: 0 | CG50: 0 | CH50: - | CI50: 21 | CJ50: 579465 | CK50: 4128.7231 | CL50: 2603.5813 | CM50: 1525.1418 | CN50: 214156.4 | CO50: 212838.71 | CP50: 0 | CQ50: 0 | CR50: - | CS50: 21 | CT50: 580979 | CU50: 3723.5861 | CV50: 11143.091 | CW50: -7419.5052 | CX50: 207005.95 | CY50: 209245.4 | CZ50: 0 | DA50: 0 | DB50: - | DC50: 21 | DD50: 577039 | DE50: 1626.5984 | DF50: 13099.39 | DG50: -11472.792 | DH50: 195400.07 | DI50: 201314.95 | DJ50: 0 | DK50: 0 | DL50: - | DM50: =S50+AC50+AM50+AW50+BG50+BQ50+CA50+CK50+CU50+DE50 | DN50: =U50+AE50+AO50+AY50+BI50+BS50+CC50+CM50+CW50+DG50 | DO50: - | DP50: =IFERROR((DE50-CU50)/CU50,"-") | DQ50: =IFERROR((DG50-CW50)/CW50,"-") | DR50: =IFERROR((DH50-CX50)/CX50,"-") | DS50: 21 | DT50: 573786 | DU50: 1673.7781 | DV50: 3975.9205 | DW50: -2302.1424 | DX50: 194780.96 | DY50: 194992.93 | DZ50: 0 | EA50: 0 | EB50: - | EC50: =S50+AC50+AM50+AW50+BG50+BQ50+CA50+CK50+CU50+DE50+DU50 | ED50: =U50+AE50+AO50+AY50+BI50+BS50+CC50+CM50+CW50+DG50+DW50 | EE50: - | EF50: =IFERROR((DU50-DE50)/DE50,"-") | EG50: =IFERROR((DW50-DG50)/DG50,"-") | EH50: =IFERROR((DX50-DH50)/DH50,"-") | EI50: - | EJ50: 21 | EK50: 573401 | EL50: 8680.953 | EM50: 23973.539 | EN50: -15292.586 | EO50: 178430.61 | EP50: 186940.84 | EQ50: 0 | ER50: 0 | ES50: - | ET50: =S50+AC50+AM50+AW50+BG50+BQ50+CA50+CK50+CU50+DE50+DU50+EL50 | EU50: =U50+AE50+AO50+AY50+BI50+BS50+CC50+CM50+CW50+DG50+DW50+EN50 | EV50: - | EW50: =IFERROR((EL50-DU50)/DU50,"-") | EX50: =IFERROR((EN50-DW50)/DW50,"-") | EY50: =IFERROR((EO50-DX50)/DX50,"-")
A51: Ultra Short Duration Fund | B51: Income/Debt Oriented Schemes | C51: Open ended Schemes | D51: Debt | E51: TD | F51: Active Debt (incl Hybrid) | K51: =IF(OR(I51="",J51=""),"",I51-J51) | L51: 98541.794 | M51: 103614.95 | P51: - | Q51: 25 | R51: 672543 | S51: 41099.83 | T51: 14366.022 | U51: 26733.808 | V51: 126436.7 | W51: 114947.49 | X51: 0 | Y51: 0 | Z51: - | AA51: 25 | AB51: 695720 | AC51: 20775.122 | AD51: 18927.547 | AE51: 1847.5743 | AF51: 129110 | AG51: 128267.07 | AH51: 0 | AI51: 0 | AJ51: - | AK51: 25 | AL51: 718333 | AM51: 31480.342 | AN51: 28536.581 | AO51: 2943.7611 | AP51: 132827.32 | AQ51: 130140.43 | AR51: 0 | AS51: 0 | AT51: - | AU51: 25 | AV51: 724730 | AW51: 35894.963 | AX51: 33618.338 | AY51: 2276.6244 | AZ51: 135868.22 | BA51: 135111.63 | BB51: 0 | BC51: 0 | BD51: - | BE51: 25 | BF51: 732657 | BG51: 22318.352 | BH51: 21944.829 | BI51: 373.52314 | BJ51: 136833.54 | BK51: 136704.27 | BL51: 0 | BM51: 0 | BN51: - | BO51: 25 | BP51: 735253 | BQ51: 22792.097 | BR51: 36397.759 | BS51: -13605.662 | BT51: 123935.96 | BU51: 133900.2 | BV51: 0 | BW51: 0 | BX51: - | BY51: 25 | BZ51: 744239 | CA51: 37282.726 | CB51: 22216.089 | CC51: 15066.637 | CD51: 139715.15 | CE51: 134716.34 | CF51: 0 | CG51: 0 | CH51: - | CI51: 25 | CJ51: 763342 | CK51: 30363.097 | CL51: 22002.188 | CM51: 8360.9095 | CN51: 148782.98 | CO51: 143671.98 | CP51: 0 | CQ51: 0 | CR51: - | CS51: 25 | CT51: 766379 | CU51: 24881.026 | CV51: 42529.182 | CW51: -17648.155 | CX51: 131827.26 | CY51: 146522.96 | CZ51: 0 | DA51: 0 | DB51: - | DC51: 25 | DD51: 768654 | DE51: 29442.045 | DF51: 29186.676 | DG51: 255.36866 | DH51: 132482.35 | DI51: 136859.04 | DJ51: 0 | DK51: 0 | DL51: - | DM51: =S51+AC51+AM51+AW51+BG51+BQ51+CA51+CK51+CU51+DE51 | DN51: =U51+AE51+AO51+AY51+BI51+BS51+CC51+CM51+CW51+DG51 | DO51: - | DP51: =IFERROR((DE51-CU51)/CU51,"-") | DQ51: =IFERROR((DG51-CW51)/CW51,"-") | DR51: =IFERROR((DH51-CX51)/CX51,"-") | DS51: 25 | DT51: 778455 | DU51: 20712.481 | DV51: 25086.408 | DW51: -4373.9276 | DX51: 127759.88 | DY51: 130179.27 | DZ51: 0 | EA51: 0 | EB51: - | EC51: =S51+AC51+AM51+AW51+BG51+BQ51+CA51+CK51+CU51+DE51+DU51 | ED51: =U51+AE51+AO51+AY51+BI51+BS51+CC51+CM51+CW51+DG51+DW51 | EE51: - | EF51: =IFERROR((DU51-DE51)/DE51,"-") | EG51: =IFERROR((DW51-DG51)/DG51,"-") | EH51: =IFERROR((DX51-DH51)/DH51,"-") | EI51: - | EJ51: 25 | EK51: 777807 | EL51: 20523.246 | EM51: 36610.501 | EN51: -16087.255 | EO51: 113339.58 | EP51: 121687.25 | EQ51: 0 | ER51: 0 | ES51: - | ET51: =S51+AC51+AM51+AW51+BG51+BQ51+CA51+CK51+CU51+DE51+DU51+EL51 | EU51: =U51+AE51+AO51+AY51+BI51+BS51+CC51+CM51+CW51+DG51+DW51+EN51 | EV51: - | EW51: =IFERROR((EL51-DU51)/DU51,"-") | EX51: =IFERROR((EN51-DW51)/DW51,"-") | EY51: =IFERROR((EO51-DX51)/DX51,"-")
A52: Total for Active Debt (incl Hybrid) | G52: =SUM(G31:G51) | H52: =SUM(H31:H51) | I52: =SUM(I31:I51) | J52: =SUM(J31:J51) | K52: =SUM(K31:K51) | L52: =SUM(L31:L51) | M52: =SUM(M31:M51) | N52: =SUM(N31:N51) | O52: =SUM(O31:O51) | Q52: =SUM(Q31:Q51) | R52: =SUM(R31:R51) | S52: =SUM(S31:S51) | T52: =SUM(T31:T51) | U52: =SUM(U31:U51) | V52: =SUM(V31:V51) | W52: =SUM(W31:W51) | X52: =SUM(X31:X51) | Y52: =SUM(Y31:Y51) | AA52: =SUM(AA31:AA51) | AB52: =SUM(AB31:AB51) | AC52: =SUM(AC31:AC51) | AD52: =SUM(AD31:AD51) | AE52: =SUM(AE31:AE51) | AF52: =SUM(AF31:AF51) | AG52: =SUM(AG31:AG51) | AH52: =SUM(AH31:AH51) | AI52: =SUM(AI31:AI51) | AK52: =SUM(AK31:AK51) | AL52: =SUM(AL31:AL51) | AM52: =SUM(AM31:AM51) | AN52: =SUM(AN31:AN51) | AO52: =SUM(AO31:AO51) | AP52: =SUM(AP31:AP51) | AQ52: =SUM(AQ31:AQ51) | AR52: =SUM(AR31:AR51) | AS52: =SUM(AS31:AS51) | AU52: =SUM(AU31:AU51) | AV52: =SUM(AV31:AV51) | AW52: =SUM(AW31:AW51) | AX52: =SUM(AX31:AX51) | AY52: =SUM(AY31:AY51) | AZ52: =SUM(AZ31:AZ51) | BA52: =SUM(BA31:BA51) | BB52: =SUM(BB31:BB51) | BC52: =SUM(BC31:BC51) | BE52: =SUM(BE31:BE51) | BF52: =SUM(BF31:BF51) | BG52: =SUM(BG31:BG51) | BH52: =SUM(BH31:BH51) | BI52: =SUM(BI31:BI51) | BJ52: =SUM(BJ31:BJ51) | BK52: =SUM(BK31:BK51) | BL52: =SUM(BL31:BL51) | BM52: =SUM(BM31:BM51) | BO52: =SUM(BO31:BO51) | BP52: =SUM(BP31:BP51) | BQ52: =SUM(BQ31:BQ51) | BR52: =SUM(BR31:BR51) | BS52: =SUM(BS31:BS51) | BT52: =SUM(BT31:BT51) | BU52: =SUM(BU31:BU51) | BV52: =SUM(BV31:BV51) | BW52: =SUM(BW31:BW51) | BY52: =SUM(BY31:BY51) | BZ52: =SUM(BZ31:BZ51) | CA52: =SUM(CA31:CA51) | CB52: =SUM(CB31:CB51) | CC52: =SUM(CC31:CC51) | CD52: =SUM(CD31:CD51) | CE52: =SUM(CE31:CE51) | CF52: =SUM(CF31:CF51) | CG52: =SUM(CG31:CG51) | CI52: =SUM(CI31:CI51) | CJ52: =SUM(CJ31:CJ51) | CK52: =SUM(CK31:CK51) | CL52: =SUM(CL31:CL51) | CM52: =SUM(CM31:CM51) | CN52: =SUM(CN31:CN51) | CO52: =SUM(CO31:CO51) | CP52: =SUM(CP31:CP51) | CQ52: =SUM(CQ31:CQ51) | CS52: =SUM(CS31:CS51) | CT52: =SUM(CT31:CT51) | CU52: =SUM(CU31:CU51) | CV52: =SUM(CV31:CV51) | CW52: =SUM(CW31:CW51) | CX52: =SUM(CX31:CX51) | CY52: =SUM(CY31:CY51) | CZ52: =SUM(CZ31:CZ51) | DA52: =SUM(DA31:DA51) | DC52: =SUM(DC31:DC51) | DD52: =SUM(DD31:DD51) | DE52: =SUM(DE31:DE51) | DF52: =SUM(DF31:DF51) | DG52: =SUM(DG31:DG51) | DH52: =SUM(DH31:DH51) | DI52: =SUM(DI31:DI51) | DJ52: =SUM(DJ31:DJ51) | DK52: =SUM(DK31:DK51) | DM52: =SUM(DM31:DM51) | DN52: =SUM(DN31:DN51) | DP52: =IFERROR((DE52-CU52)/CU52,"-") | DQ52: =IFERROR((DG52-CW52)/CW52,"-") | DR52: =IFERROR((DH52-CX52)/CX52,"-") | DS52: =SUM(DS31:DS51) | DT52: =SUM(DT31:DT51) | DU52: =SUM(DU31:DU51) | DV52: =SUM(DV31:DV51) | DW52: =SUM(DW31:DW51) | DX52: =SUM(DX31:DX51) | DY52: =SUM(DY31:DY51) | DZ52: =SUM(DZ31:DZ51) | EA52: =SUM(EA31:EA51) | EC52: =SUM(EC31:EC51) | ED52: =SUM(ED31:ED51) | EF52: =IFERROR((DU52-DE52)/DE52,"-") | EG52: =IFERROR((DW52-DG52)/DG52,"-") | EH52: =IFERROR((DX52-DH52)/DH52,"-") | EJ52: =SUM(EJ31:EJ51) | EK52: =SUM(EK31:EK51) | EL52: =SUM(EL31:EL51) | EM52: =SUM(EM31:EM51) | EN52: =SUM(EN31:EN51) | EO52: =SUM(EO31:EO51) | EP52: =SUM(EP31:EP51) | EQ52: =SUM(EQ31:EQ51) | ER52: =SUM(ER31:ER51) | ET52: =SUM(ET31:ET51) | EU52: =SUM(EU31:EU51) | EW52: =IFERROR((EL52-DU52)/DU52,"-") | EX52: =IFERROR((EN52-DW52)/DW52,"-") | EY52: =IFERROR((EO52-DX52)/DX52,"-")
A53: Cash
A54: Liquid Fund | B54: Income/Debt Oriented Schemes | C54: Open ended Schemes | D54: Debt | E54: Cash | F54: Cash | K54: =IF(OR(I54="",J54=""),"",I54-J54) | L54: 437773.94 | M54: 557784.94 | P54: - | Q54: 37 | R54: 1912584 | S54: 507349.9 | T54: 388693.46 | U54: 118656.44 | V54: 559824.18 | W54: 607582.9 | X54: 0 | Y54: 0 | Z54: - | AA54: 37 | AB54: 1941435 | AC54: 345272.12 | AD54: 385477.48 | AE54: -40205.36 | AF54: 522714.52 | AG54: 568734.39 | AH54: 0 | AI54: 0 | AJ54: - | AK54: 38 | AL54: 1973815 | AM54: 503574.68 | AN54: 528770.76 | AO54: -25196.087 | AP54: 499856.82 | AQ54: 584402.99 | AR54: 0 | AS54: 0 | AT54: - | AU54: 39 | AV54: 2082344 | AW54: 477544.05 | AX54: 438189.12 | AY54: 39354.933 | AZ54: 542224.72 | BA54: 600208.97 | BB54: 0 | BC54: 0 | BD54: - | BE54: 39 | BF54: 2131349 | BG54: 347152.02 | BH54: 360502.08 | BI54: -13350.058 | BJ54: 531546.83 | BK54: 572499.66 | BL54: 0 | BM54: 0 | BN54: - | BO54: 39 | BP54: 2175269 | BQ54: 412041 | BR54: 478083.32 | BS54: -66042.325 | BT54: 467363.81 | BU54: 545880.12 | BV54: 0 | BW54: 0 | BX54: - | BY54: 40 | BZ54: 2278013 | CA54: 427684.69 | CB54: 338309.58 | CC54: 89375.119 | CD54: 559686.58 | CE54: 560718.31 | CF54: 0 | CG54: 0 | CH54: - | CI54: 41 | CJ54: 2377756 | CK54: 311162.8 | CL54: 325213.51 | CM54: -14050.716 | CN54: 548393.27 | CO54: 576514.28 | CP54: 0 | CQ54: 0 | CR54: - | CS54: 42 | CT54: 2435865 | CU54: 464668.91 | CV54: 511976.86 | CW54: -47307.955 | CX54: 503143.33 | CY54: 575533.13 | CZ54: 0 | DA54: 0 | DB54: - | DC54: 42 | DD54: 2514436 | DE54: 408835.02 | DF54: 378153.46 | DG54: 30681.554 | DH54: 536753.21 | DI54: 565989.62 | DJ54: 0 | DK54: 0 | DL54: - | DM54: =S54+AC54+AM54+AW54+BG54+BQ54+CA54+CK54+CU54+DE54 | DN54: =U54+AE54+AO54+AY54+BI54+BS54+CC54+CM54+CW54+DG54 | DO54: - | DP54: =IFERROR((DE54-CU54)/CU54,"-") | DQ54: =IFERROR((DG54-CW54)/CW54,"-") | DR54: =IFERROR((DH54-CX54)/CX54,"-") | DS54: 42 | DT54: 2616607 | DU54: 465477.84 | DV54: 406400.45 | DW54: 59077.394 | DX54: 598920.02 | DY54: 622413.14 | DZ54: 0 | EA54: 0 | EB54: - | EC54: =S54+AC54+AM54+AW54+BG54+BQ54+CA54+CK54+CU54+DE54+DU54 | ED54: =U54+AE54+AO54+AY54+BI54+BS54+CC54+CM54+CW54+DG54+DW54 | EE54: - | EF54: =IFERROR((DU54-DE54)/DE54,"-") | EG54: =IFERROR((DW54-DG54)/DG54,"-") | EH54: =IFERROR((DX54-DH54)/DH54,"-") | EI54: - | EJ54: 42 | EK54: 2719972 | EL54: 455110.25 | EM54: 590097.9 | EN54: -134987.64 | EO54: 466498.11 | EP54: 597067.86 | EQ54: 0 | ER54: 0 | ES54: - | ET54: =S54+AC54+AM54+AW54+BG54+BQ54+CA54+CK54+CU54+DE54+DU54+EL54 | EU54: =U54+AE54+AO54+AY54+BI54+BS54+CC54+CM54+CW54+DG54+DW54+EN54 | EV54: - | EW54: =IFERROR((EL54-DU54)/DU54,"-") | EX54: =IFERROR((EN54-DW54)/DW54,"-") | EY54: =IFERROR((EO54-DX54)/DX54,"-")
A55: Overnight Fund | B55: Income/Debt Oriented Schemes | C55: Open ended Schemes | D55: Debt | E55: Cash | F55: Cash | K55: =IF(OR(I55="",J55=""),"",I55-J55) | L55: 62458.426 | M55: 106086.5 | P55: - | Q55: 35 | R55: 651034 | S55: 452346.88 | T55: 428446.9 | U55: 23899.979 | V55: 86833.816 | W55: 99610.679 | X55: 0 | Y55: 0 | Z55: - | AA55: 35 | AB55: 659424 | AC55: 452387.85 | AD55: 460507.88 | AE55: -8120.0297 | AF55: 79184.256 | AG55: 97396.64 | AH55: 0 | AI55: 0 | AJ55: - | AK55: 35 | AL55: 663083 | AM55: 569989.96 | AN55: 578144.46 | AO55: -8154.4938 | AP55: 71480.93 | AQ55: 104237.28 | AR55: 0 | AS55: 0 | AT55: - | AU55: 37 | AV55: 706888 | AW55: 602367.86 | AX55: 593502.27 | AY55: 8865.5975 | AZ55: 80835.24 | BA55: 108422.78 | BB55: 0 | BC55: 0 | BD55: - | BE55: 37 | BF55: 716620 | BG55: 514292.58 | BH55: 509341.74 | BI55: 4950.8423 | BJ55: 86296.88 | BK55: 113153.74 | BL55: 0 | BM55: 0 | BN55: - | BO55: 37 | BP55: 714717 | BQ55: 622708.8 | BR55: 618429.8 | BS55: 4278.9994 | BT55: 91096.034 | BU55: 117432.18 | BV55: 0 | BW55: 0 | BX55: - | BY55: 37 | BZ55: 717799 | CA55: 540213.2 | CB55: 516162.63 | CC55: 24050.57 | CD55: 115714.42 | CE55: 124242.74 | CF55: 0 | CG55: 0 | CH55: - | CI55: 37 | CJ55: 718743 | CK55: 490785.81 | CL55: 528410.33 | CM55: -37624.526 | CN55: 78584.321 | CO55: 113503.27 | CP55: 0 | CQ55: 0 | CR55: - | CS55: 37 | CT55: 728222 | CU55: 699780.56 | CV55: 699526.31 | CW55: 254.25012 | CX55: 79367.825 | CY55: 117317.69 | CZ55: 0 | DA55: 0 | DB55: - | DC55: 37 | DD55: 734569 | DE55: 657098.14 | DF55: 610818.09 | DG55: 46280.049 | DH55: 126200.25 | DI55: 125565.4 | DJ55: 0 | DK55: 0 | DL55: - | DM55: =S55+AC55+AM55+AW55+BG55+BQ55+CA55+CK55+CU55+DE55 | DN55: =U55+AE55+AO55+AY55+BI55+BS55+CC55+CM55+CW55+DG55 | DO55: - | DP55: =IFERROR((DE55-CU55)/CU55,"-") | DQ55: =IFERROR((DG55-CW55)/CW55,"-") | DR55: =IFERROR((DH55-CX55)/CX55,"-") | DS55: 37 | DT55: 739107 | DU55: 620852.89 | DV55: 634859.1 | DW55: -14006.207 | DX55: 112665.9 | DY55: 129717.27 | DZ55: 0 | EA55: 0 | EB55: - | EC55: =S55+AC55+AM55+AW55+BG55+BQ55+CA55+CK55+CU55+DE55+DU55 | ED55: =U55+AE55+AO55+AY55+BI55+BS55+CC55+CM55+CW55+DG55+DW55 | EE55: - | EF55: =IFERROR((DU55-DE55)/DE55,"-") | EG55: =IFERROR((DW55-DG55)/DG55,"-") | EH55: =IFERROR((DX55-DH55)/DH55,"-") | EI55: - | EJ55: 37 | EK55: 744346 | EL55: 764530.5 | EM55: 804758.4 | EN55: -40227.899 | EO55: 73020.693 | EP55: 132873.16 | EQ55: 0 | ER55: 0 | ES55: - | ET55: =S55+AC55+AM55+AW55+BG55+BQ55+CA55+CK55+CU55+DE55+DU55+EL55 | EU55: =U55+AE55+AO55+AY55+BI55+BS55+CC55+CM55+CW55+DG55+DW55+EN55 | EV55: - | EW55: =IFERROR((EL55-DU55)/DU55,"-") | EX55: =IFERROR((EN55-DW55)/DW55,"-") | EY55: =IFERROR((EO55-DX55)/DX55,"-")
A56: Total for Cash | G56: =SUM(G54:G55) | H56: =SUM(H54:H55) | I56: =SUM(I54:I55) | J56: =SUM(J54:J55) | K56: =SUM(K54:K55) | L56: =SUM(L54:L55) | M56: =SUM(M54:M55) | N56: =SUM(N54:N55) | O56: =SUM(O54:O55) | Q56: =SUM(Q54:Q55) | R56: =SUM(R54:R55) | S56: =SUM(S54:S55) | T56: =SUM(T54:T55) | U56: =SUM(U54:U55) | V56: =SUM(V54:V55) | W56: =SUM(W54:W55) | X56: =SUM(X54:X55) | Y56: =SUM(Y54:Y55) | AA56: =SUM(AA54:AA55) | AB56: =SUM(AB54:AB55) | AC56: =SUM(AC54:AC55) | AD56: =SUM(AD54:AD55) | AE56: =SUM(AE54:AE55) | AF56: =SUM(AF54:AF55) | AG56: =SUM(AG54:AG55) | AH56: =SUM(AH54:AH55) | AI56: =SUM(AI54:AI55) | AK56: =SUM(AK54:AK55) | AL56: =SUM(AL54:AL55) | AM56: =SUM(AM54:AM55) | AN56: =SUM(AN54:AN55) | AO56: =SUM(AO54:AO55) | AP56: =SUM(AP54:AP55) | AQ56: =SUM(AQ54:AQ55) | AR56: =SUM(AR54:AR55) | AS56: =SUM(AS54:AS55) | AU56: =SUM(AU54:AU55) | AV56: =SUM(AV54:AV55) | AW56: =SUM(AW54:AW55) | AX56: =SUM(AX54:AX55) | AY56: =SUM(AY54:AY55) | AZ56: =SUM(AZ54:AZ55) | BA56: =SUM(BA54:BA55) | BB56: =SUM(BB54:BB55) | BC56: =SUM(BC54:BC55) | BE56: =SUM(BE54:BE55) | BF56: =SUM(BF54:BF55) | BG56: =SUM(BG54:BG55) | BH56: =SUM(BH54:BH55) | BI56: =SUM(BI54:BI55) | BJ56: =SUM(BJ54:BJ55) | BK56: =SUM(BK54:BK55) | BL56: =SUM(BL54:BL55) | BM56: =SUM(BM54:BM55) | BO56: =SUM(BO54:BO55) | BP56: =SUM(BP54:BP55) | BQ56: =SUM(BQ54:BQ55) | BR56: =SUM(BR54:BR55) | BS56: =SUM(BS54:BS55) | BT56: =SUM(BT54:BT55) | BU56: =SUM(BU54:BU55) | BV56: =SUM(BV54:BV55) | BW56: =SUM(BW54:BW55) | BY56: =SUM(BY54:BY55) | BZ56: =SUM(BZ54:BZ55) | CA56: =SUM(CA54:CA55) | CB56: =SUM(CB54:CB55) | CC56: =SUM(CC54:CC55) | CD56: =SUM(CD54:CD55) | CE56: =SUM(CE54:CE55) | CF56: =SUM(CF54:CF55) | CG56: =SUM(CG54:CG55) | CI56: =SUM(CI54:CI55) | CJ56: =SUM(CJ54:CJ55) | CK56: =SUM(CK54:CK55) | CL56: =SUM(CL54:CL55) | CM56: =SUM(CM54:CM55) | CN56: =SUM(CN54:CN55) | CO56: =SUM(CO54:CO55) | CP56: =SUM(CP54:CP55) | CQ56: =SUM(CQ54:CQ55) | CS56: =SUM(CS54:CS55) | CT56: =SUM(CT54:CT55) | CU56: =SUM(CU54:CU55) | CV56: =SUM(CV54:CV55) | CW56: =SUM(CW54:CW55) | CX56: =SUM(CX54:CX55) | CY56: =SUM(CY54:CY55) | CZ56: =SUM(CZ54:CZ55) | DA56: =SUM(DA54:DA55) | DC56: =SUM(DC54:DC55) | DD56: =SUM(DD54:DD55) | DE56: =SUM(DE54:DE55) | DF56: =SUM(DF54:DF55) | DG56: =SUM(DG54:DG55) | DH56: =SUM(DH54:DH55) | DI56: =SUM(DI54:DI55) | DJ56: =SUM(DJ54:DJ55) | DK56: =SUM(DK54:DK55) | DM56: =SUM(DM54:DM55) | DN56: =SUM(DN54:DN55) | DP56: =IFERROR((DE56-CU56)/CU56,"-") | DQ56: =IFERROR((DG56-CW56)/CW56,"-") | DR56: =IFERROR((DH56-CX56)/CX56,"-") | DS56: =SUM(DS54:DS55) | DT56: =SUM(DT54:DT55) | DU56: =SUM(DU54:DU55) | DV56: =SUM(DV54:DV55) | DW56: =SUM(DW54:DW55) | DX56: =SUM(DX54:DX55) | DY56: =SUM(DY54:DY55) | DZ56: =SUM(DZ54:DZ55) | EA56: =SUM(EA54:EA55) | EC56: =SUM(EC54:EC55) | ED56: =SUM(ED54:ED55) | EF56: =IFERROR((DU56-DE56)/DE56,"-") | EG56: =IFERROR((DW56-DG56)/DG56,"-") | EH56: =IFERROR((DX56-DH56)/DH56,"-") | EJ56: =SUM(EJ54:EJ55) | EK56: =SUM(EK54:EK55) | EL56: =SUM(EL54:EL55) | EM56: =SUM(EM54:EM55) | EN56: =SUM(EN54:EN55) | EO56: =SUM(EO54:EO55) | EP56: =SUM(EP54:EP55) | EQ56: =SUM(EQ54:EQ55) | ER56: =SUM(ER54:ER55) | ET56: =SUM(ET54:ET55) | EU56: =SUM(EU54:EU55) | EW56: =IFERROR((EL56-DU56)/DU56,"-") | EX56: =IFERROR((EN56-DW56)/DW56,"-") | EY56: =IFERROR((EO56-DX56)/DX56,"-")
A57: Passive-E/D
A58: GOLD ETF | B58: Other Schemes | C58: Open ended Schemes | D58: Debt-ETF | E58: Debt-ETF | F58: Passive-E/D | K58: =IF(OR(I58="",J58=""),"",I58-J58) | L58: 58887.991 | M58: 57101.287 | P58: - | Q58: 20 | R58: 7144848 | S58: 1663.259 | T58: 1669.0788 | U58: -5.8197261 | V58: 61422.195 | W58: 60631.367 | X58: 0 | Y58: 0 | Z58: - | AA58: 20 | AB58: 7368808 | AC58: 1266.1923 | AD58: 974.28075 | AE58: 291.91154 | AF58: 62452.936 | AG58: 62124.925 | AH58: 0 | AI58: 0 | AJ58: - | AK58: 20 | AL58: 7654158 | AM58: 2368.9898 | AN58: 288.14412 | AO58: 2080.8456 | AP58: 64777.226 | AQ58: 64833.43 | AR58: 0 | AS58: 0 | AT58: - | AU58: 21 | AV58: 7869544 | AW58: 1444.3175 | AX58: 188.22306 | AY58: 1256.0945 | AZ58: 67634.519 | BA58: 66664.074 | BB58: 0 | BC58: 0 | BD58: - | BE58: 21 | BF58: 8033855 | BG58: 2334.2308 | BH58: 144.71788 | BI58: 2189.5129 | BJ58: 72495.597 | BK58: 69918.716 | BL58: 0 | BM58: 0 | BN58: - | BO58: 22 | BP58: 8663662 | BQ58: 8460.8462 | BR58: 97.715932 | BS58: 8363.1302 | BT58: 90135.984 | BU58: 81700.391 | BV58: 0 | BW58: 0 | BX58: - | BY58: 22 | BZ58: 9575399 | CA58: 9898.6344 | CB58: 2155.4445 | CC58: 7743.1899 | CD58: 102119.86 | CE58: 102088.99 | CF58: 0 | CG58: 0 | CH58: - | CI58: 23 | CJ58: 9784310 | CK58: 4137.6076 | CL58: 395.81274 | CM58: 3741.7949 | CN58: 110517.76 | CO58: 106020.76 | CP58: 0 | CQ58: 0 | CR58: - | CS58: 25 | CT58: 10225561 | CU58: 11850.588 | CV58: 203.84816 | CW58: 11646.74 | CX58: 127896.38 | CY58: 120867.22 | CZ58: 0 | DA58: 0 | DB58: - | DC58: 25 | DD58: 11437218 | DE58: 24351.577 | DF58: 311.61689 | DG58: 24039.96 | DH58: 184276.96 | DI58: 150380.66 | DJ58: 0 | DK58: 0 | DL58: - | DM58: =S58+AC58+AM58+AW58+BG58+BQ58+CA58+CK58+CU58+DE58 | DN58: =U58+AE58+AO58+AY58+BI58+BS58+CC58+CM58+CW58+DG58 | DO58: - | DP58: =IFERROR((DE58-CU58)/CU58,"-") | DQ58: =IFERROR((DG58-CW58)/CW58,"-") | DR58: =IFERROR((DH58-CX58)/CX58,"-") | DS58: 25 | DT58: 12089782 | DU58: 7755.192 | DV58: 2500.2379 | DW58: 5254.9541 | DX58: 183325.43 | DY58: 177591.05 | DZ58: 0 | EA58: 0 | EB58: - | EC58: =S58+AC58+AM58+AW58+BG58+BQ58+CA58+CK58+CU58+DE58+DU58 | ED58: =U58+AE58+AO58+AY58+BI58+BS58+CC58+CM58+CW58+DG58+DW58 | EE58: - | EF58: =IFERROR((DU58-DE58)/DE58,"-") | EG58: =IFERROR((DW58-DG58)/DG58,"-") | EH58: =IFERROR((DX58-DH58)/DH58,"-") | EI58: - | EJ58: 26 | EK58: 12397731 | EL58: 5425.6035 | EM58: 3159.9235 | EN58: 2265.68 | EO58: 171468.35 | EP58: 178521.93 | EQ58: 0 | ER58: 0 | ES58: - | ET58: =S58+AC58+AM58+AW58+BG58+BQ58+CA58+CK58+CU58+DE58+DU58+EL58 | EU58: =U58+AE58+AO58+AY58+BI58+BS58+CC58+CM58+CW58+DG58+DW58+EN58 | EV58: - | EW58: =IFERROR((EL58-DU58)/DU58,"-") | EX58: =IFERROR((EN58-DW58)/DW58,"-") | EY58: =IFERROR((EO58-DX58)/DX58,"-")
A59: Other ETFs | B59: Other Schemes | C59: Open ended Schemes | D59: Equity-ETF | E59: Equity-ETF | F59: Passive-E/D | K59: =IF(OR(I59="",J59=""),"",I59-J59) | L59: 779630.19 | M59: 753854.5 | P59: - | Q59: 233 | R59: 20228722 | S59: 32840.788 | T59: 13784.129 | U59: 19056.659 | V59: 813120.65 | W59: 785026.31 | X59: 0 | Y59: 0 | Z59: - | AA59: 240 | AB59: 20493330 | AC59: 18281.265 | AD59: 14194.451 | AE59: 4086.8146 | AF59: 833965.85 | AG59: 826197.95 | AH59: 0 | AI59: 0 | AJ59: - | AK59: 246 | AL59: 20613868 | AM59: 16480.758 | AN59: 15636.331 | AO59: 844.42638 | AP59: 859260.59 | AQ59: 843878.11 | AR59: 0 | AS59: 0 | AT59: - | AU59: 252 | AV59: 20810327 | AW59: 18136.057 | AX59: 13659.144 | AY59: 4476.9124 | AZ59: 844401.99 | BA59: 852466.94 | BB59: 0 | BC59: 0 | BD59: - | BE59: 258 | BF59: 21252597 | BG59: 15315.893 | BH59: 8071.7794 | BI59: 7244.1131 | BJ59: 842201.47 | BK59: 846007.59 | BL59: 0 | BM59: 0 | BN59: - | BO59: 260 | BP59: 21740194 | BQ59: 20731.175 | BR59: 12580.381 | BS59: 8150.7935 | BT59: 865687.56 | BU59: 866031.77 | BV59: 0 | BW59: 0 | BX59: - | BY59: 268 | BZ59: 22859737 | CA59: 22739.323 | CB59: 16557.625 | CC59: 6181.6986 | CD59: 908398.92 | CE59: 900452.51 | CF59: 0 | CG59: 0 | CH59: - | CI59: 278 | CJ59: 23129290 | CK59: 18339.925 | CL59: 8619.1833 | CM59: 9720.7418 | CN59: 936137.64 | CO59: 919060.94 | CP59: 0 | CQ59: 0 | CR59: - | CS59: 286 | CT59: 23969652 | CU59: 25716.546 | CV59: 12517.109 | CW59: 13199.437 | CX59: 966503.97 | CY59: 947036.18 | CZ59: 0 | DA59: 0 | DB59: - | DC59: 289 | DD59: 26057440 | DE59: 34387.696 | DF59: 19381.83 | DG59: 15005.866 | DH59: 997350.41 | DI59: 979921.33 | DJ59: 0 | DK59: 0 | DL59: - | DM59: =S59+AC59+AM59+AW59+BG59+BQ59+CA59+CK59+CU59+DE59 | DN59: =U59+AE59+AO59+AY59+BI59+BS59+CC59+CM59+CW59+DG59 | DO59: - | DP59: =IFERROR((DE59-CU59)/CU59,"-") | DQ59: =IFERROR((DG59-CW59)/CW59,"-") | DR59: =IFERROR((DH59-CX59)/CX59,"-") | DS59: 296 | DT59: 27120892 | DU59: 25137.328 | DV59: 20650.179 | DW59: 4487.1485 | DX59: 976208.43 | DY59: 980273.33 | DZ59: 0 | EA59: 0 | EB59: - | EC59: =S59+AC59+AM59+AW59+BG59+BQ59+CA59+CK59+CU59+DE59+DU59 | ED59: =U59+AE59+AO59+AY59+BI59+BS59+CC59+CM59+CW59+DG59+DW59 | EE59: - | EF59: =IFERROR((DU59-DE59)/DE59,"-") | EG59: =IFERROR((DW59-DG59)/DG59,"-") | EH59: =IFERROR((DX59-DH59)/DH59,"-") | EI59: - | EJ59: 302 | EK59: 27944219 | EL59: 44649.57 | EM59: 24847.155 | EN59: 19802.415 | EO59: 894644.27 | EP59: 930915.2 | EQ59: 0 | ER59: 0 | ES59: - | ET59: =S59+AC59+AM59+AW59+BG59+BQ59+CA59+CK59+CU59+DE59+DU59+EL59 | EU59: =U59+AE59+AO59+AY59+BI59+BS59+CC59+CM59+CW59+DG59+DW59+EN59 | EV59: - | EW59: =IFERROR((EL59-DU59)/DU59,"-") | EX59: =IFERROR((EN59-DW59)/DW59,"-") | EY59: =IFERROR((EO59-DX59)/DX59,"-")
A60: Index Funds | B60: Other Schemes | C60: Open ended Schemes | D60: Index Funds | E60: Index Funds-E/D | F60: Passive-E/D | K60: =IF(OR(I60="",J60=""),"",I60-J60) | L60: 283397.13 | M60: 276621.48 | P60: - | Q60: 309 | R60: 13142219 | S60: 8880.9252 | T60: 7325.4867 | U60: 1555.4385 | V60: 292205.91 | W60: 286063.24 | X60: 0 | Y60: 0 | Z60: - | AA60: 316 | AB60: 13234811 | AC60: 8578.5802 | AD60: 7474.16 | AE60: 1104.4202 | AF60: 300811.48 | AG60: 296889.63 | AH60: 0 | AI60: 0 | AJ60: - | AK60: 324 | AL60: 13498534 | AM60: 8041.9699 | AN60: 6998.8833 | AO60: 1043.0866 | AP60: 308996.39 | AQ60: 304566.89 | AR60: 0 | AS60: 0 | AT60: - | AU60: 330 | AV60: 13698815 | AW60: 9229.248 | AX60: 6899.3747 | AY60: 2329.8732 | AZ60: 305829.46 | BA60: 308319.11 | BB60: 0 | BC60: 0 | BD60: - | BE60: 341 | BF60: 13953213 | BG60: 7684.6188 | BH60: 6182.0489 | BI60: 1502.5699 | BJ60: 304234.99 | BK60: 305471.69 | BL60: 0 | BM60: 0 | BN60: - | BO60: 344 | BP60: 14089501 | BQ60: 9066.0965 | BR60: 7485.4447 | BS60: 1580.6518 | BT60: 308893.41 | BU60: 310802.27 | BV60: 0 | BW60: 0 | BX60: - | BY60: 345 | BZ60: 14179440 | CA60: 9475.0902 | CB60: 7545.6674 | CC60: 1929.4228 | CD60: 320075.92 | CE60: 316924.74 | CF60: 0 | CG60: 0 | CH60: - | CI60: 348 | CJ60: 14338654 | CK60: 8701.8452 | CL60: 6975.0396 | CM60: 1726.8055 | CN60: 324848 | CO60: 322516.84 | CP60: 0 | CQ60: 0 | CR60: - | CS60: 352 | CT60: 14401091 | CU60: 10596.366 | CV60: 8865.8687 | CW60: 1730.4969 | CX60: 325821.4 | CY60: 323759.43 | CZ60: 0 | DA60: 0 | DB60: - | DC60: 354 | DD60: 14524940 | DE60: 8526.2222 | DF60: 8498.9254 | DG60: 27.29682 | DH60: 320493.86 | DI60: 322963.64 | DJ60: 0 | DK60: 0 | DL60: - | DM60: =S60+AC60+AM60+AW60+BG60+BQ60+CA60+CK60+CU60+DE60 | DN60: =U60+AE60+AO60+AY60+BI60+BS60+CC60+CM60+CW60+DG60 | DO60: - | DP60: =IFERROR((DE60-CU60)/CU60,"-") | DQ60: =IFERROR((DG60-CW60)/CW60,"-") | DR60: =IFERROR((DH60-CX60)/CX60,"-") | DS60: 356 | DT60: 14780965 | DU60: 10331.992 | DV60: 7098.5568 | DW60: 3233.4356 | DX60: 324567.3 | DY60: 325079.05 | DZ60: 0 | EA60: 0 | EB60: - | EC60: =S60+AC60+AM60+AW60+BG60+BQ60+CA60+CK60+CU60+DE60+DU60 | ED60: =U60+AE60+AO60+AY60+BI60+BS60+CC60+CM60+CW60+DG60+DW60 | EE60: - | EF60: =IFERROR((DU60-DE60)/DE60,"-") | EG60: =IFERROR((DW60-DG60)/DG60,"-") | EH60: =IFERROR((DX60-DH60)/DH60,"-") | EI60: - | EJ60: 360 | EK60: 15030991 | EL60: 18615.346 | EM60: 10446.588 | EN60: 8168.7583 | EO60: 307315.46 | EP60: 315059.68 | EQ60: 0 | ER60: 0 | ES60: - | ET60: =S60+AC60+AM60+AW60+BG60+BQ60+CA60+CK60+CU60+DE60+DU60+EL60 | EU60: =U60+AE60+AO60+AY60+BI60+BS60+CC60+CM60+CW60+DG60+DW60+EN60 | EV60: - | EW60: =IFERROR((EL60-DU60)/DU60,"-") | EX60: =IFERROR((EN60-DW60)/DW60,"-") | EY60: =IFERROR((EO60-DX60)/DX60,"-")
A61: Total for Passive-E/D | G61: =SUM(G58:G60) | H61: =SUM(H58:H60) | I61: =SUM(I58:I60) | J61: =SUM(J58:J60) | K61: =SUM(K58:K60) | L61: =SUM(L58:L60) | M61: =SUM(M58:M60) | N61: =SUM(N58:N60) | O61: =SUM(O58:O60) | Q61: =SUM(Q58:Q60) | R61: =SUM(R58:R60) | S61: =SUM(S58:S60) | T61: =SUM(T58:T60) | U61: =SUM(U58:U60) | V61: =SUM(V58:V60) | W61: =SUM(W58:W60) | X61: =SUM(X58:X60) | Y61: =SUM(Y58:Y60) | AA61: =SUM(AA58:AA60) | AB61: =SUM(AB58:AB60) | AC61: =SUM(AC58:AC60) | AD61: =SUM(AD58:AD60) | AE61: =SUM(AE58:AE60) | AF61: =SUM(AF58:AF60) | AG61: =SUM(AG58:AG60) | AH61: =SUM(AH58:AH60) | AI61: =SUM(AI58:AI60) | AK61: =SUM(AK58:AK60) | AL61: =SUM(AL58:AL60) | AM61: =SUM(AM58:AM60) | AN61: =SUM(AN58:AN60) | AO61: =SUM(AO58:AO60) | AP61: =SUM(AP58:AP60) | AQ61: =SUM(AQ58:AQ60) | AR61: =SUM(AR58:AR60) | AS61: =SUM(AS58:AS60) | AU61: =SUM(AU58:AU60) | AV61: =SUM(AV58:AV60) | AW61: =SUM(AW58:AW60) | AX61: =SUM(AX58:AX60) | AY61: =SUM(AY58:AY60) | AZ61: =SUM(AZ58:AZ60) | BA61: =SUM(BA58:BA60) | BB61: =SUM(BB58:BB60) | BC61: =SUM(BC58:BC60) | BE61: =SUM(BE58:BE60) | BF61: =SUM(BF58:BF60) | BG61: =SUM(BG58:BG60) | BH61: =SUM(BH58:BH60) | BI61: =SUM(BI58:BI60) | BJ61: =SUM(BJ58:BJ60) | BK61: =SUM(BK58:BK60) | BL61: =SUM(BL58:BL60) | BM61: =SUM(BM58:BM60) | BO61: =SUM(BO58:BO60) | BP61: =SUM(BP58:BP60) | BQ61: =SUM(BQ58:BQ60) | BR61: =SUM(BR58:BR60) | BS61: =SUM(BS58:BS60) | BT61: =SUM(BT58:BT60) | BU61: =SUM(BU58:BU60) | BV61: =SUM(BV58:BV60) | BW61: =SUM(BW58:BW60) | BY61: =SUM(BY58:BY60) | BZ61: =SUM(BZ58:BZ60) | CA61: =SUM(CA58:CA60) | CB61: =SUM(CB58:CB60) | CC61: =SUM(CC58:CC60) | CD61: =SUM(CD58:CD60) | CE61: =SUM(CE58:CE60) | CF61: =SUM(CF58:CF60) | CG61: =SUM(CG58:CG60) | CI61: =SUM(CI58:CI60) | CJ61: =SUM(CJ58:CJ60) | CK61: =SUM(CK58:CK60) | CL61: =SUM(CL58:CL60) | CM61: =SUM(CM58:CM60) | CN61: =SUM(CN58:CN60) | CO61: =SUM(CO58:CO60) | CP61: =SUM(CP58:CP60) | CQ61: =SUM(CQ58:CQ60) | CS61: =SUM(CS58:CS60) | CT61: =SUM(CT58:CT60) | CU61: =SUM(CU58:CU60) | CV61: =SUM(CV58:CV60) | CW61: =SUM(CW58:CW60) | CX61: =SUM(CX58:CX60) | CY61: =SUM(CY58:CY60) | CZ61: =SUM(CZ58:CZ60) | DA61: =SUM(DA58:DA60) | DC61: =SUM(DC58:DC60) | DD61: =SUM(DD58:DD60) | DE61: =SUM(DE58:DE60) | DF61: =SUM(DF58:DF60) | DG61: =SUM(DG58:DG60) | DH61: =SUM(DH58:DH60) | DI61: =SUM(DI58:DI60) | DJ61: =SUM(DJ58:DJ60) | DK61: =SUM(DK58:DK60) | DM61: =SUM(DM58:DM60) | DN61: =SUM(DN58:DN60) | DP61: =IFERROR((DE61-CU61)/CU61,"-") | DQ61: =IFERROR((DG61-CW61)/CW61,"-") | DR61: =IFERROR((DH61-CX61)/CX61,"-") | DS61: =SUM(DS58:DS60) | DT61: =SUM(DT58:DT60) | DU61: =SUM(DU58:DU60) | DV61: =SUM(DV58:DV60) | DW61: =SUM(DW58:DW60) | DX61: =SUM(DX58:DX60) | DY61: =SUM(DY58:DY60) | DZ61: =SUM(DZ58:DZ60) | EA61: =SUM(EA58:EA60) | EC61: =SUM(EC58:EC60) | ED61: =SUM(ED58:ED60) | EF61: =IFERROR((DU61-DE61)/DE61,"-") | EG61: =IFERROR((DW61-DG61)/DG61,"-") | EH61: =IFERROR((DX61-DH61)/DH61,"-") | EJ61: =SUM(EJ58:EJ60) | EK61: =SUM(EK58:EK60) | EL61: =SUM(EL58:EL60) | EM61: =SUM(EM58:EM60) | EN61: =SUM(EN58:EN60) | EO61: =SUM(EO58:EO60) | EP61: =SUM(EP58:EP60) | EQ61: =SUM(EQ58:EQ60) | ER61: =SUM(ER58:ER60) | ET61: =SUM(ET58:ET60) | EU61: =SUM(EU58:EU60) | EW61: =IFERROR((EL61-DU61)/DU61,"-") | EX61: =IFERROR((EN61-DW61)/DW61,"-") | EY61: =IFERROR((EO61-DX61)/DX61,"-")
A62: Interval Schemes
A63: Growth/Equity Oriented Schemes | B63: Interval Schemes | C63: - | D63: - | E63: - | F63: Interval Schemes | K63: =IF(OR(I63="",J63=""),"",I63-J63) | L63: 0 | M63: 0 | P63: - | Q63: 0 | R63: 0 | S63: 0 | T63: 0 | U63: 0 | V63: 0 | W63: 0 | X63: 0 | Y63: 0 | Z63: - | AA63: 0 | AB63: 0 | AC63: 0 | AD63: 0 | AE63: 0 | AF63: 0 | AG63: 0 | AH63: 0 | AI63: 0 | AJ63: - | AK63: 0 | AL63: 0 | AM63: 0 | AN63: 0 | AO63: 0 | AP63: 0 | AQ63: 0 | AR63: 0 | AS63: 0 | AT63: - | AU63: 0 | AV63: 0 | AW63: 0 | AX63: 0 | AY63: 0 | AZ63: 0 | BA63: 0 | BB63: 0 | BC63: 0 | BD63: - | BE63: 0 | BF63: 0 | BG63: 0 | BH63: 0 | BI63: 0 | BJ63: 0 | BK63: 0 | BL63: 0 | BM63: 0 | BN63: - | BO63: 0 | BP63: 0 | BQ63: 0 | BR63: 0 | BS63: 0 | BT63: 0 | BU63: 0 | BV63: 0 | BW63: 0 | BX63: - | BY63: 0 | BZ63: 0 | CA63: 0 | CB63: 0 | CC63: 0 | CD63: 0 | CE63: 0 | CF63: 0 | CG63: 0 | CH63: - | CI63: 0 | CJ63: 0 | CK63: 0 | CL63: 0 | CM63: 0 | CN63: 0 | CO63: 0 | CP63: 0 | CQ63: 0 | CR63: - | CS63: 0 | CT63: 0 | CU63: 0 | CV63: 0 | CW63: 0 | CX63: 0 | CY63: 0 | CZ63: 0 | DA63: 0 | DB63: - | DC63: 0 | DD63: 0 | DE63: 0 | DF63: 0 | DG63: 0 | DH63: 0 | DI63: 0 | DJ63: 0 | DK63: 0 | DL63: - | DM63: =S63+AC63+AM63+AW63+BG63+BQ63+CA63+CK63+CU63+DE63 | DN63: =U63+AE63+AO63+AY63+BI63+BS63+CC63+CM63+CW63+DG63 | DO63: - | DP63: 0 | DQ63: 0 | DR63: 0 | DS63: 0 | DT63: 0 | DU63: 0 | DV63: 0 | DW63: 0 | DX63: 0 | DY63: 0 | DZ63: 0 | EA63: 0 | EB63: - | EC63: =S63+AC63+AM63+AW63+BG63+BQ63+CA63+CK63+CU63+DE63+DU63 | ED63: =U63+AE63+AO63+AY63+BI63+BS63+CC63+CM63+CW63+DG63+DW63 | EE63: - | EF63: =IFERROR((DU63-DE63)/DE63,"-") | EG63: =IFERROR((DW63-DG63)/DG63,"-") | EH63: =IFERROR((DX63-DH63)/DH63,"-") | EI63: - | EJ63: 0 | EK63: 0 | EL63: 0 | EM63: 0 | EN63: 0 | EO63: 0 | EP63: 0 | EQ63: 0 | ER63: 0 | ES63: - | ET63: =S63+AC63+AM63+AW63+BG63+BQ63+CA63+CK63+CU63+DE63+DU63+EL63 | EU63: =U63+AE63+AO63+AY63+BI63+BS63+CC63+CM63+CW63+DG63+DW63+EN63 | EV63: - | EW63: =IFERROR((EL63-DU63)/DU63,"-") | EX63: =IFERROR((EN63-DW63)/DW63,"-") | EY63: =IFERROR((EO63-DX63)/DX63,"-")
A64: Total for Interval Schemes | G64: =SUM(G63:G63) | H64: =SUM(H63:H63) | I64: =SUM(I63:I63) | J64: =SUM(J63:J63) | K64: =SUM(K63:K63) | L64: =SUM(L63:L63) | M64: =SUM(M63:M63) | N64: =SUM(N63:N63) | O64: =SUM(O63:O63) | Q64: =SUM(Q63:Q63) | R64: =SUM(R63:R63) | S64: =SUM(S63:S63) | T64: =SUM(T63:T63) | U64: =SUM(U63:U63) | V64: =SUM(V63:V63) | W64: =SUM(W63:W63) | X64: =SUM(X63:X63) | Y64: =SUM(Y63:Y63) | AA64: =SUM(AA63:AA63) | AB64: =SUM(AB63:AB63) | AC64: =SUM(AC63:AC63) | AD64: =SUM(AD63:AD63) | AE64: =SUM(AE63:AE63) | AF64: =SUM(AF63:AF63) | AG64: =SUM(AG63:AG63) | AH64: =SUM(AH63:AH63) | AI64: =SUM(AI63:AI63) | AK64: =SUM(AK63:AK63) | AL64: =SUM(AL63:AL63) | AM64: =SUM(AM63:AM63) | AN64: =SUM(AN63:AN63) | AO64: =SUM(AO63:AO63) | AP64: =SUM(AP63:AP63) | AQ64: =SUM(AQ63:AQ63) | AR64: =SUM(AR63:AR63) | AS64: =SUM(AS63:AS63) | AU64: =SUM(AU63:AU63) | AV64: =SUM(AV63:AV63) | AW64: =SUM(AW63:AW63) | AX64: =SUM(AX63:AX63) | AY64: =SUM(AY63:AY63) | AZ64: =SUM(AZ63:AZ63) | BA64: =SUM(BA63:BA63) | BB64: =SUM(BB63:BB63) | BC64: =SUM(BC63:BC63) | BE64: =SUM(BE63:BE63) | BF64: =SUM(BF63:BF63) | BG64: =SUM(BG63:BG63) | BH64: =SUM(BH63:BH63) | BI64: =SUM(BI63:BI63) | BJ64: =SUM(BJ63:BJ63) | BK64: =SUM(BK63:BK63) | BL64: =SUM(BL63:BL63) | BM64: =SUM(BM63:BM63) | BO64: =SUM(BO63:BO63) | BP64: =SUM(BP63:BP63) | BQ64: =SUM(BQ63:BQ63) | BR64: =SUM(BR63:BR63) | BS64: =SUM(BS63:BS63) | BT64: =SUM(BT63:BT63) | BU64: =SUM(BU63:BU63) | BV64: =SUM(BV63:BV63) | BW64: =SUM(BW63:BW63) | BY64: =SUM(BY63:BY63) | BZ64: =SUM(BZ63:BZ63) | CA64: =SUM(CA63:CA63) | CB64: =SUM(CB63:CB63) | CC64: =SUM(CC63:CC63) | CD64: =SUM(CD63:CD63) | CE64: =SUM(CE63:CE63) | CF64: =SUM(CF63:CF63) | CG64: =SUM(CG63:CG63) | CI64: =SUM(CI63:CI63) | CJ64: =SUM(CJ63:CJ63) | CK64: =SUM(CK63:CK63) | CL64: =SUM(CL63:CL63) | CM64: =SUM(CM63:CM63) | CN64: =SUM(CN63:CN63) | CO64: =SUM(CO63:CO63) | CP64: =SUM(CP63:CP63) | CQ64: =SUM(CQ63:CQ63) | CS64: =SUM(CS63:CS63) | CT64: =SUM(CT63:CT63) | CU64: =SUM(CU63:CU63) | CV64: =SUM(CV63:CV63) | CW64: =SUM(CW63:CW63) | CX64: =SUM(CX63:CX63) | CY64: =SUM(CY63:CY63) | CZ64: =SUM(CZ63:CZ63) | DA64: =SUM(DA63:DA63) | DC64: =SUM(DC63:DC63) | DD64: =SUM(DD63:DD63) | DE64: =SUM(DE63:DE63) | DF64: =SUM(DF63:DF63) | DG64: =SUM(DG63:DG63) | DH64: =SUM(DH63:DH63) | DI64: =SUM(DI63:DI63) | DJ64: =SUM(DJ63:DJ63) | DK64: =SUM(DK63:DK63) | DM64: =SUM(DM63:DM63) | DN64: =SUM(DN63:DN63) | DP64: =IFERROR((DE64-CU64)/CU64,"-") | DQ64: =IFERROR((DG64-CW64)/CW64,"-") | DR64: =IFERROR((DH64-CX64)/CX64,"-") | DS64: =SUM(DS63:DS63) | DT64: =SUM(DT63:DT63) | DU64: =SUM(DU63:DU63) | DV64: =SUM(DV63:DV63) | DW64: =SUM(DW63:DW63) | DX64: =SUM(DX63:DX63) | DY64: =SUM(DY63:DY63) | DZ64: =SUM(DZ63:DZ63) | EA64: =SUM(EA63:EA63) | EC64: =SUM(EC63:EC63) | ED64: =SUM(ED63:ED63) | EF64: =IFERROR((DU64-DE64)/DE64,"-") | EG64: =IFERROR((DW64-DG64)/DG64,"-") | EH64: =IFERROR((DX64-DH64)/DH64,"-") | EJ64: =SUM(EJ63:EJ63) | EK64: =SUM(EK63:EK63) | EL64: =SUM(EL63:EL63) | EM64: =SUM(EM63:EM63) | EN64: =SUM(EN63:EN63) | EO64: =SUM(EO63:EO63) | EP64: =SUM(EP63:EP63) | EQ64: =SUM(EQ63:EQ63) | ER64: =SUM(ER63:ER63) | ET64: =SUM(ET63:ET63) | EU64: =SUM(EU63:EU63) | EW64: =IFERROR((EL64-DU64)/DU64,"-") | EX64: =IFERROR((EN64-DW64)/DW64,"-") | EY64: =IFERROR((EO64-DX64)/DX64,"-")
A65: Grand Total | G65: =SUM(G25,G29,G52,G56,G61,G64) | H65: =SUM(H25,H29,H52,H56,H61,H64) | I65: =SUM(I25,I29,I52,I56,I61,I64) | J65: =SUM(J25,J29,J52,J56,J61,J64) | K65: =SUM(K25,K29,K52,K56,K61,K64) | L65: =SUM(L25,L29,L52,L56,L61,L64) | M65: =SUM(M25,M29,M52,M56,M61,M64) | N65: =SUM(N25,N29,N52,N56,N61,N64) | O65: =SUM(O25,O29,O52,O56,O61,O64) | Q65: =SUM(Q25,Q29,Q52,Q56,Q61,Q64) | R65: =SUM(R25,R29,R52,R56,R61,R64) | S65: =SUM(S25,S29,S52,S56,S61,S64) | T65: =SUM(T25,T29,T52,T56,T61,T64) | U65: =SUM(U25,U29,U52,U56,U61,U64) | V65: =SUM(V25,V29,V52,V56,V61,V64) | W65: =SUM(W25,W29,W52,W56,W61,W64) | X65: =SUM(X25,X29,X52,X56,X61,X64) | Y65: =SUM(Y25,Y29,Y52,Y56,Y61,Y64) | AA65: =SUM(AA25,AA29,AA52,AA56,AA61,AA64) | AB65: =SUM(AB25,AB29,AB52,AB56,AB61,AB64) | AC65: =SUM(AC25,AC29,AC52,AC56,AC61,AC64) | AD65: =SUM(AD25,AD29,AD52,AD56,AD61,AD64) | AE65: =SUM(AE25,AE29,AE52,AE56,AE61,AE64) | AF65: =SUM(AF25,AF29,AF52,AF56,AF61,AF64) | AG65: =SUM(AG25,AG29,AG52,AG56,AG61,AG64) | AH65: =SUM(AH25,AH29,AH52,AH56,AH61,AH64) | AI65: =SUM(AI25,AI29,AI52,AI56,AI61,AI64) | AK65: =SUM(AK25,AK29,AK52,AK56,AK61,AK64) | AL65: =SUM(AL25,AL29,AL52,AL56,AL61,AL64) | AM65: =SUM(AM25,AM29,AM52,AM56,AM61,AM64) | AN65: =SUM(AN25,AN29,AN52,AN56,AN61,AN64) | AO65: =SUM(AO25,AO29,AO52,AO56,AO61,AO64) | AP65: =SUM(AP25,AP29,AP52,AP56,AP61,AP64) | AQ65: =SUM(AQ25,AQ29,AQ52,AQ56,AQ61,AQ64) | AR65: =SUM(AR25,AR29,AR52,AR56,AR61,AR64) | AS65: =SUM(AS25,AS29,AS52,AS56,AS61,AS64) | AU65: =SUM(AU25,AU29,AU52,AU56,AU61,AU64) | AV65: =SUM(AV25,AV29,AV52,AV56,AV61,AV64) | AW65: =SUM(AW25,AW29,AW52,AW56,AW61,AW64) | AX65: =SUM(AX25,AX29,AX52,AX56,AX61,AX64) | AY65: =SUM(AY25,AY29,AY52,AY56,AY61,AY64) | AZ65: =SUM(AZ25,AZ29,AZ52,AZ56,AZ61,AZ64) | BA65: =SUM(BA25,BA29,BA52,BA56,BA61,BA64) | BB65: =SUM(BB25,BB29,BB52,BB56,BB61,BB64) | BC65: =SUM(BC25,BC29,BC52,BC56,BC61,BC64) | BE65: =SUM(BE25,BE29,BE52,BE56,BE61,BE64) | BF65: =SUM(BF25,BF29,BF52,BF56,BF61,BF64) | BG65: =SUM(BG25,BG29,BG52,BG56,BG61,BG64) | BH65: =SUM(BH25,BH29,BH52,BH56,BH61,BH64) | BI65: =SUM(BI25,BI29,BI52,BI56,BI61,BI64) | BJ65: =SUM(BJ25,BJ29,BJ52,BJ56,BJ61,BJ64) | BK65: =SUM(BK25,BK29,BK52,BK56,BK61,BK64) | BL65: =SUM(BL25,BL29,BL52,BL56,BL61,BL64) | BM65: =SUM(BM25,BM29,BM52,BM56,BM61,BM64) | BO65: =SUM(BO25,BO29,BO52,BO56,BO61,BO64) | BP65: =SUM(BP25,BP29,BP52,BP56,BP61,BP64) | BQ65: =SUM(BQ25,BQ29,BQ52,BQ56,BQ61,BQ64) | BR65: =SUM(BR25,BR29,BR52,BR56,BR61,BR64) | BS65: =SUM(BS25,BS29,BS52,BS56,BS61,BS64) | BT65: =SUM(BT25,BT29,BT52,BT56,BT61,BT64) | BU65: =SUM(BU25,BU29,BU52,BU56,BU61,BU64) | BV65: =SUM(BV25,BV29,BV52,BV56,BV61,BV64) | BW65: =SUM(BW25,BW29,BW52,BW56,BW61,BW64) | BY65: =SUM(BY25,BY29,BY52,BY56,BY61,BY64) | BZ65: =SUM(BZ25,BZ29,BZ52,BZ56,BZ61,BZ64) | CA65: =SUM(CA25,CA29,CA52,CA56,CA61,CA64) | CB65: =SUM(CB25,CB29,CB52,CB56,CB61,CB64) | CC65: =SUM(CC25,CC29,CC52,CC56,CC61,CC64) | CD65: =SUM(CD25,CD29,CD52,CD56,CD61,CD64) | CE65: =SUM(CE25,CE29,CE52,CE56,CE61,CE64) | CF65: =SUM(CF25,CF29,CF52,CF56,CF61,CF64) | CG65: =SUM(CG25,CG29,CG52,CG56,CG61,CG64) | CI65: =SUM(CI25,CI29,CI52,CI56,CI61,CI64) | CJ65: =SUM(CJ25,CJ29,CJ52,CJ56,CJ61,CJ64) | CK65: =SUM(CK25,CK29,CK52,CK56,CK61,CK64) | CL65: =SUM(CL25,CL29,CL52,CL56,CL61,CL64) | CM65: =SUM(CM25,CM29,CM52,CM56,CM61,CM64) | CN65: =SUM(CN25,CN29,CN52,CN56,CN61,CN64) | CO65: =SUM(CO25,CO29,CO52,CO56,CO61,CO64) | CP65: =SUM(CP25,CP29,CP52,CP56,CP61,CP64) | CQ65: =SUM(CQ25,CQ29,CQ52,CQ56,CQ61,CQ64) | CS65: =SUM(CS25,CS29,CS52,CS56,CS61,CS64) | CT65: =SUM(CT25,CT29,CT52,CT56,CT61,CT64) | CU65: =SUM(CU25,CU29,CU52,CU56,CU61,CU64) | CV65: =SUM(CV25,CV29,CV52,CV56,CV61,CV64) | CW65: =SUM(CW25,CW29,CW52,CW56,CW61,CW64) | CX65: =SUM(CX25,CX29,CX52,CX56,CX61,CX64) | CY65: =SUM(CY25,CY29,CY52,CY56,CY61,CY64) | CZ65: =SUM(CZ25,CZ29,CZ52,CZ56,CZ61,CZ64) | DA65: =SUM(DA25,DA29,DA52,DA56,DA61,DA64) | DC65: =SUM(DC25,DC29,DC52,DC56,DC61,DC64) | DD65: =SUM(DD25,DD29,DD52,DD56,DD61,DD64) | DE65: =SUM(DE25,DE29,DE52,DE56,DE61,DE64) | DF65: =SUM(DF25,DF29,DF52,DF56,DF61,DF64) | DG65: =SUM(DG25,DG29,DG52,DG56,DG61,DG64) | DH65: =SUM(DH25,DH29,DH52,DH56,DH61,DH64) | DI65: =SUM(DI25,DI29,DI52,DI56,DI61,DI64) | DJ65: =SUM(DJ25,DJ29,DJ52,DJ56,DJ61,DJ64) | DK65: =SUM(DK25,DK29,DK52,DK56,DK61,DK64) | DM65: =SUM(DM25,DM29,DM52,DM56,DM61,DM64) | DN65: =SUM(DN25,DN29,DN52,DN56,DN61,DN64) | DP65: =IFERROR((DE65-CU65)/CU65,"-") | DQ65: =IFERROR((DG65-CW65)/CW65,"-") | DR65: =IFERROR((DH65-CX65)/CX65,"-") | DS65: =SUM(DS25,DS29,DS52,DS56,DS61,DS64) | DT65: =SUM(DT25,DT29,DT52,DT56,DT61,DT64) | DU65: =SUM(DU25,DU29,DU52,DU56,DU61,DU64) | DV65: =SUM(DV25,DV29,DV52,DV56,DV61,DV64) | DW65: =SUM(DW25,DW29,DW52,DW56,DW61,DW64) | DX65: =SUM(DX25,DX29,DX52,DX56,DX61,DX64) | DY65: =SUM(DY25,DY29,DY52,DY56,DY61,DY64) | DZ65: =SUM(DZ25,DZ29,DZ52,DZ56,DZ61,DZ64) | EA65: =SUM(EA25,EA29,EA52,EA56,EA61,EA64) | EC65: =SUM(EC25,EC29,EC52,EC56,EC61,EC64) | ED65: =SUM(ED25,ED29,ED52,ED56,ED61,ED64) | EF65: =IFERROR((DU65-DE65)/DE65,"-") | EG65: =IFERROR((DW65-DG65)/DG65,"-") | EH65: =IFERROR((DX65-DH65)/DH65,"-") | EJ65: =SUM(EJ25,EJ29,EJ52,EJ56,EJ61,EJ64) | EK65: =SUM(EK25,EK29,EK52,EK56,EK61,EK64) | EL65: =SUM(EL25,EL29,EL52,EL56,EL61,EL64) | EM65: =SUM(EM25,EM29,EM52,EM56,EM61,EM64) | EN65: =SUM(EN25,EN29,EN52,EN56,EN61,EN64) | EO65: =SUM(EO25,EO29,EO52,EO56,EO61,EO64) | EP65: =SUM(EP25,EP29,EP52,EP56,EP61,EP64) | EQ65: =SUM(EQ25,EQ29,EQ52,EQ56,EQ61,EQ64) | ER65: =SUM(ER25,ER29,ER52,ER56,ER61,ER64) | ET65: =SUM(ET25,ET29,ET52,ET56,ET61,ET64) | EU65: =SUM(EU25,EU29,EU52,EU56,EU61,EU64) | EW65: =IFERROR((EL65-DU65)/DU65,"-") | EX65: =IFERROR((EN65-DW65)/DW65,"-") | EY65: =IFERROR((EO65-DX65)/DX65,"-")
A66: Fund of Funds Scheme (Domestic) ** | P66: - | Q66: ## 96 | R66: 3647098 | S66: 4475.9275 | T66: 3335.9398 | U66: 1139.9878 | V66: 100335.14 | W66: 98868.024 | X66: 0 | Y66: 0 | Z66: - | AA66: ## 102 | AB66: 3854287 | AC66: 7281.7311 | AD66: 1452.4144 | AE66: 5829.3168 | AF66: 108136.9 | AG66: 104870.21 | AH66: 0 | AI66: 0 | AJ66: - | AK66: ## 104 | AL66: 4085861 | AM66: 10188.23 | AN66: 1540.6595 | AO66: 8647.5705 | AP66: 118077.41 | AQ66: 114607.8 | AR66: 0 | AS66: 0 | AT66: - | AU66: ## 109 | AV66: 4342221 | AW66: 8880.8008 | AX66: 1846.6492 | AY66: 7034.1516 | AZ66: 125750.77 | BA66: 123742.52 | BB66: 0 | BC66: 0 | BD66: - | BE66: 114 | BF66: 4612682 | BG66: 7070.6395 | BH66: 1654.1927 | BI66: 5416.4468 | BJ66: 131767.03 | BK66: 130681.26 | BL66: 0 | BM66: 0 | BN66: - | BO66: # 119 | BP66: 5435446 | BQ66: 14691.2 | BR66: 2295.237 | BS66: 12395.963 | BT66: 150121.81 | BU66: 143230.54 | BV66: 0 | BW66: 0 | BX66: - | BY66: ## 120 | BZ66: 6563721 | CA66: 14053.691 | CB66: 6283.0049 | CC66: 7770.6865 | CD66: 161978.18 | CE66: 162168.21 | CF66: 0 | CG66: 0 | CH66: - | CI66: ## 121 | CJ66: 7116095 | CK66: 7641.5343 | CL66: 2559.727 | CM66: 5081.8073 | CN66: 170138.67 | CO66: 168529.18 | CP66: 0 | CQ66: 0 | CR66: - | CS66: ## 127 | CT66: 8432466 | CU66: 15431.295 | CV66: 5181.0288 | CW66: 10250.266 | CX66: 188244.46 | CY66: 183180.67 | CZ66: 0 | DA66: 0 | DB66: - | DC66: ## 132 | DD66: 10633970 | DE66: 23858.545 | DF66: 12607.941 | DG66: 11250.604 | DH66: 216823.63 | DI66: 207522.03 | DJ66: 0 | DK66: 0 | DL66: - | DM66: 0 | DN66: 0 | DO66: - | DP66: =(DE66-CU66)/CU66 | DQ66: =(DG66-CW66)/CW66 | DR66: =(DI66-CY66)/CY66 | DS66: ## 136 | DT66: 11519870 | DU66: 12564.522 | DV66: 8995.7147 | DW66: 3568.8069 | DX66: 214642.07 | DY66: 212743.8 | DZ66: 0 | EA66: 0 | EB66: - | EC66: 0 | ED66: 0 | EE66: - | EI66: - | EJ66: ## 145 | EK66: 12096585 | EL66: 10358.334 | EM66: 6622.0404 | EN66: 3736.2931 | EO66: 202965.08 | EP66: 212377.24 | EQ66: 0 | ER66: 0 | ES66: - | ET66: 0 | EU66: 0 | EV66: -
A67: ** Data in respect Fund of Funds Domestic is shown for information only. The same is included in the respective underlying schemes.
A68: ## Include NFO - Mirae Asset BSE Select IPO ETF Fund of Fund and Mirae Asset BSE 200 Equal Weight ETF Fund of Fund. There was a Fundamental Attribute Change carried out in one MF scheme, pursuant to which, the scheme which was earlier categorised as fund of fund overseas is now classified as fund of fund domestic.

Sheet Analytics
K1: Data Source (auto-updates)
K2: Source sheet: | L2: AMFI-Mar'25 to Mar'26
K3: Latest month: | L3: =SUBSTITUTE($D$4,"AUM ","")
A4: Category | B4: {="AUM "&INDEX('AMFI-Mar''25 to Mar''26'!$A$2:$AAG$2,1,LARGE(_xlfn._xlws.FILTER(COLUMN('AMFI-Mar''25 to Mar''26'!$A$3:$AAG$3),ISNUMBER(SEARCH("Net Assets Under Management as on",'AMFI-Mar''25 to Mar''26'!$A$3:$AAG$3))),2)-5)} | C4: {="AUM Share "&INDEX('AMFI-Mar''25 to Mar''26'!$A$2:$AAG$2,1,LARGE(_xlfn._xlws.FILTER(COLUMN('AMFI-Mar''25 to Mar''26'!$A$3:$AAG$3),ISNUMBER(SEARCH("Net Assets Under Management as on",'AMFI-Mar''25 to Mar''26'!$A$3:$AAG$3))),2)-5)} | D4: {="AUM "&INDEX('AMFI-Mar''25 to Mar''26'!$A$2:$AAG$2,1,MAX(_xlfn._xlws.FILTER(COLUMN('AMFI-Mar''25 to Mar''26'!$A$3:$AAG$3),ISNUMBER(SEARCH("Net Assets Under Management as on",'AMFI-Mar''25 to Mar''26'!$A$3:$AAG$3))))-5)} | E4: {="AUM Share "&INDEX('AMFI-Mar''25 to Mar''26'!$A$2:$AAG$2,1,MAX(_xlfn._xlws.FILTER(COLUMN('AMFI-Mar''25 to Mar''26'!$A$3:$AAG$3),ISNUMBER(SEARCH("Net Assets Under Management as on",'AMFI-Mar''25 to Mar''26'!$A$3:$AAG$3))))-5)} | F4: Growth % | G4: YTD Sales | H4: YTD Redemption | I4: YTD Net Flow | K4: Previous month: | L4: =SUBSTITUTE($B$4,"AUM ","")
A5: Active Equity (incl Hybrid) | B5: {=INDEX('AMFI-Mar''25 to Mar''26'!$1:$1048576,MATCH("Total for "&$A5,'AMFI-Mar''25 to Mar''26'!$A:$A,0),LARGE(_xlfn._xlws.FILTER(COLUMN('AMFI-Mar''25 to Mar''26'!$A$3:$AAG$3),ISNUMBER(SEARCH("Net Assets Under Management as on",'AMFI-Mar''25 to Mar''26'!$A$3:$AAG$3))),2))} | C5: =IFERROR(B5/$B$11,"") | D5: {=INDEX('AMFI-Mar''25 to Mar''26'!$1:$1048576,MATCH("Total for "&$A5,'AMFI-Mar''25 to Mar''26'!$A:$A,0),MAX(_xlfn._xlws.FILTER(COLUMN('AMFI-Mar''25 to Mar''26'!$A$3:$AAG$3),ISNUMBER(SEARCH("Net Assets Under Management as on",'AMFI-Mar''25 to Mar''26'!$A$3:$AAG$3)))))} | E5: =IFERROR(D5/$D$11,"") | F5: =IFERROR(D5/B5-1,"") | G5: {=INDEX('AMFI-Mar''25 to Mar''26'!$1:$1048576,MATCH("Total for "&$A5,'AMFI-Mar''25 to Mar''26'!$A:$A,0),MAX(_xlfn._xlws.FILTER(COLUMN('AMFI-Mar''25 to Mar''26'!$A$3:$AAG$3),ISNUMBER(SEARCH("Funds Mobilized",'AMFI-Mar''25 to Mar''26'!$A$3:$AAG$3))*ISNUMBER(SEARCH(" to ",'AMFI-Mar''25 to Mar''26'!$A$2:$AAG$2)))))} | H5: =G5-I5 | I5: {=INDEX('AMFI-Mar''25 to Mar''26'!$1:$1048576,MATCH("Total for "&$A5,'AMFI-Mar''25 to Mar''26'!$A:$A,0),MAX(_xlfn._xlws.FILTER(COLUMN('AMFI-Mar''25 to Mar''26'!$A$3:$AAG$3),ISNUMBER(SEARCH("Funds Mobilized",'AMFI-Mar''25 to Mar''26'!$A$3:$AAG$3))*ISNUMBER(SEARCH(" to ",'AMFI-Mar''25 to Mar''26'!$A$2:$AAG$2))))+1)} | K5: Categories: | L5: Rows 5–10
A6: Arb/ESF | B6: {=INDEX('AMFI-Mar''25 to Mar''26'!$1:$1048576,MATCH("Total for "&$A6,'AMFI-Mar''25 to Mar''26'!$A:$A,0),LARGE(_xlfn._xlws.FILTER(COLUMN('AMFI-Mar''25 to Mar''26'!$A$3:$AAG$3),ISNUMBER(SEARCH("Net Assets Under Management as on",'AMFI-Mar''25 to Mar''26'!$A$3:$AAG$3))),2))} | C6: =IFERROR(B6/$B$11,"") | D6: {=INDEX('AMFI-Mar''25 to Mar''26'!$1:$1048576,MATCH("Total for "&$A6,'AMFI-Mar''25 to Mar''26'!$A:$A,0),MAX(_xlfn._xlws.FILTER(COLUMN('AMFI-Mar''25 to Mar''26'!$A$3:$AAG$3),ISNUMBER(SEARCH("Net Assets Under Management as on",'AMFI-Mar''25 to Mar''26'!$A$3:$AAG$3)))))} | E6: =IFERROR(D6/$D$11,"") | F6: =IFERROR(D6/B6-1,"") | G6: {=INDEX('AMFI-Mar''25 to Mar''26'!$1:$1048576,MATCH("Total for "&$A6,'AMFI-Mar''25 to Mar''26'!$A:$A,0),MAX(_xlfn._xlws.FILTER(COLUMN('AMFI-Mar''25 to Mar''26'!$A$3:$AAG$3),ISNUMBER(SEARCH("Funds Mobilized",'AMFI-Mar''25 to Mar''26'!$A$3:$AAG$3))*ISNUMBER(SEARCH(" to ",'AMFI-Mar''25 to Mar''26'!$A$2:$AAG$2)))))} | H6: =G6-I6 | I6: {=INDEX('AMFI-Mar''25 to Mar''26'!$1:$1048576,MATCH("Total for "&$A6,'AMFI-Mar''25 to Mar''26'!$A:$A,0),MAX(_xlfn._xlws.FILTER(COLUMN('AMFI-Mar''25 to Mar''26'!$A$3:$AAG$3),ISNUMBER(SEARCH("Funds Mobilized",'AMFI-Mar''25 to Mar''26'!$A$3:$AAG$3))*ISNUMBER(SEARCH(" to ",'AMFI-Mar''25 to Mar''26'!$A$2:$AAG$2))))+1)} | K6: Months tracked: | L6: =COUNT($Q$28:$Q$40)
A7: Active Debt (incl Hybrid) | B7: {=INDEX('AMFI-Mar''25 to Mar''26'!$1:$1048576,MATCH("Total for "&$A7,'AMFI-Mar''25 to Mar''26'!$A:$A,0),LARGE(_xlfn._xlws.FILTER(COLUMN('AMFI-Mar''25 to Mar''26'!$A$3:$AAG$3),ISNUMBER(SEARCH("Net Assets Under Management as on",'AMFI-Mar''25 to Mar''26'!$A$3:$AAG$3))),2))} | C7: =IFERROR(B7/$B$11,"") | D7: {=INDEX('AMFI-Mar''25 to Mar''26'!$1:$1048576,MATCH("Total for "&$A7,'AMFI-Mar''25 to Mar''26'!$A:$A,0),MAX(_xlfn._xlws.FILTER(COLUMN('AMFI-Mar''25 to Mar''26'!$A$3:$AAG$3),ISNUMBER(SEARCH("Net Assets Under Management as on",'AMFI-Mar''25 to Mar''26'!$A$3:$AAG$3)))))} | E7: =IFERROR(D7/$D$11,"") | F7: =IFERROR(D7/B7-1,"") | G7: {=INDEX('AMFI-Mar''25 to Mar''26'!$1:$1048576,MATCH("Total for "&$A7,'AMFI-Mar''25 to Mar''26'!$A:$A,0),MAX(_xlfn._xlws.FILTER(COLUMN('AMFI-Mar''25 to Mar''26'!$A$3:$AAG$3),ISNUMBER(SEARCH("Funds Mobilized",'AMFI-Mar''25 to Mar''26'!$A$3:$AAG$3))*ISNUMBER(SEARCH(" to ",'AMFI-Mar''25 to Mar''26'!$A$2:$AAG$2)))))} | H7: =G7-I7 | I7: {=INDEX('AMFI-Mar''25 to Mar''26'!$1:$1048576,MATCH("Total for "&$A7,'AMFI-Mar''25 to Mar''26'!$A:$A,0),MAX(_xlfn._xlws.FILTER(COLUMN('AMFI-Mar''25 to Mar''26'!$A$3:$AAG$3),ISNUMBER(SEARCH("Funds Mobilized",'AMFI-Mar''25 to Mar''26'!$A$3:$AAG$3))*ISNUMBER(SEARCH(" to ",'AMFI-Mar''25 to Mar''26'!$A$2:$AAG$2))))+1)}
A8: Cash | B8: {=INDEX('AMFI-Mar''25 to Mar''26'!$1:$1048576,MATCH("Total for "&$A8,'AMFI-Mar''25 to Mar''26'!$A:$A,0),LARGE(_xlfn._xlws.FILTER(COLUMN('AMFI-Mar''25 to Mar''26'!$A$3:$AAG$3),ISNUMBER(SEARCH("Net Assets Under Management as on",'AMFI-Mar''25 to Mar''26'!$A$3:$AAG$3))),2))} | C8: =IFERROR(B8/$B$11,"") | D8: {=INDEX('AMFI-Mar''25 to Mar''26'!$1:$1048576,MATCH("Total for "&$A8,'AMFI-Mar''25 to Mar''26'!$A:$A,0),MAX(_xlfn._xlws.FILTER(COLUMN('AMFI-Mar''25 to Mar''26'!$A$3:$AAG$3),ISNUMBER(SEARCH("Net Assets Under Management as on",'AMFI-Mar''25 to Mar''26'!$A$3:$AAG$3)))))} | E8: =IFERROR(D8/$D$11,"") | F8: =IFERROR(D8/B8-1,"") | G8: {=INDEX('AMFI-Mar''25 to Mar''26'!$1:$1048576,MATCH("Total for "&$A8,'AMFI-Mar''25 to Mar''26'!$A:$A,0),MAX(_xlfn._xlws.FILTER(COLUMN('AMFI-Mar''25 to Mar''26'!$A$3:$AAG$3),ISNUMBER(SEARCH("Funds Mobilized",'AMFI-Mar''25 to Mar''26'!$A$3:$AAG$3))*ISNUMBER(SEARCH(" to ",'AMFI-Mar''25 to Mar''26'!$A$2:$AAG$2)))))} | H8: =G8-I8 | I8: {=INDEX('AMFI-Mar''25 to Mar''26'!$1:$1048576,MATCH("Total for "&$A8,'AMFI-Mar''25 to Mar''26'!$A:$A,0),MAX(_xlfn._xlws.FILTER(COLUMN('AMFI-Mar''25 to Mar''26'!$A$3:$AAG$3),ISNUMBER(SEARCH("Funds Mobilized",'AMFI-Mar''25 to Mar''26'!$A$3:$AAG$3))*ISNUMBER(SEARCH(" to ",'AMFI-Mar''25 to Mar''26'!$A$2:$AAG$2))))+1)}
A9: Passive-E/D | B9: {=INDEX('AMFI-Mar''25 to Mar''26'!$1:$1048576,MATCH("Total for "&$A9,'AMFI-Mar''25 to Mar''26'!$A:$A,0),LARGE(_xlfn._xlws.FILTER(COLUMN('AMFI-Mar''25 to Mar''26'!$A$3:$AAG$3),ISNUMBER(SEARCH("Net Assets Under Management as on",'AMFI-Mar''25 to Mar''26'!$A$3:$AAG$3))),2))} | C9: =IFERROR(B9/$B$11,"") | D9: {=INDEX('AMFI-Mar''25 to Mar''26'!$1:$1048576,MATCH("Total for "&$A9,'AMFI-Mar''25 to Mar''26'!$A:$A,0),MAX(_xlfn._xlws.FILTER(COLUMN('AMFI-Mar''25 to Mar''26'!$A$3:$AAG$3),ISNUMBER(SEARCH("Net Assets Under Management as on",'AMFI-Mar''25 to Mar''26'!$A$3:$AAG$3)))))} | E9: =IFERROR(D9/$D$11,"") | F9: =IFERROR(D9/B9-1,"") | G9: {=INDEX('AMFI-Mar''25 to Mar''26'!$1:$1048576,MATCH("Total for "&$A9,'AMFI-Mar''25 to Mar''26'!$A:$A,0),MAX(_xlfn._xlws.FILTER(COLUMN('AMFI-Mar''25 to Mar''26'!$A$3:$AAG$3),ISNUMBER(SEARCH("Funds Mobilized",'AMFI-Mar''25 to Mar''26'!$A$3:$AAG$3))*ISNUMBER(SEARCH(" to ",'AMFI-Mar''25 to Mar''26'!$A$2:$AAG$2)))))} | H9: =G9-I9 | I9: {=INDEX('AMFI-Mar''25 to Mar''26'!$1:$1048576,MATCH("Total for "&$A9,'AMFI-Mar''25 to Mar''26'!$A:$A,0),MAX(_xlfn._xlws.FILTER(COLUMN('AMFI-Mar''25 to Mar''26'!$A$3:$AAG$3),ISNUMBER(SEARCH("Funds Mobilized",'AMFI-Mar''25 to Mar''26'!$A$3:$AAG$3))*ISNUMBER(SEARCH(" to ",'AMFI-Mar''25 to Mar''26'!$A$2:$AAG$2))))+1)}
A10: Interval Schemes | B10: {=INDEX('AMFI-Mar''25 to Mar''26'!$1:$1048576,MATCH("Total for "&$A10,'AMFI-Mar''25 to Mar''26'!$A:$A,0),LARGE(_xlfn._xlws.FILTER(COLUMN('AMFI-Mar''25 to Mar''26'!$A$3:$AAG$3),ISNUMBER(SEARCH("Net Assets Under Management as on",'AMFI-Mar''25 to Mar''26'!$A$3:$AAG$3))),2))} | C10: =IFERROR(B10/$B$11,"") | D10: {=INDEX('AMFI-Mar''25 to Mar''26'!$1:$1048576,MATCH("Total for "&$A10,'AMFI-Mar''25 to Mar''26'!$A:$A,0),MAX(_xlfn._xlws.FILTER(COLUMN('AMFI-Mar''25 to Mar''26'!$A$3:$AAG$3),ISNUMBER(SEARCH("Net Assets Under Management as on",'AMFI-Mar''25 to Mar''26'!$A$3:$AAG$3)))))} | E10: =IFERROR(D10/$D$11,"") | F10: =IFERROR(D10/B10-1,"") | G10: {=INDEX('AMFI-Mar''25 to Mar''26'!$1:$1048576,MATCH("Total for "&$A10,'AMFI-Mar''25 to Mar''26'!$A:$A,0),MAX(_xlfn._xlws.FILTER(COLUMN('AMFI-Mar''25 to Mar''26'!$A$3:$AAG$3),ISNUMBER(SEARCH("Funds Mobilized",'AMFI-Mar''25 to Mar''26'!$A$3:$AAG$3))*ISNUMBER(SEARCH(" to ",'AMFI-Mar''25 to Mar''26'!$A$2:$AAG$2)))))} | H10: =G10-I10 | I10: {=INDEX('AMFI-Mar''25 to Mar''26'!$1:$1048576,MATCH("Total for "&$A10,'AMFI-Mar''25 to Mar''26'!$A:$A,0),MAX(_xlfn._xlws.FILTER(COLUMN('AMFI-Mar''25 to Mar''26'!$A$3:$AAG$3),ISNUMBER(SEARCH("Funds Mobilized",'AMFI-Mar''25 to Mar''26'!$A$3:$AAG$3))*ISNUMBER(SEARCH(" to ",'AMFI-Mar''25 to Mar''26'!$A$2:$AAG$2))))+1)}
A11: Grand Total | B11: =SUM(B5:B10) | C11: =SUM(C5:C10) | D11: =SUM(D5:D10) | E11: =SUM(E5:E10) | F11: =IFERROR(D11/B11-1,"") | G11: =SUM(G5:G10) | H11: =SUM(H5:H10) | I11: =SUM(I5:I10)
A14: Summary
A15: {=_xlfn.LET(_xlpm.src,'AMFI-Mar''25 to Mar''26'!$A:$AAG,_xlpm.h,'AMFI-Mar''25 to Mar''26'!$A$3:$AAG$3,_xlpm.m,'AMFI-Mar''25 to Mar''26'!$A$2:$AAG$2,_xlpm.c,COLUMN('AMFI-Mar''25 to Mar''26'!$A$3:$AAG$3),_xlpm.aCols,_xlfn._xlws.FILTER(_xlpm.c,ISNUMBER(SEARCH("Net Assets Under Management as on",_xlpm.h))),_xlpm.lc,LARGE(_xlpm.aCols,1),_xlpm.pc,LARGE(_xlpm.aCols,2),_xlpm.r,MATCH("Grand Total",'AMFI-Mar''25 to Mar''26'!$A:$A,0),_xlpm.aum,INDEX(_xlpm.src,_xlpm.r,_xlpm.lc),_xlpm.paum,INDEX(_xlpm.src,_xlpm.r,_xlpm.pc),_xlpm.net,INDEX(_xlpm.src,_xlpm.r,_xlpm.lc-1),_xlpm.pnet,INDEX(_xlpm.src,_xlpm.r,_xlpm.pc-1),_xlpm.mon,INDEX(_xlpm.m,1,_xlpm.lc-5),_xlpm.pmon,INDEX(_xlpm.m,1,_xlpm.pc-5),"Industry Monthly net flow was Rs "&TEXT(_xlpm.net,"#,##0")&" Cr in "&_xlpm.mon&" vs Rs "&TEXT(_xlpm.pnet,"#,##0")&" Cr in "&_xlpm.pmon&", with AUM at Rs "&TEXT(_xlpm.aum,"#,##0")&" Cr ("&TEXT(_xlpm.aum/_xlpm.paum-1,"+0.0%;-0.0%;0.0%")&" MoM).")}
A16: {=_xlfn.LET(_xlpm.cats,$A$5:$A$10,_xlpm.aums,$D$5:$D$10,_xlpm.shares,$E$5:$E$10,_xlpm.nets,$I$5:$I$10,_xlpm.topAUM,MAX(_xlpm.aums),_xlpm.topCat,_xlfn.XLOOKUP(_xlpm.topAUM,_xlpm.aums,_xlpm.cats),_xlpm.topShare,_xlfn.XLOOKUP(_xlpm.topAUM,_xlpm.aums,_xlpm.shares),_xlpm.topNet,_xlfn.XLOOKUP(_xlpm.topAUM,_xlpm.aums,_xlpm.nets),"AUM mix remains led by "&_xlpm.topCat&" at "&TEXT(_xlpm.topShare,"0.0%")&" share, with YTD net flow of Rs "&TEXT(_xlpm.topNet,"#,##0")&" Cr.")}
A17: {=_xlfn.LET(_xlpm.cats,$A$5:$A$10,_xlpm.nets,$I$5:$I$10,_xlpm.leader,_xlfn.XLOOKUP(MAX(_xlpm.nets),_xlpm.nets,_xlpm.cats),_xlpm.nz,_xlfn._xlws.FILTER(_xlpm.nets,_xlpm.nets<>0),_xlpm.lowVal,MIN(_xlpm.nz),_xlpm.lowCat,_xlfn.XLOOKUP(_xlpm.lowVal,_xlpm.nets,_xlpm.cats),"YTD category flows are strongest in "&_xlpm.leader&" at Rs "&TEXT(MAX(_xlpm.nets),"#,##0")&" Cr, while "&_xlpm.lowCat&" is the lowest non-zero flow at Rs "&TEXT(_xlpm.lowVal,"#,##0")&" Cr.")}
A18: {=_xlfn.LET(_xlpm.src,'AMFI-Mar''25 to Mar''26'!$A:$AAG,_xlpm.h,'AMFI-Mar''25 to Mar''26'!$A$3:$AAG$3,_xlpm.m,'AMFI-Mar''25 to Mar''26'!$A$2:$AAG$2,_xlpm.c,COLUMN('AMFI-Mar''25 to Mar''26'!$A$3:$AAG$3),_xlpm.aCols,_xlfn._xlws.FILTER(_xlpm.c,ISNUMBER(SEARCH("Net Assets Under Management as on",_xlpm.h))),_xlpm.lc,LARGE(_xlpm.aCols,1),_xlpm.pc,LARGE(_xlpm.aCols,2),_xlpm.r,MATCH("Grand Total",'AMFI-Mar''25 to Mar''26'!$A:$A,0),_xlpm.sales,INDEX(_xlpm.src,_xlpm.r,_xlpm.lc-3),_xlpm.red,INDEX(_xlpm.src,_xlpm.r,_xlpm.lc-2),_xlpm.net,INDEX(_xlpm.src,_xlpm.r,_xlpm.lc-1),_xlpm.pnet,INDEX(_xlpm.src,_xlpm.r,_xlpm.pc-1),_xlpm.mon,INDEX(_xlpm.m,1,_xlpm.lc-5),_xlpm.pmon,INDEX(_xlpm.m,1,_xlpm.pc-5),"Latest-month activity: sales were Rs "&TEXT(_xlpm.sales,"#,##0")&" Cr and redemptions Rs "&TEXT(_xlpm.red,"#,##0")&" Cr in "&_xlpm.mon&", resulting in net flow of Rs "&TEXT(_xlpm.net,"#,##0")&" Cr vs Rs "&TEXT(_xlpm.pnet,"#,##0")&" Cr in "&_xlpm.pmon&".")}
A19: {=_xlfn.LET(_xlpm.cats,$A$5:$A$10,_xlpm.g,$F$5:$F$10,_xlpm.up,MAX(_xlpm.g),_xlpm.upCat,_xlfn.XLOOKUP(_xlpm.up,_xlpm.g,_xlpm.cats),_xlpm.dn,MIN(_xlpm.g),_xlpm.dnCat,_xlfn.XLOOKUP(_xlpm.dn,_xlpm.g,_xlpm.cats),"Month-on-month, "&_xlpm.upCat&" held up best ("&TEXT(_xlpm.up,"+0.0%;-0.0%")&"), while "&_xlpm.dnCat&" declined most ("&TEXT(_xlpm.dn,"+0.0%;-0.0%")&").")}
A20: ="YTD industry sales total Rs "&TEXT($G$11,"#,##0")&" Cr vs redemptions of Rs "&TEXT($H$11,"#,##0")&" Cr, leaving net flow of Rs "&TEXT($I$11,"#,##0")&" Cr ("&TEXT($I$11/$D$11,"0.0%")&" of latest AUM)."
A21: {=_xlfn.LET(_xlpm.src,'AMFI-Mar''25 to Mar''26'!$A:$AAG,_xlpm.h,'AMFI-Mar''25 to Mar''26'!$A$3:$AAG$3,_xlpm.m,'AMFI-Mar''25 to Mar''26'!$A$2:$AAG$2,_xlpm.c,COLUMN('AMFI-Mar''25 to Mar''26'!$A$3:$AAG$3),_xlpm.a,_xlfn._xlws.FILTER(_xlpm.c,ISNUMBER(SEARCH("Net Assets Under Management as on",_xlpm.h))),_xlpm.lc,LARGE(_xlpm.a,1),_xlpm.pc,LARGE(_xlpm.a,2),_xlpm.r,MATCH("Total for Active Equity (incl Hybrid)",'AMFI-Mar''25 to Mar''26'!$A:$A,0),_xlpm.cur,INDEX(_xlpm.src,_xlpm.r,_xlpm.lc-1),_xlpm.prev,INDEX(_xlpm.src,_xlpm.r,_xlpm.pc-1),_xlpm.mon,INDEX(_xlpm.m,1,_xlpm.lc-5),_xlpm.pmon,INDEX(_xlpm.m,1,_xlpm.pc-5),"Active Equity inflows "&IF(_xlpm.cur<_xlpm.prev,"moderated","rose")&" to Rs "&TEXT(_xlpm.cur,"#,##0")&" Cr in "&_xlpm.mon&" from Rs "&TEXT(_xlpm.prev,"#,##0")&" Cr in "&_xlpm.pmon&", "&IF(_xlpm.cur>0,"but remained positive","turning negative")&".")}
A22: {=_xlfn.LET(_xlpm.cats,$A$5:$A$10,_xlpm.nets,$I$5:$I$10,_xlpm.nOut,SUMPRODUCT(--(_xlpm.nets<0)),_xlpm.worst,MIN(_xlpm.nets),_xlpm.worstCat,_xlfn.XLOOKUP(_xlpm.worst,_xlpm.nets,_xlpm.cats),_xlpm.topRed,MAX($H$5:$H$10),_xlpm.topRedCat,_xlfn.XLOOKUP(_xlpm.topRed,$H$5:$H$10,_xlpm.cats),IF(_xlpm.nOut=0,"All six categories recorded positive YTD net flows; "&_xlpm.topRedCat&" saw the largest redemptions at Rs "&TEXT(_xlpm.topRed,"#,##0")&" Cr.","Of six categories, "&_xlpm.nOut&" recorded YTD net outflows, weakest "&_xlpm.worstCat&" at Rs "&TEXT(_xlpm.worst,"#,##0;(#,##0)")&" Cr."))}
A26: Monthly Trend — TOTAL (Rs Cr) | I26: Monthly Trend — Active Equity (incl Hybrid) (Rs Cr) | P26: AUM Trend Chart Source
A27: Month | B27: AUM | C27: Avg AUM | D27: Gross Sales | E27: Redemption | F27: Net Sales | I27: Month | J27: AUM | K27: Avg AUM | L27: Gross Sales | M27: Redemption | N27: Net Sales | P27: Month | Q27: AUM
A28: {=_xlfn.LET(_xlpm.m,'AMFI-Mar''25 to Mar''26'!$A$2:$AAG$2,_xlpm.h,'AMFI-Mar''25 to Mar''26'!$A$3:$AAG$3,_xlpm.cond,(_xlpm.m<>"")*(_xlpm.m<>"-")*ISNUMBER(SEARCH("'",_xlpm.m))*ISERROR(SEARCH(" to ",_xlpm.m)),_xlpm.labels,_xlfn._xlws.FILTER(_xlpm.m,_xlpm.cond),_xlpm.hdrs,_xlfn._xlws.FILTER(_xlpm.h,_xlpm.cond),_xlpm.idx,ROW()-ROW($A$28)+1,_xlpm.n,COLUMNS(_xlpm.labels),_xlpm.x,IF(_xlpm.idx<=MIN(13,_xlpm.n),INDEX(_xlpm.labels,1,_xlpm.idx+MAX(0,_xlpm.n-13)),""),_xlpm.hx,IF(_xlpm.idx<=MIN(13,_xlpm.n),INDEX(_xlpm.hdrs,1,_xlpm.idx+MAX(0,_xlpm.n-13)),""),IF(_xlpm.x="","",IF(ISNUMBER(SEARCH("No. of Schemes as on",_xlpm.hx)),LOOKUP(2,1/ISNUMBER(SEARCH({"January","February","March","April","May","June","July","August","September","October","November","December"},_xlpm.hx)),{"Jan","Feb","Mar","Apr","May","Jun","Jul","Aug","Sep","Oct","Nov","Dec"})&"'"&RIGHT(MID(_xlpm.hx,FIND(", ",_xlpm.hx)+2,4),2),_xlpm.x)))} | B28: {=IF($A28="","",IFERROR(_xlfn.LET(_xlpm.lbl,$A28,_xlpm.mm,LEFT(_xlpm.lbl,3),_xlpm.yy,"20"&RIGHT(_xlpm.lbl,2),_xlpm.full,CHOOSE(MATCH(_xlpm.mm,{"Jan";"Feb";"Mar";"Apr";"May";"Jun";"Jul";"Aug";"Sep";"Oct";"Nov";"Dec"},0),"January","February","March","April","May","June","July","August","September","October","November","December")&" ",_xlpm.h,'AMFI-Mar''25 to Mar''26'!$A$3:$AAG$3,_xlpm.c,COLUMN('AMFI-Mar''25 to Mar''26'!$A$3:$AAG$3),_xlpm.hit,_xlfn._xlws.FILTER(_xlpm.c,ISNUMBER(SEARCH("Net Assets Under Management as on",_xlpm.h))*ISNUMBER(SEARCH(_xlpm.full&"*"&_xlpm.yy,_xlpm.h))),_xlpm.col,IFERROR(INDEX(_xlpm.hit,1),0),_xlpm.colf,IF(_xlpm.col=0,IFERROR(MATCH(_xlpm.lbl,'AMFI-Mar''25 to Mar''26'!$A$2:$AAG$2,0)+5,0),_xlpm.col),IF(_xlpm.colf=0,NA(),INDEX('AMFI-Mar''25 to Mar''26'!$1:$1048576,MATCH("Grand Total",'AMFI-Mar''25 to Mar''26'!$A:$A,0),_xlpm.colf))),""))} | C28: {=IF($A28="","",IFERROR(_xlfn.LET(_xlpm.lbl,$A28,_xlpm.mm,LEFT(_xlpm.lbl,3),_xlpm.yy,"20"&RIGHT(_xlpm.lbl,2),_xlpm.full,CHOOSE(MATCH(_xlpm.mm,{"Jan";"Feb";"Mar";"Apr";"May";"Jun";"Jul";"Aug";"Sep";"Oct";"Nov";"Dec"},0),"January","February","March","April","May","June","July","August","September","October","November","December")&" ",_xlpm.h,'AMFI-Mar''25 to Mar''26'!$A$3:$AAG$3,_xlpm.c,COLUMN('AMFI-Mar''25 to Mar''26'!$A$3:$AAG$3),_xlpm.hit,_xlfn._xlws.FILTER(_xlpm.c,ISNUMBER(SEARCH("Net Assets Under Management as on",_xlpm.h))*ISNUMBER(SEARCH(_xlpm.full&"*"&_xlpm.yy,_xlpm.h))),_xlpm.col,IFERROR(INDEX(_xlpm.hit,1),0),_xlpm.colf,IF(_xlpm.col=0,IFERROR(MATCH(_xlpm.lbl,'AMFI-Mar''25 to Mar''26'!$A$2:$AAG$2,0)+5,0),_xlpm.col),IF(_xlpm.colf=0,NA(),INDEX('AMFI-Mar''25 to Mar''26'!$1:$1048576,MATCH("Grand Total",'AMFI-Mar''25 to Mar''26'!$A:$A,0),_xlpm.colf+1))),""))} | D28: {=IF($A28="","",IFERROR(_xlfn.LET(_xlpm.lbl,$A28,_xlpm.mm,LEFT(_xlpm.lbl,3),_xlpm.yy,"20"&RIGHT(_xlpm.lbl,2),_xlpm.full,CHOOSE(MATCH(_xlpm.mm,{"Jan";"Feb";"Mar";"Apr";"May";"Jun";"Jul";"Aug";"Sep";"Oct";"Nov";"Dec"},0),"January","February","March","April","May","June","July","August","September","October","November","December")&" "&_xlpm.yy,_xlpm.h,'AMFI-Mar''25 to Mar''26'!$A$3:$AAG$3,_xlpm.c,COLUMN('AMFI-Mar''25 to Mar''26'!$A$3:$AAG$3),_xlpm.hit,_xlfn._xlws.FILTER(_xlpm.c,ISNUMBER(SEARCH("Funds Mobilized for the month of "&_xlpm.full,_xlpm.h))),_xlpm.col,IFERROR(INDEX(_xlpm.hit,1),0),IF(_xlpm.col=0,"",INDEX('AMFI-Mar''25 to Mar''26'!$1:$1048576,MATCH("Grand Total",'AMFI-Mar''25 to Mar''26'!$A:$A,0),_xlpm.col))),""))} | E28: {=IF($A28="","",IFERROR(_xlfn.LET(_xlpm.lbl,$A28,_xlpm.mm,LEFT(_xlpm.lbl,3),_xlpm.yy,"20"&RIGHT(_xlpm.lbl,2),_xlpm.full,CHOOSE(MATCH(_xlpm.mm,{"Jan";"Feb";"Mar";"Apr";"May";"Jun";"Jul";"Aug";"Sep";"Oct";"Nov";"Dec"},0),"January","February","March","April","May","June","July","August","September","October","November","December")&" "&_xlpm.yy,_xlpm.h,'AMFI-Mar''25 to Mar''26'!$A$3:$AAG$3,_xlpm.c,COLUMN('AMFI-Mar''25 to Mar''26'!$A$3:$AAG$3),_xlpm.hit,_xlfn._xlws.FILTER(_xlpm.c,ISNUMBER(SEARCH("Repurchase/Redemption for the month of "&_xlpm.full,_xlpm.h))+ISNUMBER(SEARCH("Redemption for the month of "&_xlpm.full,_xlpm.h))),_xlpm.col,IFERROR(INDEX(_xlpm.hit,1),0),IF(_xlpm.col=0,"",INDEX('AMFI-Mar''25 to Mar''26'!$1:$1048576,MATCH("Grand Total",'AMFI-Mar''25 to Mar''26'!$A:$A,0),_xlpm.col))),""))} | F28: =IF($A28="","",IFERROR(D28-E28,"")) | I28: =$A28 | J28: {=IF($A28="","",IFERROR(_xlfn.LET(_xlpm.lbl,$A28,_xlpm.mm,LEFT(_xlpm.lbl,3),_xlpm.yy,"20"&RIGHT(_xlpm.lbl,2),_xlpm.full,CHOOSE(MATCH(_xlpm.mm,{"Jan";"Feb";"Mar";"Apr";"May";"Jun";"Jul";"Aug";"Sep";"Oct";"Nov";"Dec"},0),"January","February","March","April","May","June","July","August","September","October","November","December")&" ",_xlpm.h,'AMFI-Mar''25 to Mar''26'!$A$3:$ZS$3,_xlpm.c,COLUMN('AMFI-Mar''25 to Mar''26'!$A$3:$ZS$3),_xlpm.hit,_xlfn._xlws.FILTER(_xlpm.c,ISNUMBER(SEARCH("Net Assets Under Management as on",_xlpm.h))*ISNUMBER(SEARCH(_xlpm.full&"*"&_xlpm.yy,_xlpm.h))),_xlpm.col,IFERROR(INDEX(_xlpm.hit,1),0),IF(_xlpm.col=0,"",INDEX('AMFI-Mar''25 to Mar''26'!$1:$1048576,MATCH("Total for Active Equity (incl Hybrid)",'AMFI-Mar''25 to Mar''26'!$A:$A,0),_xlpm.col))),""))} | K28: {=IF($A28="","",IFERROR(_xlfn.LET(_xlpm.lbl,$A28,_xlpm.mm,LEFT(_xlpm.lbl,3),_xlpm.yy,"20"&RIGHT(_xlpm.lbl,2),_xlpm.full,CHOOSE(MATCH(_xlpm.mm,{"Jan";"Feb";"Mar";"Apr";"May";"Jun";"Jul";"Aug";"Sep";"Oct";"Nov";"Dec"},0),"January","February","March","April","May","June","July","August","September","October","November","December")&" ",_xlpm.h,'AMFI-Mar''25 to Mar''26'!$A$3:$ZS$3,_xlpm.c,COLUMN('AMFI-Mar''25 to Mar''26'!$A$3:$ZS$3),_xlpm.hit,_xlfn._xlws.FILTER(_xlpm.c,ISNUMBER(SEARCH("Net Assets Under Management as on",_xlpm.h))*ISNUMBER(SEARCH(_xlpm.full&"*"&_xlpm.yy,_xlpm.h))),_xlpm.col,IFERROR(INDEX(_xlpm.hit,1),0),IF(_xlpm.col=0,"",INDEX('AMFI-Mar''25 to Mar''26'!$1:$1048576,MATCH("Total for Active Equity (incl Hybrid)",'AMFI-Mar''25 to Mar''26'!$A:$A,0),_xlpm.col+1))),""))} | L28: {=IF($A28="","",IFERROR(_xlfn.LET(_xlpm.lbl,$A28,_xlpm.mm,LEFT(_xlpm.lbl,3),_xlpm.yy,"20"&RIGHT(_xlpm.lbl,2),_xlpm.full,CHOOSE(MATCH(_xlpm.mm,{"Jan";"Feb";"Mar";"Apr";"May";"Jun";"Jul";"Aug";"Sep";"Oct";"Nov";"Dec"},0),"January","February","March","April","May","June","July","August","September","October","November","December")&" "&_xlpm.yy,_xlpm.h,'AMFI-Mar''25 to Mar''26'!$A$3:$ZS$3,_xlpm.c,COLUMN('AMFI-Mar''25 to Mar''26'!$A$3:$ZS$3),_xlpm.hit,_xlfn._xlws.FILTER(_xlpm.c,ISNUMBER(SEARCH("Funds Mobilized for the month of "&_xlpm.full,_xlpm.h))),_xlpm.col,IFERROR(INDEX(_xlpm.hit,1),0),IF(_xlpm.col=0,"",INDEX('AMFI-Mar''25 to Mar''26'!$1:$1048576,MATCH("Total for Active Equity (incl Hybrid)",'AMFI-Mar''25 to Mar''26'!$A:$A,0),_xlpm.col))),""))} | M28: {=IF($A28="","",IFERROR(_xlfn.LET(_xlpm.lbl,$A28,_xlpm.mm,LEFT(_xlpm.lbl,3),_xlpm.yy,"20"&RIGHT(_xlpm.lbl,2),_xlpm.full,CHOOSE(MATCH(_xlpm.mm,{"Jan";"Feb";"Mar";"Apr";"May";"Jun";"Jul";"Aug";"Sep";"Oct";"Nov";"Dec"},0),"January","February","March","April","May","June","July","August","September","October","November","December")&" "&_xlpm.yy,_xlpm.h,'AMFI-Mar''25 to Mar''26'!$A$3:$ZS$3,_xlpm.c,COLUMN('AMFI-Mar''25 to Mar''26'!$A$3:$ZS$3),_xlpm.hit,_xlfn._xlws.FILTER(_xlpm.c,ISNUMBER(SEARCH("Repurchase/ Redemption for the month of "&_xlpm.full,_xlpm.h))+ISNUMBER(SEARCH("Repurchase/Redemption for the month of "&_xlpm.full,_xlpm.h))+ISNUMBER(SEARCH("Redemption for the month of "&_xlpm.full,_xlpm.h))),_xlpm.col,IFERROR(INDEX(_xlpm.hit,1),0),IF(_xlpm.col=0,"",INDEX('AMFI-Mar''25 to Mar''26'!$1:$1048576,MATCH("Total for Active Equity (incl Hybrid)",'AMFI-Mar''25 to Mar''26'!$A:$A,0),_xlpm.col))),""))} | N28: =IF($I28="","",IFERROR(L28-M28,"")) | P28: =IF(OR($A28="",N($B28)=0),"",$A28) | Q28: =IF(OR($A28="",N($B28)=0),"",$B28)
A29: {=_xlfn.LET(_xlpm.m,'AMFI-Mar''25 to Mar''26'!$A$2:$AAG$2,_xlpm.h,'AMFI-Mar''25 to Mar''26'!$A$3:$AAG$3,_xlpm.cond,(_xlpm.m<>"")*(_xlpm.m<>"-")*ISNUMBER(SEARCH("'",_xlpm.m))*ISERROR(SEARCH(" to ",_xlpm.m)),_xlpm.labels,_xlfn._xlws.FILTER(_xlpm.m,_xlpm.cond),_xlpm.hdrs,_xlfn._xlws.FILTER(_xlpm.h,_xlpm.cond),_xlpm.idx,ROW()-ROW($A$28)+1,_xlpm.n,COLUMNS(_xlpm.labels),_xlpm.x,IF(_xlpm.idx<=MIN(13,_xlpm.n),INDEX(_xlpm.labels,1,_xlpm.idx+MAX(0,_xlpm.n-13)),""),_xlpm.hx,IF(_xlpm.idx<=MIN(13,_xlpm.n),INDEX(_xlpm.hdrs,1,_xlpm.idx+MAX(0,_xlpm.n-13)),""),IF(_xlpm.x="","",IF(ISNUMBER(SEARCH("No. of Schemes as on",_xlpm.hx)),LOOKUP(2,1/ISNUMBER(SEARCH({"January","February","March","April","May","June","July","August","September","October","November","December"},_xlpm.hx)),{"Jan","Feb","Mar","Apr","May","Jun","Jul","Aug","Sep","Oct","Nov","Dec"})&"'"&RIGHT(MID(_xlpm.hx,FIND(", ",_xlpm.hx)+2,4),2),_xlpm.x)))} | B29: {=IF($A29="","",IFERROR(_xlfn.LET(_xlpm.lbl,$A29,_xlpm.mm,LEFT(_xlpm.lbl,3),_xlpm.yy,"20"&RIGHT(_xlpm.lbl,2),_xlpm.full,CHOOSE(MATCH(_xlpm.mm,{"Jan";"Feb";"Mar";"Apr";"May";"Jun";"Jul";"Aug";"Sep";"Oct";"Nov";"Dec"},0),"January","February","March","April","May","June","July","August","September","October","November","December")&" ",_xlpm.h,'AMFI-Mar''25 to Mar''26'!$A$3:$AAG$3,_xlpm.c,COLUMN('AMFI-Mar''25 to Mar''26'!$A$3:$AAG$3),_xlpm.hit,_xlfn._xlws.FILTER(_xlpm.c,ISNUMBER(SEARCH("Net Assets Under Management as on",_xlpm.h))*ISNUMBER(SEARCH(_xlpm.full&"*"&_xlpm.yy,_xlpm.h))),_xlpm.col,IFERROR(INDEX(_xlpm.hit,1),0),_xlpm.colf,IF(_xlpm.col=0,IFERROR(MATCH(_xlpm.lbl,'AMFI-Mar''25 to Mar''26'!$A$2:$AAG$2,0)+5,0),_xlpm.col),IF(_xlpm.colf=0,NA(),INDEX('AMFI-Mar''25 to Mar''26'!$1:$1048576,MATCH("Grand Total",'AMFI-Mar''25 to Mar''26'!$A:$A,0),_xlpm.colf))),""))} | C29: {=IF($A29="","",IFERROR(_xlfn.LET(_xlpm.lbl,$A29,_xlpm.mm,LEFT(_xlpm.lbl,3),_xlpm.yy,"20"&RIGHT(_xlpm.lbl,2),_xlpm.full,CHOOSE(MATCH(_xlpm.mm,{"Jan";"Feb";"Mar";"Apr";"May";"Jun";"Jul";"Aug";"Sep";"Oct";"Nov";"Dec"},0),"January","February","March","April","May","June","July","August","September","October","November","December")&" ",_xlpm.h,'AMFI-Mar''25 to Mar''26'!$A$3:$AAG$3,_xlpm.c,COLUMN('AMFI-Mar''25 to Mar''26'!$A$3:$AAG$3),_xlpm.hit,_xlfn._xlws.FILTER(_xlpm.c,ISNUMBER(SEARCH("Net Assets Under Management as on",_xlpm.h))*ISNUMBER(SEARCH(_xlpm.full&"*"&_xlpm.yy,_xlpm.h))),_xlpm.col,IFERROR(INDEX(_xlpm.hit,1),0),_xlpm.colf,IF(_xlpm.col=0,IFERROR(MATCH(_xlpm.lbl,'AMFI-Mar''25 to Mar''26'!$A$2:$AAG$2,0)+5,0),_xlpm.col),IF(_xlpm.colf=0,NA(),INDEX('AMFI-Mar''25 to Mar''26'!$1:$1048576,MATCH("Grand Total",'AMFI-Mar''25 to Mar''26'!$A:$A,0),_xlpm.colf+1))),""))} | D29: {=IF($A29="","",IFERROR(_xlfn.LET(_xlpm.lbl,$A29,_xlpm.mm,LEFT(_xlpm.lbl,3),_xlpm.yy,"20"&RIGHT(_xlpm.lbl,2),_xlpm.full,CHOOSE(MATCH(_xlpm.mm,{"Jan";"Feb";"Mar";"Apr";"May";"Jun";"Jul";"Aug";"Sep";"Oct";"Nov";"Dec"},0),"January","February","March","April","May","June","July","August","September","October","November","December")&" "&_xlpm.yy,_xlpm.h,'AMFI-Mar''25 to Mar''26'!$A$3:$AAG$3,_xlpm.c,COLUMN('AMFI-Mar''25 to Mar''26'!$A$3:$AAG$3),_xlpm.hit,_xlfn._xlws.FILTER(_xlpm.c,ISNUMBER(SEARCH("Funds Mobilized for the month of "&_xlpm.full,_xlpm.h))),_xlpm.col,IFERROR(INDEX(_xlpm.hit,1),0),IF(_xlpm.col=0,"",INDEX('AMFI-Mar''25 to Mar''26'!$1:$1048576,MATCH("Grand Total",'AMFI-Mar''25 to Mar''26'!$A:$A,0),_xlpm.col))),""))} | E29: {=IF($A29="","",IFERROR(_xlfn.LET(_xlpm.lbl,$A29,_xlpm.mm,LEFT(_xlpm.lbl,3),_xlpm.yy,"20"&RIGHT(_xlpm.lbl,2),_xlpm.full,CHOOSE(MATCH(_xlpm.mm,{"Jan";"Feb";"Mar";"Apr";"May";"Jun";"Jul";"Aug";"Sep";"Oct";"Nov";"Dec"},0),"January","February","March","April","May","June","July","August","September","October","November","December")&" "&_xlpm.yy,_xlpm.h,'AMFI-Mar''25 to Mar''26'!$A$3:$AAG$3,_xlpm.c,COLUMN('AMFI-Mar''25 to Mar''26'!$A$3:$AAG$3),_xlpm.hit,_xlfn._xlws.FILTER(_xlpm.c,ISNUMBER(SEARCH("Repurchase/Redemption for the month of "&_xlpm.full,_xlpm.h))+ISNUMBER(SEARCH("Redemption for the month of "&_xlpm.full,_xlpm.h))),_xlpm.col,IFERROR(INDEX(_xlpm.hit,1),0),IF(_xlpm.col=0,"",INDEX('AMFI-Mar''25 to Mar''26'!$1:$1048576,MATCH("Grand Total",'AMFI-Mar''25 to Mar''26'!$A:$A,0),_xlpm.col))),""))} | F29: =IF($A29="","",IFERROR(D29-E29,"")) | I29: =$A29 | J29: {=IF($A29="","",IFERROR(_xlfn.LET(_xlpm.lbl,$A29,_xlpm.mm,LEFT(_xlpm.lbl,3),_xlpm.yy,"20"&RIGHT(_xlpm.lbl,2),_xlpm.full,CHOOSE(MATCH(_xlpm.mm,{"Jan";"Feb";"Mar";"Apr";"May";"Jun";"Jul";"Aug";"Sep";"Oct";"Nov";"Dec"},0),"January","February","March","April","May","June","July","August","September","October","November","December")&" ",_xlpm.h,'AMFI-Mar''25 to Mar''26'!$A$3:$ZS$3,_xlpm.c,COLUMN('AMFI-Mar''25 to Mar''26'!$A$3:$ZS$3),_xlpm.hit,_xlfn._xlws.FILTER(_xlpm.c,ISNUMBER(SEARCH("Net Assets Under Management as on",_xlpm.h))*ISNUMBER(SEARCH(_xlpm.full&"*"&_xlpm.yy,_xlpm.h))),_xlpm.col,IFERROR(INDEX(_xlpm.hit,1),0),IF(_xlpm.col=0,"",INDEX('AMFI-Mar''25 to Mar''26'!$1:$1048576,MATCH("Total for Active Equity (incl Hybrid)",'AMFI-Mar''25 to Mar''26'!$A:$A,0),_xlpm.col))),""))} | K29: {=IF($A29="","",IFERROR(_xlfn.LET(_xlpm.lbl,$A29,_xlpm.mm,LEFT(_xlpm.lbl,3),_xlpm.yy,"20"&RIGHT(_xlpm.lbl,2),_xlpm.full,CHOOSE(MATCH(_xlpm.mm,{"Jan";"Feb";"Mar";"Apr";"May";"Jun";"Jul";"Aug";"Sep";"Oct";"Nov";"Dec"},0),"January","February","March","April","May","June","July","August","September","October","November","December")&" ",_xlpm.h,'AMFI-Mar''25 to Mar''26'!$A$3:$ZS$3,_xlpm.c,COLUMN('AMFI-Mar''25 to Mar''26'!$A$3:$ZS$3),_xlpm.hit,_xlfn._xlws.FILTER(_xlpm.c,ISNUMBER(SEARCH("Net Assets Under Management as on",_xlpm.h))*ISNUMBER(SEARCH(_xlpm.full&"*"&_xlpm.yy,_xlpm.h))),_xlpm.col,IFERROR(INDEX(_xlpm.hit,1),0),IF(_xlpm.col=0,"",INDEX('AMFI-Mar''25 to Mar''26'!$1:$1048576,MATCH("Total for Active Equity (incl Hybrid)",'AMFI-Mar''25 to Mar''26'!$A:$A,0),_xlpm.col+1))),""))} | L29: {=IF($A29="","",IFERROR(_xlfn.LET(_xlpm.lbl,$A29,_xlpm.mm,LEFT(_xlpm.lbl,3),_xlpm.yy,"20"&RIGHT(_xlpm.lbl,2),_xlpm.full,CHOOSE(MATCH(_xlpm.mm,{"Jan";"Feb";"Mar";"Apr";"May";"Jun";"Jul";"Aug";"Sep";"Oct";"Nov";"Dec"},0),"January","February","March","April","May","June","July","August","September","October","November","December")&" "&_xlpm.yy,_xlpm.h,'AMFI-Mar''25 to Mar''26'!$A$3:$ZS$3,_xlpm.c,COLUMN('AMFI-Mar''25 to Mar''26'!$A$3:$ZS$3),_xlpm.hit,_xlfn._xlws.FILTER(_xlpm.c,ISNUMBER(SEARCH("Funds Mobilized for the month of "&_xlpm.full,_xlpm.h))),_xlpm.col,IFERROR(INDEX(_xlpm.hit,1),0),IF(_xlpm.col=0,"",INDEX('AMFI-Mar''25 to Mar''26'!$1:$1048576,MATCH("Total for Active Equity (incl Hybrid)",'AMFI-Mar''25 to Mar''26'!$A:$A,0),_xlpm.col))),""))} | M29: {=IF($A29="","",IFERROR(_xlfn.LET(_xlpm.lbl,$A29,_xlpm.mm,LEFT(_xlpm.lbl,3),_xlpm.yy,"20"&RIGHT(_xlpm.lbl,2),_xlpm.full,CHOOSE(MATCH(_xlpm.mm,{"Jan";"Feb";"Mar";"Apr";"May";"Jun";"Jul";"Aug";"Sep";"Oct";"Nov";"Dec"},0),"January","February","March","April","May","June","July","August","September","October","November","December")&" "&_xlpm.yy,_xlpm.h,'AMFI-Mar''25 to Mar''26'!$A$3:$ZS$3,_xlpm.c,COLUMN('AMFI-Mar''25 to Mar''26'!$A$3:$ZS$3),_xlpm.hit,_xlfn._xlws.FILTER(_xlpm.c,ISNUMBER(SEARCH("Repurchase/ Redemption for the month of "&_xlpm.full,_xlpm.h))+ISNUMBER(SEARCH("Repurchase/Redemption for the month of "&_xlpm.full,_xlpm.h))+ISNUMBER(SEARCH("Redemption for the month of "&_xlpm.full,_xlpm.h))),_xlpm.col,IFERROR(INDEX(_xlpm.hit,1),0),IF(_xlpm.col=0,"",INDEX('AMFI-Mar''25 to Mar''26'!$1:$1048576,MATCH("Total for Active Equity (incl Hybrid)",'AMFI-Mar''25 to Mar''26'!$A:$A,0),_xlpm.col))),""))} | N29: =IF($I29="","",IFERROR(L29-M29,"")) | P29: =IF(OR($A29="",N($B29)=0),"",$A29) | Q29: =IF(OR($A29="",N($B29)=0),"",$B29)
